Workbook

Sheet How to Solve
A1: This describes the model notes.
A4: MODEL SOLUTION
A5: 1. Note that we have designed the runs so that a file named "Rice_{date}.xlsm" is the file in which the assumptions are
A6: embedded. This allows a common set of assumptions for all variants.
A7: Note that this uses the Baseline with damages as the calibration for utility and units.
A9: 2. The major controls are at the top of the "Controls" sheet. You can do the following:
A11: a. For the baseline, set as follows, and make sure that the "Global carbon price" in row 9 is set to .001. This is >0 to prevent numerical problems.
A12: Control = 1 if tax or 0 if capped | I12: 1
A13: Trade (0) or no trade (1) | I13: 1
A15: Be careful not to override the if statement that starts around 2150.
A16: b. For the optimal run, you need to optimize with solver. You can get a starting point by copying the "tentative optimal prices" from row 84 of "Controls" sheet.
A17: Make sure the settings at the top are:
A18: Control = 1 if tax or 0 if capped | I18: 1
A19: Trade (0) or no trade (1) | I19: 1
A22: c. For the Copenhagen runs, we set the top controls at:
A23: Control = 1 if tax or 0 if capped | D23: 1
A24: If you want FULL trading, set the second row as:
A25: Trade (0) or no trade (1) | D25: 0
A26: Note: The full trade requires optimization. You need to minimize the error in the "Global" spreadsheet at entry B115.
A27: This is done by adjusting the carbon prices for trading in row 118. This is very tricky and is best accomplished by moving slowly from left to right.
A29: d. If you want NO trading, set the second row as:
A30: Trade (0) or no trade (1) | D30: 1
A31: Note: This is calculated directly and needs no further calculations.
A33: MODEL CHANGES
A34: VERY IMPORTANT NOTE FOR USERS:
A35: 3. The model has been calibrated for the current baseline assumptions. In general there will be no problems in changing assumptions
A36: about POLICIES. However, if you change the baseline, you may run in to all kinds of calibration problems.
A37: The problems will require only modest adjustments for the baseline, optimal, and limit runs.
A38: However, the calibration for the Copenhagen runs is complicated, and users are advised that changes in these runs
A39: are likely to introduce errors.
A41: 4. The main changes that are necessary if you make parameter changes is that you will need to RENORMALIZE THE BASELINE RUN.A64
A42: Procedures for this are described below. Make sure that the renormalization is for the Baseline. DO NOT renormalize the
A43: policy runs; rather use the renormalization for the baseline as the normalization for other runs.
A45: NORMALIZATIONS AND INITIALIZATIONS
... A133: 14. Note that the utility and consumption discount rates are as follows for US, China, and India for the base case
B134: 2015 | C134: 2005-2055 | D134: 2005-2105
A135: Model real rates
A136: Utility rates | E136: 2005 | F136: 2015 | G136: 2025 | H136: 2035 | I136: 2045 | J136: 2055 | K136: 2065 | L136: 2075 | M136: 2085 | N136: 2095 | O136: 2105 | P136: 2115
A137: US | B137: 0.046980023 | C137: 0.043355523 | D137: 0.032182676 | F137: 0.046980023 | G137: 0.047203002 | H137: 0.041644592 | I137: 0.037594477 | J137: 0.034485311 | K137: 0.032592476 | L137: 0.031458552 | M137: 0.030553561 | N137: 0.029746124 | O137: 0.028848234 | P137: 0.027041372
A138: China | B138: 0.11343412 | C138: 0.068386495 | D138: 0.037861577 | F138: 0.11343412 | G138: 0.061657543 | H138: 0.05260098 | I138: 0.045853336 | J138: 0.041762666 | K138: 0.039374227 | L138: 0.037081845 | M138: 0.034525088 | N138: 0.032984987 | O138: 0.033448893 | P138: 0.034101759
A139: India | B139: 0.096298796 | C139: 0.075764576 | D139: 0.047113243 | F139: 0.096298796 | G139: 0.078202186 | H139: 0.068465564 | I139: 0.060091759 | J139: 0.052787176 | K139: 0.048441285 | L139: 0.045601351 | M139: 0.043101946 | N139: 0.040881298 | O139: 0.038887886 | P139: 0.036788563
A141: 15. Note that the projections of output, emissions, etc. for the baseline are not sensitive to the interest rate assumptions. However, the
A142: optimal carbon tax is sensitive (as has been seen repeatedly in the discounting debates).
A144: 16. The "Diag" sheet is diagnostics to evaluate the major results for countries.
A146: 17. Notes on the Copenhagen runs:
A147: a. The "Copenhagen rich only" scenario has only the participation of the high-income countries. These are US, EU, Japan, OHI, Russia.
A149: b. For Copenhagen runs, you go to the "Copen" sheet, lines 160-171. You then set the participation date for the non-participating countries at the
A150: date at which it is assumed they participate. In these runs, the date in 2150.
A151: For example, for China, set the value in cell W165 at 2150, and then China is unconstrained until that date.
A152: Note that these assume trading, so it requires some calibration as above.
A154: c. It is possible to have alternative configuations of participants. For example, you can exclude all developing countries. This requires changing
A155: participation rates. This is done by changing the assumptions box in Copen sheet at lines 159-171. For example, if India is not to participate,
A156: set the entry date at 2150.
... A172: If this assumption is changed, some of the "IF" statements may need to be changed, so be careful.

Sheet Results
B1: 2005 | C1: 2015 | D1: 2025 | E1: 2035 | F1: 2045 | G1: 2055 | H1: 2065 | I1: 2075 | J1: 2085 | K1: 2095 | L1: 2105 | M1: 2115 | N1: 2125 | O1: 2135 | P1: 2145 | Q1: 2155 | R1: 2165 | S1: 2175 | T1: 2185 | U1: 2195 | V1: 2205 | W1: 2215 | X1: 2225 | Y1: 2235 | Z1: 2245 | AA1: 2255 | AB1: 2265 | AC1: 2275 | AD1: 2285 | AE1: 2295 | AF1: 2305 | AG1: 2315 | AH1: 2325 | AI1: 2335 | AJ1: 2345 | AK1: 2355 | AL1: 2365 | AM1: 2375 | AN1: 2385 | AO1: 2395 | AP1: 2405 | AQ1: 2415 | AR1: 2425 | AS1: 2435 | AT1: 2445 | AU1: 2455 | AV1: 2465 | AW1: 2475 | AX1: 2485 | AY1: 2495 | AZ1: 2505 | BA1: 2515 | BB1: 2525 | BC1: 2535 | BD1: 2545 | BE1: 2555 | BF1: 2565 | BG1: 2575 | BH1: 2585 | BI1: 2595 | BJ1: 2605 | BK1: 2615 | BL1: 2625 | BM1: 2635 | BN1: 2645 | BO1: 2655 | BP1: 2665 | BQ1: 2675 | BR1: 2685 | BS1: 2695 | BT1: 2705 | BU1: 2715 | BV1: 2725 | BW1: 2735 | BX1: 2745 | BY1: 2755 | BZ1: 2765 | CA1: 2775 | CB1: 2785 | CC1: 2795 | CD1: 2805 | CE1: 2815 | CF1: 2825 | CG1: 2835 | CH1: 2845 | CI1: 2855 | CJ1: 2865 | CK1: 2875 | CL1: 2885 | CM1: 2895 | CN1: 2905 | CO1: 2915 | CP1: 2925 | CQ1: 2935 | CR1: 2945 | CS1: 2955 | CT1: 2965 | CU1: 2975 | CV1: 2985 | CW1: 2995 | CX1: 3005 | CY1: 3015
B2: 0.001
A3: base utility | B3: =+Controls!B4 -> 2301.518
A4: add emissions
A5: Total carbon emissions (GTC per year) | B5: =SUM(US:OthAsia!B70)+B4 -> 9.5676364 | C5: =SUM(US:OthAsia!C70)+C4 -> 11.283554 | D5: =SUM(US:OthAsia!D70)+D4 -> 12.742375 | E5: =SUM(US:OthAsia!E70)+E4 -> 13.997138 | F5: =SUM(US:OthAsia!F70)+F4 -> 15.097383 | G5: =SUM(US:OthAsia!G70)+G4 -> 15.959184 | H5: =SUM(US:OthAsia!H70)+H4 -> 16.704702 | I5: =SUM(US:OthAsia!I70)+I4 -> 17.457585 | ... BI5: =SUM(US:OthAsia!BI70)+BI4 -> 3.0649911e-06
A6: Base utility value | B6: 1753.4878
A7: New delta utility value | B7: 1753.4876 | C7: 1753.4876 | D7: 1753.4877 | E7: 1753.4877 | F7: 1753.4877 | G7: 1753.4877 | L7: 1753.4878
A8: Correction factor | B8: 0.98484913 | C8: 1.028416 | D8: 1.1148742 | E8: 0.68942855 | F8: 0.75831031 | G8: 0.83100581 | L8: 0.866
A9: Utility discount rate | B9: =+Global!B366 -> 1 | C9: =+Global!C366 -> 0.56467664 | D9: =+Global!D366 -> 0.32827176 | E9: =+Global!F366 -> 0.12755891 | F9: =+Global!G366 -> 0.083386464 | G9: =+Global!H366 -> 0.055946662 | H9: =+Global!I366 -> 0.038321989 | I9: =+Global!J366 -> 0.026723173 | J9: =+Global!K366 -> 0.018945339 | K9: =+Global!L366 -> 0.013654215 | L9: =+Global!M366 -> 0.010096491 | ... BH9: =+Global!BI366 -> 0 | BI9: =+Global!#REF! -> #REF!
A10: PV change | B10: =100000*($B6-B7)/B9 -> 17.753654 | C10: =100000*($B6-C7)/C9 -> 28.993156 | D10: =100000*($B6-D7)/D9 -> 37.351038 | E10: =100000*($B6-E7)/E9 -> 72.282425 | F10: =100000*($B6-F7)/F9 -> 83.596518 | G10: =100000*($B6-G7)/G9 -> 94.902587 | L10: =100000*($B6-L7)/L9 -> 149.24869
A11: PV corrected | B11: =+B10*B8 -> 17.484671 | C11: =+C10*C8 -> 29.817026 | D11: =+D10*D8 -> 41.641708 | E11: =+E10*E8 -> 49.833567 | F11: =+F10*F8 -> 63.392101 | G11: =+G10*G8 -> 78.864602 | L11: =+L10*L8 -> 129.24937
A12: From tax estimates (base case) | B12: 17.48467 | C12: 32.86382 | D12: 48.723172 | E12: 68.744445 | F12: 93.800861 | G12: 124.48185 | H12: 161.24872 | I12: 204.68798 | J12: 254.94894 | K12: 311.87486 | L12: 374.22828 | M12: 831.12188
A13: From analytical | B13: =+Global!B378 -> 38.667086 | C13: =+Global!C378 -> 68.47651 | D13: =+Global!D378 -> 113.71469 | E13: =+Global!E378 -> 170.37783 | F13: =+Global!F378 -> 230.74967 | G13: =+Global!G378 -> 295.12026
A14: Run | B14: =+C14+1 -> 1004 | C14: 1003
A15: Rate of social time preference (% py) | F15: =+IF(D10>70,1,"")
A16: Elasticity of MU of consumption (set) | F16: Error from correction factor | I16: =+SUMPRODUCT(F17:K17*F17:K17) -> 0.34477945
A17: Damage coefficient on temperature | B17: =NORMINV(RAND(),0,1) -> -0.1393038 | C17: 1.3244487 | F17: =+B11/B12-1 -> 2.0491439e-08 | G17: =+C11/C12-1 -> -0.092709651 | H17: =+D11/D12-1 -> -0.14534078 | I17: =+E11/E12-1 -> -0.27508954 | J17: =+F11/F12-1 -> -0.32418423 | K17: =+G11/G12-1 -> -0.36645704
A18: Damage coefficient on temperature squared | B18: =NORMINV(RAND(),0,1) -> 1.6161299 | C18: 0.37069644 | F18: [need to estimate optimal taxes to use this]
A19: Exponent on damages | B19: =NORMINV(RAND(),0,1) -> -0.26279453 | C19: 0.25897881 | F19: =+B12/B10 -> 0.98484911 | G19: =+C12/C10 -> 1.1335027 | H19: =+D12/D10 -> 1.3044664 | I19: =+E12/E10 -> 0.95105339 | J19: =+F12/F10 -> 1.1220666 | K19: =+G12/G10 -> 1.3116803 | P19: =+L12/L10 -> 2.5074141
A20: Price backstop technology (2005 US 000 $ per tC) | B20: =NORMINV(RAND(),0,1) -> 0.30282431 | C20: -1.1981161 | E20: T(2200) | F20: =+Z62 -> 6.466549
A21: Exponent of control cost function | B21: =NORMINV(RAND(),0,1) -> -0.1650027 | C21: 0.43330179 | E21: SLR(2500) | F21: =+BB77 -> 7.7009348
A22: Backstop inflection year | B22: =NORMINV(RAND(),0,1) -> 1.1218685 | C22: 1.6502441
A23: Maximum carbon resources (GtC) | B23: =NORMINV(RAND(),0,1) -> 0.16622682 | C23: 0.55269204
A24: Equilibrium temperature increase for CO2 doubling | B24: =NORMINV(RAND(),0,1) -> -0.56548631 | C24: -0.091249155
A25: Decline rate TFP (per decade) | B25: =NORMINV(RAND(),0,1) -> -0.51388316 | C25: -1.7407395
A26: TFP convergence rate (per decade) | B26: =NORMINV(RAND(),0,1) -> 2.3301223 | C26: -0.42879277
A27: Long run growth rate (per year) | B27: =NORMINV(RAND(),0,1) -> -0.33463247 | C27: 1.9653861
A28: Decline rate sigma growth (per decade) | B28: =NORMINV(RAND(),0,1) -> -0.81814271 | C28: -1.0779841
A29: Trend sigma growth (per year) | B29: =NORMINV(RAND(),0,1) -> 2.0741159 | C29: 0.46847076
A30: Uncertainty for frontier (US) TFP | B30: =NORMINV(RAND(),0,1) -> 1.1571671 | C30: -1.0454297
A31: Adjustment rates for SLR (multiplicative) | B31: =NORMINV(RAND(),0,1) -> -1.6299691 | C31: 0.35346622
A32: Random threshold temperature for melt SLR (m) | B32: =NORMINV(RAND(),0,1) -> -2.2812446 | C32: -0.75943163
A33: Population adjustment (factor for 2200) | B33: =NORMINV(RAND(),0,1) -> -0.20131174 | C33: 1.0994498
... A36: Convergence uncertainty | B36: =NORMINV(RAND(),0,1) -> 0.74771639 | C36: 1.0148936
A37: dummy
A38: dummy
S40: =+Parameters!B22 -> 0.1
B42: =+Parameters!A9 -> Rate of social time preference (% py) | C42: =+Parameters!A10 -> Elasticity of MU of consumption (set) | D42: =+Parameters!A11 -> Damage coefficient on temperature | E42: =+Parameters!A12 -> Damage coefficient on temperature squared | F42: =+Parameters!A13 -> Exponent on damages | G42: =+Parameters!A14 -> Price backstop technology (2005 US 000 $ per tC) | H42: =+Parameters!A15 -> Exponent of control cost function | I42: =+Parameters!A16 -> Backstop inflection year | J42: =+Parameters!A17 -> Maximum carbon resources (GtC) | K42: =+Parameters!A18 -> Equilibrium temperature increase for CO2 doubling | L42: =+Parameters!A19 -> Decline rate TFP (per decade) | M42: =+Parameters!A20 -> TFP convergence rate (per decade) | N42: =+Parameters!A21 -> Long run growth rate (per year) | O42: =+Parameters!A22 -> Decline rate sigma growth (per decade) | P42: =+Parameters!A23 -> Trend sigma growth (per year) | Q42: =+Parameters!A24 -> Uncertainty for frontier (US) TFP | R42: =+Parameters!A25 -> Adjustment rates for SLR (multiplicative) | S42: =+Parameters!A26 -> Random threshold temperature for melt SLR (m) | T42: =+Parameters!A27 -> Population uncertainty (factor for 2200) | U42: =+Parameters!A28 -> Carbon cycle adjustment coefficient | V42: =+Parameters!A29 -> Damage rate at threshold for catastrophic damages | W42: =+Parameters!A30 -> Convergence uncertainty
B43: 2005 | C43: =+B43+10 -> 2015 | D43: =+C43+10 -> 2025 | E43: =+D43+10 -> 2035 | F43: =+E43+10 -> 2045 | G43: =+F43+10 -> 2055 | H43: =+G43+10 -> 2065 | I43: =+H43+10 -> 2075 | J43: =+I43+10 -> 2085 | ... CY43: =+CX43+10 -> 3015
A44: Parameters of uncertain variables | B44: =+Parameters!B9 -> 0.015 | C44: =+Parameters!B10 -> 1.5 | D44: =+Parameters!B11 -> 0.0017543802 | E44: =+Parameters!B12 -> 0.0022592108 | F44: =+Parameters!B13 -> 2 | G44: =+Parameters!B14 -> 1.2 | H44: =+Parameters!B15 -> 2.8 | I44: =+Parameters!B16 -> 2250 | J44: =+Parameters!B17 -> 6000 | K44: =+Parameters!B18 -> 3.2 | L44: =+Parameters!B19 -> 0.1 | M44: =+Parameters!B20 -> 0.1 | N44: =+Parameters!B21 -> 0.0033 | O44: =+Parameters!B22 -> 0.1 | P44: =+Parameters!B23 -> -0.0025 | Q44: =+Parameters!B24 -> 0 | R44: =+Parameters!B25 -> 1 | S44: =+Parameters!B26 -> 0 | T44: =+Parameters!B27 -> 1 | U44: =+Parameters!B28 -> 12 | V44: =+Parameters!B29 -> 0 | W44: =+Parameters!B30 -> 0
A45: =+Global!A34 -> Population (millions) | B45: =+Global!B34 -> 6410.8916 | C45: =+Global!C34 -> 7182.9956 | D45: =+Global!D34 -> 7868.2303 | E45: =+Global!E34 -> 8397.5753 | F45: =+Global!F34 -> 8788.5837 | G45: =+Global!G34 -> 8922.3414 | H45: =+Global!H34 -> 8924.7181 | ... BI45: =+Global!BI34 -> 8699.4589
A46: Aarun number | B46: =+B14 -> 1004
A47: =+Global!A42 -> Climate damages ($ trillions per year) | B47: =+Global!B42 -> 0.087272389 | C47: =+Global!C42 -> 0.24561446 | D47: =+Global!D42 -> 0.50434772 | E47: =+Global!E42 -> 0.9639029 | F47: =+Global!F42 -> 1.7012513 | G47: =+Global!G42 -> 2.7733273 | H47: =+Global!H42 -> 4.2503015 | ... BI47: =+Global!BI42 -> 1789.0854
A48: =+Global!A45 -> Abatement cost ($ trillion) | B48: =+Global!B45 -> 1.2013016e-09 | C48: =+Global!C45 -> 1.570166e-09 | D48: =+Global!D45 -> 1.8775042e-09 | E48: =+Global!E45 -> 2.1535366e-09 | F48: =+Global!F45 -> 2.4072811e-09 | G48: =+Global!G45 -> 2.625465e-09 | H48: =+Global!H45 -> 2.8287052e-09 | ... BI48: =+Global!BI45 -> 1.7901176e-10
A49: =+Global!A46 -> Gross output (net of damages and abatement, $trill p.a.) | B49: =+Global!B46 -> 55.291673 | C49: =+Global!C46 -> 81.029789 | D49: =+Global!D46 -> 111.80514 | E49: =+Global!E46 -> 146.52832 | F49: =+Global!F46 -> 184.98432 | G49: =+Global!G46 -> 225.24466 | H49: =+Global!H46 -> 267.74895 | ... BI49: =+Global!BI46 -> 3779.2481
A50: =+Global!A48 -> Consumption ($trill per year) | B50: =+Global!B48 -> 43.426253 | C50: =+Global!C48 -> 63.059116 | D50: =+Global!D48 -> 87.530538 | E50: =+Global!E48 -> 115.24055 | F50: =+Global!F48 -> 146.09796 | G50: =+Global!G48 -> 178.03781 | H50: =+Global!H48 -> 211.27524 | ... BI50: =+Global!BI48 -> 2869.9655
A51: =+Global!A49 -> Net capital accumulation ($trill per year) | B51: =+Global!B49 -> 3.437964 | C51: =+Global!C49 -> 5.5247448 | D51: =+Global!D49 -> 8.0316116 | E51: =+Global!E49 -> 9.1043752 | F51: =+Global!F49 -> 10.187679 | G51: =+Global!G49 -> 11.150814 | H51: =+Global!H49 -> 12.208533 | ... BI51: =+Global!BI49 -> 27.591348
A52: =+Global!A51 -> NET NATIONAL INCOME (Consumption basis) | B52: =+Global!B51 -> 46.864217 | C52: =+Global!C51 -> 68.583861 | D52: =+Global!D51 -> 95.562149 | E52: =+Global!E51 -> 124.34492 | F52: =+Global!F51 -> 156.28564 | G52: =+Global!G51 -> 189.18862 | H52: =+Global!H51 -> 223.48377 | ... BI52: =+Global!BI51 -> 2897.5569
A53: =+Global!A52 -> World per capita consumption | B53: =+Global!B52 -> 6.7738242 | C53: =+Global!C52 -> 8.778944 | D53: =+Global!D52 -> 11.124552 | E53: =+Global!E52 -> 13.723074 | F53: =+Global!F52 -> 16.623607 | G53: =+Global!G52 -> 19.954158 | H53: =+Global!H52 -> 23.673043 | ... BI53: =+Global!BI52 -> 329.90161
A54: =+Global!A53 -> World gross savings rate | B54: =+Global!B53 -> 0.21459688 | C54: =+Global!C53 -> 0.2217786 | D54: =+Global!D53 -> 0.21711523 | E54: =+Global!E53 -> 0.21352716 | F54: =+Global!F53 -> 0.21021439 | G54: =+Global!G53 -> 0.20958034 | H54: =+Global!H53 -> 0.21092039 | ... BI54: =+Global!BI53 -> 0.24059882
A55: =+Results!A5 -> Total carbon emissions (GTC per year) | B55: =+Results!B5 -> 9.5676364 | C55: =+Results!C5 -> 11.283554 | D55: =+Results!D5 -> 12.742375 | E55: =+Results!E5 -> 13.997138 | F55: =+Results!F5 -> 15.097383 | G55: =+Results!G5 -> 15.959184 | H55: =+Results!H5 -> 16.704702 | ... BI55: =+Results!BI5 -> 3.0649911e-06
A56: =+Global!A56 -> Industrial emissions (GTC per year) | B56: =+Global!B56 -> 7.9676364 | C56: =+Global!C56 -> 10.003554 | D56: =+Global!D56 -> 11.718375 | E56: =+Global!E56 -> 13.177938 | F56: =+Global!F56 -> 14.442023 | G56: =+Global!G56 -> 15.434896 | H56: =+Global!H56 -> 16.285272 | ... BI56: =+Global!BI56 -> 0
A57: =+Global!A57 -> World emissions intensity (sigma) | B57: =+Global!B57 -> 0.14387483 | C57: =+Global!C57 -> 0.12308218 | D57: =+Global!D57 -> 0.10434003 | E57: =+Global!E57 -> 0.089346661 | F57: =+Global!F57 -> 0.077360143 | G57: =+Global!G57 -> 0.06769157 | H57: =+Global!H57 -> 0.059872488 | ... BI57: =+Global!BI57 -> 0
A58: =+Global!A60 -> Atmospheric concentration of carbon (ppm) | B58: =+Global!B60 -> 369.48357 | C58: =+Global!C60 -> 389.20188 | D58: =+Global!D60 -> 431.21991 | E58: =+Global!E60 -> 475.54717 | F58: =+Global!F60 -> 521.15956 | G58: =+Global!G60 -> 567.39053 | H58: =+Global!H60 -> 613.25567 | ... BI58: =+Global!BI60 -> 931.97855
A59: =+Global!A61 -> Concentration in biosphere and upper oceans (GTC) | B59: =+Global!B61 -> 1600 | C59: =+Global!C61 -> 1618.6835 | D59: =+Global!D61 -> 1641.4351 | E59: =+Global!E61 -> 1673.7429 | F59: =+Global!F61 -> 1715.7 | G59: =+Global!G61 -> 1767.1329 | H59: =+Global!H61 -> 1827.7066 | ... BI59: =+Global!BI61 -> 4952.9915
A60: =+Global!A62 -> Concentration in deep oceans (GTC) | B60: =+Global!B62 -> 10010 | C60: =+Global!C62 -> 10010.493 | D60: =+Global!D62 -> 10011.078 | E60: =+Global!E62 -> 10011.777 | F60: =+Global!F62 -> 10012.637 | G60: =+Global!G62 -> 10013.706 | H60: =+Global!H62 -> 10015.031 | ... BI60: =+Global!BI62 -> 10713.66
A61: =+Global!A64 -> Cumulative Emissions to date | B61: =+Global!B64 -> 79.676364 | C61: =+Global!C64 -> 179.7119 | D61: =+Global!D64 -> 296.89566 | E61: =+Global!E64 -> 428.67504 | F61: =+Global!F64 -> 573.09527 | G61: =+Global!G64 -> 727.44422 | H61: =+Global!H64 -> 890.29694 | ... BI61: =+Global!BI64 -> 5209.2665
A62: =+Global!A70 -> Atmospheric temperature (degrees Celsius above preindustrial) | B62: =+Global!B70 -> 0.83 | C62: =+Global!C70 -> 0.98 | D62: =+Global!D70 -> 1.2299073 | E62: =+Global!E70 -> 1.5203062 | F62: =+Global!F70 -> 1.8319126 | G62: =+Global!G70 -> 2.1509718 | H62: =+Global!H70 -> 2.4680618 | ... BI62: =+Global!BI70 -> 5.7417772
A63: =+Global!A71 -> Total increase in radiative forcing since preindustrial (Watts per square meter) | B63: =+Global!B71 -> 1.6046851 | C63: =+Global!C71 -> 2.0695681 | D63: =+Global!D71 -> 2.6541597 | E63: =+Global!E71 -> 3.2086205 | F63: =+Global!F71 -> 3.7278544 | G63: =+Global!G71 -> 4.2090963 | H63: =+Global!H71 -> 4.6524319 | ... BI63: =+Global!BI71 -> 6.8852861
A64: =+Global!A72 -> Lower ocean temperature (degrees Celsius above preindustrial) | B64: =+Global!B72 -> 0.0068 | C64: =+Global!C72 -> 0.04796 | D64: =+Global!D72 -> 0.094562 | E64: =+Global!E72 -> 0.15132926 | F64: =+Global!F72 -> 0.21977811 | G64: =+Global!G72 -> 0.30038484 | H64: =+Global!H72 -> 0.39291419 | ... BI64: =+Global!BI72 -> 5.4711426
A65: =+Global!A77 -> Sum of utilities (international weights) | B65: =+Global!B77 -> 2301.518
A66: =+Global!A81 -> Backstop price (US) | B66: =+Global!B81 -> 1134 | C66: =+Global!C81 -> 1082.97 | D66: =+Global!D81 -> 1034.4915 | E66: =+Global!E81 -> 988.43692 | F66: =+Global!F81 -> 944.68508 | G66: =+Global!G81 -> 903.12082 | H66: =+Global!H81 -> 863.63478 | ... BI66: =+Global!BI81 -> 1.1973432e-08
A67: =+Global!A82 -> Backstop price (wt average) | B67: =+Global!B82 -> 1259.2275 | C67: =+Global!C82 -> 1202.5622 | D67: =+Global!D82 -> 1148.7303 | E67: =+Global!E82 -> 1097.5899 | F67: =+Global!F82 -> 1049.0065 | G67: =+Global!G82 -> 1002.8523 | H67: =+Global!H82 -> 959.00585 | ... BI67: =+Global!BI82 -> 228.41764
A68: =+Global!A41 -> 0 | B68: =+Global!B41 -> 0 | C68: =+Global!C41 -> 0 | D68: =+Global!D41 -> 0 | E68: =+Global!E41 -> 0 | F68: =+Global!F41 -> 0 | G68: =+Global!G41 -> 0 | H68: =+Global!H41 -> 0 | ... BI68: =+Global!BI41 -> 0
A69: =+US!A134 -> Discount rate t to t+1, US | B69: =+US!B134 -> 0 | C69: =+US!C134 -> 0.034628474 | D69: =+US!D134 -> 0.043789667 | E69: =+US!E134 -> 0.039073996 | F69: =+US!F134 -> 0.036131766 | G69: =+US!G134 -> 0.034138949 | H69: =+US!H134 -> 0.032264582 | ... AO69: =+US!AO134 -> 0.020092078
A70: =+US!A131 -> Ramsey (average), US | B70: =+US!B131 -> 0 | C70: =+US!C131 -> 0.047048399 | D70: =+US!D131 -> 0.047408022 | E70: =+US!E131 -> 0.042062233 | F70: =+US!F131 -> 0.038033383 | G70: =+US!G131 -> 0.03467765 | H70: =+US!H131 -> 0.032493935 | ... AO70: =+US!AO131 -> 0.019966686
A71: =+China!A134 -> Discount rate t to t+1, China | B71: =+China!B134 -> 0 | C71: =+China!C134 -> 0.16613249 | D71: =+China!D134 -> 0.064807169 | E71: =+China!E134 -> 0.057401253 | F71: =+China!F134 -> 0.052048257 | G71: =+China!G134 -> 0.047738902 | H71: =+China!H134 -> 0.044897091 | ... AO71: =+China!AO134 -> 0.015951917
A72: =+China!A131 -> Ramsey (average), China | B72: =+China!B131 -> 0 | C72: =+China!C131 -> 0.11345366 | D72: =+China!D131 -> 0.061737165 | E72: =+China!E131 -> 0.052943858 | F72: =+China!F131 -> 0.046393285 | G72: =+China!G131 -> 0.04208064 | H72: =+China!H131 -> 0.039327339 | ... AQ72: =+China!AQ131 -> 0.01548635
A73: SCC (analytical) | B73: =+Global!B378 -> 38.667086 | C73: =+Global!C378 -> 68.47651 | D73: =+Global!D378 -> 113.71469 | E73: =+Global!E378 -> 170.37783 | F73: =+Global!F378 -> 230.74967 | G73: =+Global!G378 -> 295.12026 | L73: =+Global!L378 -> 640.26818
A74: SCC (delta utility estimation) | B74: =+B11 -> 17.484671 | C74: =+C11 -> 29.817026 | D74: =+D11 -> 41.641708 | E74: =+E11 -> 49.833567 | F74: =+F11 -> 63.392101 | G74: =+G11 -> 78.864602
A75: =+Global!A132 -> Thermal expansion | B75: =+Global!B132 -> 0.099841682 | C75: =+Global!C132 -> 0.10923519 | D75: =+Global!D132 -> 0.12141094 | E75: =+Global!E132 -> 0.13678938 | F75: =+Global!F132 -> 0.15554872 | G75: =+Global!G132 -> 0.17769725 | H75: =+Global!H132 -> 0.20312969 | ... BI75: =+Global!BI132 -> 2.1498154 | BJ75: =+Global!BJ77 -> 2.1663465 | BK75: =+Global!BK77 -> 2.1818834 | BL75: =+Global!BL77 -> 2.196608 | BM75: =+Global!BM77 -> 2.2106466 | BN75: =+Global!BN77 -> 2.224088 | BO75: =+Global!BO77 -> 2.2369952 | BP75: =+Global!BP77 -> 2.2494139 | BQ75: =+Global!BQ77 -> 2.2613779 | ... CY75: =+Global!CY77 -> 2.4794866
A76: =+Global!A134 -> TE, G&SIC, GIS | B76: =+Global!B134 -> 0.12048168 | C76: =+Global!C134 -> 0.14327374 | D76: =+Global!D134 -> 0.18421248 | E76: =+Global!E134 -> 0.23320727 | F76: =+Global!F134 -> 0.29056178 | G76: =+Global!G134 -> 0.35606789 | H76: =+Global!H134 -> 0.42920291 | ... BI76: =+Global!BI134 -> 5.3868142 | BJ76: =+Global!BJ79 -> 5.4444781 | BK76: =+Global!BK79 -> 5.5004314 | BL76: =+Global!BL79 -> 5.5549541 | BM76: =+Global!BM79 -> 5.6082401 | BN76: =+Global!BN79 -> 5.6604246 | BO76: =+Global!BO79 -> 5.7116038 | BP76: =+Global!BP79 -> 5.7618468 | BQ76: =+Global!BQ79 -> 5.8112046 | ... CY76: =+Global!CY79 -> 7.0878393
A77: =+Global!A135 -> TE, G&SIC, GIS. AIS | B77: =+Global!B135 -> 0.12170662 | C77: =+Global!C135 -> 0.14455281 | D77: =+Global!D135 -> 0.1835951 | E77: =+Global!E135 -> 0.22842677 | F77: =+Global!F135 -> 0.279186 | G77: =+Global!G135 -> 0.33560647 | H77: =+Global!H135 -> 0.39718088 | ... BI77: =+Global!BI135 -> 8.5853782 | BJ77: =+Global!BJ80 -> 8.7046246 | BK77: =+Global!BK80 -> 8.8210582 | BL77: =+Global!BL80 -> 8.9352511 | BM77: =+Global!BM80 -> 9.0475946 | BN77: =+Global!BN80 -> 9.1583573 | BO77: =+Global!BO80 -> 9.2677254 | BP77: =+Global!BP80 -> 9.3758287 | BQ77: =+Global!BQ80 -> 9.482759 | ... CY77: =+Global!CY80 -> 12.585917
A78: =+Global!A408 -> pop wtd MU | B78: =+Global!B408 -> 288.77288 | C78: =+Global!C408 -> 147.71502 | D78: =+Global!D408 -> 85.63681 | E78: =+Global!E408 -> 53.479593 | F78: =+Global!F408 -> 34.894268 | G78: =+Global!G408 -> 23.756616 | H78: =+Global!H408 -> 16.858024 | ... AF78: =+Global!AF408 -> 0.6116165
A79: =+Global!A409 -> st dev MU/mean | B79: =+Global!B409 -> 1.3584127 | C79: =+Global!C409 -> 1.3665313 | D79: =+Global!D409 -> 1.2948451 | E79: =+Global!E409 -> 1.2245791 | F79: =+Global!F409 -> 1.1471273 | G79: =+Global!G409 -> 1.0778941 | H79: =+Global!H409 -> 1.0218218 | ... AF79: =+Global!AF409 -> 0.57814905
A80: =+Global!A410 -> max/min MUC | B80: =+Global!B410 -> 154.40195 | C80: =+Global!C410 -> 100.89208 | D80: =+Global!D410 -> 72.369231 | E80: =+Global!E410 -> 53.732063 | F80: =+Global!F410 -> 40.435633 | G80: =+Global!G410 -> 31.641966 | H80: =+Global!H410 -> 25.791319 | ... AF80: =+Global!AF410 -> 5.9861865
A81: mean MU | B81: =+Global!B411 -> 179.20419 | C81: =+Global!C411 -> 93.59902 | D81: =+Global!D411 -> 53.111 | E81: =+Global!E411 -> 32.674664 | F81: =+Global!F411 -> 21.178227 | G81: =+Global!G411 -> 14.478833 | H81: =+Global!H411 -> 10.373911 | I81: =+Global!I411 -> 7.6905931 | ... AF81: =+Global!AF411 -> 0.45269489

Sheet Controls
A1: OBJECTIVE FUNCTION TO BE MAXIMIZED | C1: Control = 1 if tax or 0 if capped | I1: 1
A2: Welfare with International Weights | C2: Trade (0) or no trade (1) | I2: 1
A4: Sum of utilities (trillions of 2005 US$) | B4: =SUM(US:OthAsia!B95) -> 2301.518 | C4: 2301.518 | D4: =+B4-C4 -> 0
B5: 1 | C5: 2 | D5: 3 | E5: 4 | F5: 5 | G5: 6 | H5: 7 | I5: 8 | J5: 9 | K5: 10 | L5: 11 | M5: 12 | N5: 13 | O5: 14 | P5: 15 | Q5: 16 | R5: 17 | S5: 18 | T5: 19 | U5: 20 | V5: 21 | W5: 22 | X5: 23 | Y5: 24 | Z5: 25 | AA5: 26 | AB5: 27 | AC5: 28 | AD5: 29 | AE5: 30 | AF5: 31 | AG5: 32 | AH5: 33 | AI5: 34 | AJ5: 35 | AK5: 36 | AL5: 37 | AM5: 38 | AN5: 39 | AO5: 40 | AP5: 41 | AQ5: 42 | AR5: 43 | AS5: 44 | AT5: 45 | AU5: 46 | AV5: 47 | AW5: 48 | AX5: 49 | AY5: 50 | AZ5: 51 | BA5: 52 | BB5: 53 | BC5: 54 | BD5: 55 | BE5: 56 | BF5: 57 | BG5: 58 | BH5: 59 | BI5: 60
B6: 2005 | C6: 2015 | D6: 2025 | E6: 2035 | F6: 2045 | G6: 2055 | H6: 2065 | I6: 2075 | J6: 2085 | K6: 2095 | L6: 2105 | M6: 2115 | N6: 2125 | O6: 2135 | P6: 2145 | Q6: 2155 | R6: 2165 | S6: 2175 | T6: 2185 | U6: 2195 | V6: 2205 | W6: 2215 | X6: 2225 | Y6: 2235 | Z6: 2245 | AA6: 2255 | AB6: 2265 | AC6: 2275 | AD6: 2285 | AE6: 2295 | AF6: 2305 | AG6: 2315 | AH6: 2325 | AI6: 2335 | AJ6: 2345 | AK6: 2355 | AL6: 2365 | AM6: 2375 | AN6: 2385 | AO6: 2395 | AP6: 2405 | AQ6: 2415 | AR6: 2425 | AS6: 2435 | AT6: 2445 | AU6: 2455 | AV6: 2465 | AW6: 2475 | AX6: 2485 | AY6: 2495 | AZ6: 2505 | BA6: 2515 | BB6: 2525 | BC6: 2535 | BD6: 2545 | BE6: 2555 | BF6: 2565 | BG6: 2575 | BH6: 2585 | BI6: 2595
A7: CARBON TAX CONTROL VARIABLE | C7: 0
A8: Carbon tax (2005 US$ per ton C) | B8: =+B9+B10 -> 0.001 | C8: =+C9+C10 -> 0.001 | D8: =+D9+D10 -> 0.001 | E8: =+E9+E10 -> 0.001 | F8: =+F9+F10 -> 0.001 | G8: =+G9+G10 -> 0.0010000001 | H8: =+H9+H10 -> 0.001000001 | I8: =+I9+I10 -> 0.0010000114 | ... Z8: =+Z9+Z10 -> 5.6313005 | AA8: =+MIN(AA9+AA10,Global!AA81) -> 10.591311 | AB8: =+MIN(AB9+AB10,Global!AB81) -> 102.851 | AC8: =+MIN(AC9+AC10,Global!AC81) -> 51.4255 | AD8: =+MIN(AD9+AD10,Global!AD81) -> 25.71275 | AE8: =+MIN(AE9+AE10,Global!AE81) -> 12.856375 | AF8: =+MIN(AF9+AF10,Global!AF81) -> 6.4281875 | AG8: =+MIN(AG9+AG10,Global!AG81) -> 3.2140937 | AH8: =+MIN(AH9+AH10,Global!AH81) -> 1.6070469 | ... BI8: =+MIN(BI9+BI10,Global!BI81) -> 1.1973432e-08
A9: Carbon tax for Hotelling rents | B9: 0 | C9: =+Global!C84 -> 3.0070389e-21 | D9: =+Global!D84 -> 5.2132334e-17 | E9: =+Global!E84 -> 2.15492e-14 | F9: =+Global!F84 -> 1.7689817e-12 | G9: =+Global!G84 -> 5.7664278e-11 | H9: =+Global!H84 -> 1.008745e-09 | I9: =+Global!I84 -> 1.1392095e-08 | J9: =+Global!J84 -> 9.4039466e-08 | ... BI9: =+Global!BI84 -> 18.344415
A10: GLOBAL | B10: 0.001 | C10: 0.001 | D10: 0.001 | E10: 0.001 | F10: 0.001 | G10: 0.001 | H10: 0.001 | I10: 0.001 | J10: 0.001 | K10: 0.001 | L10: 0.001 | M10: 0.001 | N10: 0.001 | O10: 0.001 | P10: 0.001 | Q10: 0.001 | R10: 0.001 | S10: 0.001 | T10: 0.001 | U10: 0.001 | V10: 0.001 | W10: 0.001 | X10: 0.001 | Y10: 0.001 | Z10: 0.001 | AA10: 0.001 | AB10: 1200 | AC10: 1200 | AD10: 1200 | AE10: 1200 | AF10: 1200 | AG10: 1200 | AH10: 1200 | AI10: 1200 | AJ10: 1200 | AK10: 1200 | AL10: 1200 | AM10: 1200 | AN10: 1200 | AO10: 1200 | AP10: 1200 | AQ10: 1200 | AR10: 1200 | AS10: 1200 | AT10: 1200 | AU10: 1200 | AV10: 1200 | AW10: 1200 | AX10: 1200 | AY10: 1200 | AZ10: 1200 | BA10: 1200 | BB10: 1200 | BC10: 1200 | BD10: 1200 | BE10: 1200 | BF10: 1200 | BG10: 1200 | BH10: 1200 | BI10: 1200
A11: US | B11: =+B$10 -> 0.001 | C11: =+C$10 -> 0.001 | D11: =+D$10 -> 0.001 | E11: =+E$10 -> 0.001 | F11: =+F$10 -> 0.001 | G11: =+G$10 -> 0.001 | H11: =+H$10 -> 0.001 | I11: =+I$10 -> 0.001 | ... BI11: =+BI$10 -> 1200
A12: EU | B12: =+B$10 -> 0.001 | C12: =+C$10 -> 0.001 | D12: =+D$10 -> 0.001 | E12: =+E$10 -> 0.001 | F12: =+F$10 -> 0.001 | G12: =+G$10 -> 0.001 | H12: =+H$10 -> 0.001 | I12: =+I$10 -> 0.001 | ... BI12: =+BI$10 -> 1200
A13: Japan | B13: =+B$10 -> 0.001 | C13: =+C$10 -> 0.001 | D13: =+D$10 -> 0.001 | E13: =+E$10 -> 0.001 | F13: =+F$10 -> 0.001 | G13: =+G$10 -> 0.001 | H13: =+H$10 -> 0.001 | I13: =+I$10 -> 0.001 | ... BI13: =+BI$10 -> 1200
A14: Russia | B14: =+B$10 -> 0.001 | C14: =+C$10 -> 0.001 | D14: =+D$10 -> 0.001 | E14: =+E$10 -> 0.001 | F14: =+F$10 -> 0.001 | G14: =+G$10 -> 0.001 | H14: =+H$10 -> 0.001 | I14: =+I$10 -> 0.001 | ... BI14: =+BI$10 -> 1200
A15: Eurasia | B15: =+B$10 -> 0.001 | C15: =+C$10 -> 0.001 | D15: =+D$10 -> 0.001 | E15: =+E$10 -> 0.001 | F15: =+F$10 -> 0.001 | G15: =+G$10 -> 0.001 | H15: =+H$10 -> 0.001 | I15: =+I$10 -> 0.001 | ... BI15: =+BI$10 -> 1200
A16: China | B16: =+B$10 -> 0.001 | C16: =+C$10 -> 0.001 | D16: =+D$10 -> 0.001 | E16: =+E$10 -> 0.001 | F16: =+F$10 -> 0.001 | G16: =+G$10 -> 0.001 | H16: =+H$10 -> 0.001 | I16: =+I$10 -> 0.001 | ... BI16: =+BI$10 -> 1200
A17: India | B17: =+B$10 -> 0.001 | C17: =+C$10 -> 0.001 | D17: =+D$10 -> 0.001 | E17: =+E$10 -> 0.001 | F17: =+F$10 -> 0.001 | G17: =+G$10 -> 0.001 | H17: =+H$10 -> 0.001 | I17: =+I$10 -> 0.001 | ... BI17: =+BI$10 -> 1200
A18: Middle East | B18: =+B$10 -> 0.001 | C18: =+C$10 -> 0.001 | D18: =+D$10 -> 0.001 | E18: =+E$10 -> 0.001 | F18: =+F$10 -> 0.001 | G18: =+G$10 -> 0.001 | H18: =+H$10 -> 0.001 | I18: =+I$10 -> 0.001 | ... BI18: =+BI$10 -> 1200
A19: Africa | B19: =+B$10 -> 0.001 | C19: =+C$10 -> 0.001 | D19: =+D$10 -> 0.001 | E19: =+E$10 -> 0.001 | F19: =+F$10 -> 0.001 | G19: =+G$10 -> 0.001 | H19: =+H$10 -> 0.001 | I19: =+I$10 -> 0.001 | ... BI19: =+BI$10 -> 1200
A20: Latin America | B20: =+B$10 -> 0.001 | C20: =+C$10 -> 0.001 | D20: =+D$10 -> 0.001 | E20: =+E$10 -> 0.001 | F20: =+F$10 -> 0.001 | G20: =+G$10 -> 0.001 | H20: =+H$10 -> 0.001 | I20: =+I$10 -> 0.001 | ... BI20: =+BI$10 -> 1200
A21: OHI | B21: =+B$10 -> 0.001 | C21: =+C$10 -> 0.001 | D21: =+D$10 -> 0.001 | E21: =+E$10 -> 0.001 | F21: =+F$10 -> 0.001 | G21: =+G$10 -> 0.001 | H21: =+H$10 -> 0.001 | I21: =+I$10 -> 0.001 | ... BI21: =+BI$10 -> 1200
A22: Other | B22: =+B$10 -> 0.001 | C22: =+C$10 -> 0.001 | D22: =+D$10 -> 0.001 | E22: =+E$10 -> 0.001 | F22: =+F$10 -> 0.001 | G22: =+G$10 -> 0.001 | H22: =+H$10 -> 0.001 | I22: =+I$10 -> 0.001 | ... BI22: =+BI$10 -> 1200
A23: Emissions wtd tax | B23: =+SUMPRODUCT(Controls!B11:B22*Data!$C$89:$C$100)/SUM(Data!$C$89:$C$100) -> 0.001 | C23: =+SUMPRODUCT(Controls!C11:C22*Data!$C$89:$C$100)/SUM(Data!$C$89:$C$100) -> 0.001 | D23: =+SUMPRODUCT(Controls!D11:D22*Data!$C$89:$C$100)/SUM(Data!$C$89:$C$100) -> 0.001 | E23: =+SUMPRODUCT(Controls!E11:E22*Data!$C$89:$C$100)/SUM(Data!$C$89:$C$100) -> 0.001 | F23: =+SUMPRODUCT(Controls!F11:F22*Data!$C$89:$C$100)/SUM(Data!$C$89:$C$100) -> 0.001 | G23: =+SUMPRODUCT(Controls!G11:G22*Data!$C$89:$C$100)/SUM(Data!$C$89:$C$100) -> 0.001 | H23: =+SUMPRODUCT(Controls!H11:H22*Data!$C$89:$C$100)/SUM(Data!$C$89:$C$100) -> 0.001 | I23: =+SUMPRODUCT(Controls!I11:I22*Data!$C$89:$C$100)/SUM(Data!$C$89:$C$100) -> 0.001 | ... M23: =+SUMPRODUCT(Controls!M11:M22*Data!$C$89:$C$100)/SUM(Data!$C$89:$C$100) -> 0.001
A24: Note: The GLOBAL figure is control variable for optimal runs.
B26: 2005 | C26: 2015 | D26: 2025 | E26: 2035 | F26: 2045 | G26: 2055 | H26: 2065 | I26: 2075 | J26: 2085 | K26: 2095 | L26: 2105 | M26: 2115 | N26: 2125 | O26: 2135 | P26: 2145 | Q26: 2155 | R26: 2165 | S26: 2175 | T26: 2185 | U26: 2195 | V26: 2205 | W26: 2215 | X26: 2225 | Y26: 2235 | Z26: 2245 | AA26: 2255 | AB26: 2265 | AC26: 2275 | AD26: 2285 | AE26: 2295 | AF26: 2305 | AG26: 2315 | AH26: 2325 | AI26: 2335 | AJ26: 2345 | AK26: 2355 | AL26: 2365 | AM26: 2375 | AN26: 2385 | AO26: 2395 | AP26: 2405 | AQ26: 2415 | AR26: 2425 | AS26: 2435 | AT26: 2445 | AU26: 2455 | AV26: 2465 | AW26: 2475 | AX26: 2485 | AY26: 2495 | AZ26: 2505 | BA26: 2515 | BB26: 2525 | BC26: 2535 | BD26: 2545 | BE26: 2555 | BF26: 2565 | BG26: 2575 | BH26: 2585 | BI26: 2595
A27: SAVINGS RATE | B27: 0.17851792 | C27: 0.20440907 | D27: 0.20081284 | E27: 0.19862437 | F27: 0.19724537 | G27: 0.19749783 | H27: 0.19980406
A28: US | B28: 0.17851792 | C28: 0.20441169 | D28: 0.20081131 | E28: 0.19862348 | F28: 0.19724518 | G28: 0.19749773 | H28: 0.19978659 | I28: 0.20224864 | J28: 0.20500133 | K28: 0.20701315 | L28: 0.20687069 | M28: 0.22030308 | N28: =+M28 -> 0.22030308 | O28: =+N28 -> 0.22030308 | P28: =+O28 -> 0.22030308 | Q28: =+P28 -> 0.22030308 | R28: =+Q28 -> 0.22030308 | S28: =+R28 -> 0.22030308 | T28: =+S28 -> 0.22030308 | U28: =+T28 -> 0.22030308 | ... BI28: =+BH28 -> 0.22030308
A29: EU | B29: 0.17464279 | C29: 0.19951188 | D29: 0.19621703 | E29: 0.19444765 | F29: 0.1931177 | G29: 0.19342038 | H29: 0.19499882 | I29: 0.19675156 | J29: 0.19867754 | K29: 0.20517685 | L29: 0.21074493 | M29: 0.22033628 | N29: =+M29 -> 0.22033628 | O29: =+N29 -> 0.22033628 | P29: =+O29 -> 0.22033628 | Q29: =+P29 -> 0.22033628 | R29: =+Q29 -> 0.22033628 | S29: =+R29 -> 0.22033628 | T29: =+S29 -> 0.22033628 | U29: =+T29 -> 0.22033628 | ... BI29: =+BH29 -> 0.22033628
A30: Japan | B30: 0.15130517 | C30: 0.1802888 | D30: 0.17561051 | E30: 0.1683494 | F30: 0.17936265 | G30: 0.18715053 | H30: 0.18886752 | I30: 0.19078953 | J30: 0.19299544 | K30: 0.20201478 | L30: 0.20937149 | M30: 0.22226937 | N30: =+M30 -> 0.22226937 | O30: =+N30 -> 0.22226937 | P30: =+O30 -> 0.22226937 | Q30: =+P30 -> 0.22226937 | R30: =+Q30 -> 0.22226937 | S30: =+R30 -> 0.22226937 | T30: =+S30 -> 0.22226937 | U30: =+T30 -> 0.22226937 | ... BI30: =+BH30 -> 0.22226937
A31: Russia | B31: 0.1911687 | C31: 0.18903154 | D31: 0.18513371 | E31: 0.18556387 | F31: 0.18787393 | G31: 0.18989119 | H31: 0.19064813 | I31: 0.1916834 | J31: 0.1930806 | K31: 0.2031348 | L31: 0.21241991 | M31: 0.22223323 | N31: =+M31 -> 0.22223323 | O31: =+N31 -> 0.22223323 | P31: =+O31 -> 0.22223323 | Q31: =+P31 -> 0.22223323 | R31: =+Q31 -> 0.22223323 | S31: =+R31 -> 0.22223323 | T31: =+S31 -> 0.22223323 | U31: =+T31 -> 0.22223323 | ... BI31: =+BH31 -> 0.22223323
A32: Eurasia | B32: 0.19500684 | C32: 0.22579566 | D32: 0.21818997 | E32: 0.2137652 | F32: 0.21103997 | G32: 0.21054286 | H32: 0.21015163 | I32: 0.21016396 | J32: 0.21067751 | K32: 0.21679425 | L32: 0.22273955 | M32: 0.22890899 | N32: =+M32 -> 0.22890899 | O32: =+N32 -> 0.22890899 | P32: =+O32 -> 0.22890899 | Q32: =+P32 -> 0.22890899 | R32: =+Q32 -> 0.22890899 | S32: =+R32 -> 0.22890899 | T32: =+S32 -> 0.22890899 | U32: =+T32 -> 0.22890899 | ... BI32: =+BH32 -> 0.22890899
A33: China | B33: 0.35708144 | C33: 0.22676101 | D33: 0.21516476 | E33: 0.20754873 | F33: 0.20327969 | G33: 0.20375853 | H33: 0.20342374 | I33: 0.20334247 | J33: 0.2031673 | K33: 0.20922027 | L33: 0.21852012 | M33: 0.21324434 | N33: =+M33 -> 0.21324434 | O33: =+N33 -> 0.21324434 | P33: =+O33 -> 0.21324434 | Q33: =+P33 -> 0.21324434 | R33: =+Q33 -> 0.21324434 | S33: =+R33 -> 0.21324434 | T33: =+S33 -> 0.21324434 | U33: =+T33 -> 0.21324434 | ... BI33: =+BH33 -> 0.21324434
A34: India | B34: 0.29484649 | C34: 0.26865631 | D34: 0.25373354 | E34: 0.24344426 | F34: 0.23218357 | G34: 0.22645882 | H34: 0.22526328 | I34: 0.22454207 | J34: 0.22439286 | K34: 0.22474462 | L34: 0.22572862 | M34: 0.22819109 | N34: =+M34 -> 0.22819109 | O34: =+N34 -> 0.22819109 | P34: =+O34 -> 0.22819109 | Q34: =+P34 -> 0.22819109 | R34: =+Q34 -> 0.22819109 | S34: =+R34 -> 0.22819109 | T34: =+S34 -> 0.22819109 | U34: =+T34 -> 0.22819109 | ... BI34: =+BH34 -> 0.22819109
A35: Middle East | B35: 0.25700191 | C35: 0.25015233 | D35: 0.23912168 | E35: 0.23072693 | F35: 0.22098173 | G35: 0.21762884 | H35: 0.21845421 | I35: 0.21955434 | J35: 0.22101455 | K35: 0.21586229 | L35: 0.20942697 | M35: 0.21875519 | N35: =+M35 -> 0.21875519 | O35: =+N35 -> 0.21875519 | P35: =+O35 -> 0.21875519 | Q35: =+P35 -> 0.21875519 | R35: =+Q35 -> 0.21875519 | S35: =+R35 -> 0.21875519 | T35: =+S35 -> 0.21875519 | U35: =+T35 -> 0.21875519 | ... BI35: =+BH35 -> 0.21875519
A36: Africa | B36: 0.29788861 | C36: 0.30359078 | D36: 0.28874203 | E36: 0.27593629 | F36: 0.2561328 | G36: 0.24401481 | H36: 0.24256581 | I36: 0.24152834 | J36: 0.24092325 | K36: 0.23202159 | L36: 0.22490583 | M36: 0.22378232 | N36: =+M36 -> 0.22378232 | O36: =+N36 -> 0.22378232 | P36: =+O36 -> 0.22378232 | Q36: =+P36 -> 0.22378232 | R36: =+Q36 -> 0.22378232 | S36: =+R36 -> 0.22378232 | T36: =+S36 -> 0.22378232 | U36: =+T36 -> 0.22378232 | ... BI36: =+BH36 -> 0.22378232
A37: Latin America | B37: 0.23570389 | C37: 0.23790902 | D37: 0.2291227 | E37: 0.22069702 | F37: 0.21416108 | G37: 0.21272082 | H37: 0.21309604 | I37: 0.21378594 | J37: 0.21491052 | K37: 0.21680028 | L37: 0.21764557 | M37: 0.22618787 | N37: =+M37 -> 0.22618787 | O37: =+N37 -> 0.22618787 | P37: =+O37 -> 0.22618787 | Q37: =+P37 -> 0.22618787 | R37: =+Q37 -> 0.22618787 | S37: =+R37 -> 0.22618787 | T37: =+S37 -> 0.22618787 | U37: =+T37 -> 0.22618787 | ... BI37: =+BH37 -> 0.22618787
A38: OHI | B38: 0.18690855 | C38: 0.20306632 | D38: 0.19794957 | E38: 0.19302618 | F38: 0.18994992 | G38: 0.18934598 | H38: 0.19102341 | I38: 0.19285652 | J38: 0.19479925 | K38: 0.20167915 | L38: 0.20770716 | M38: 0.2169109 | N38: =+M38 -> 0.2169109 | O38: =+N38 -> 0.2169109 | P38: =+O38 -> 0.2169109 | Q38: =+P38 -> 0.2169109 | R38: =+Q38 -> 0.2169109 | S38: =+R38 -> 0.2169109 | T38: =+S38 -> 0.2169109 | U38: =+T38 -> 0.2169109 | ... BI38: =+BH38 -> 0.2169109
A39: Other | B39: 0.24090678 | C39: 0.27878901 | D39: 0.26593413 | E39: 0.254325 | F39: 0.24142114 | G39: 0.23453135 | H39: 0.23295199 | I39: 0.2318317 | J39: 0.23124471 | K39: 0.22879017 | L39: 0.22945447 | M39: 0.22371271 | N39: =+M39 -> 0.22371271 | O39: =+N39 -> 0.22371271 | P39: =+O39 -> 0.22371271 | Q39: =+P39 -> 0.22371271 | R39: =+Q39 -> 0.22371271 | S39: =+R39 -> 0.22371271 | T39: =+S39 -> 0.22371271 | U39: =+T39 -> 0.22371271 | ... BI39: =+BH39 -> 0.22371271
A41: Note: Shaded values are optimized. First period is given, and later periods are held constant at last period.
B43: 2005 | C43: 2015 | D43: 2025 | E43: 2035 | F43: 2045 | G43: 2055 | H43: 2065 | I43: 2075 | J43: 2085 | K43: 2095 | L43: 2105 | M43: 2115 | N43: 2125 | O43: 2135 | P43: 2145 | Q43: 2155 | R43: 2165 | S43: 2175 | T43: 2185 | U43: 2195 | V43: 2205 | W43: 2215 | X43: 2225 | Y43: 2235 | Z43: 2245 | AA43: 2255 | AB43: 2265 | AC43: 2275 | AD43: 2285 | AE43: 2295 | AF43: 2305 | AG43: 2315 | AH43: 2325 | AI43: 2335 | AJ43: 2345 | AK43: 2355 | AL43: 2365 | AM43: 2375 | AN43: 2385 | AO43: 2395 | AP43: 2405 | AQ43: 2415 | AR43: 2425 | AS43: 2435 | AT43: 2445 | AU43: 2455 | AV43: 2465 | AW43: 2475 | AX43: 2485 | AY43: 2495 | AZ43: 2505 | BA43: 2515 | BB43: 2525 | BC43: 2535 | BD43: 2545 | BE43: 2555 | BF43: 2565 | BG43: 2575 | BH43: 2585 | BI43: 2595
A44: PARTICIPATION RATES
B45: US | C45: EU | D45: Japan | E45: Russia | F45: Eurasia | G45: China | H45: India | I45: Middle East | J45: Africa | K45: Latin America | L45: OHI | M45: Other
A46: Participation rate first year (2015) | B46: 1 | C46: 1 | D46: 1 | E46: 1 | F46: 1 | G46: 1 | H46: 1 | I46: 1 | J46: 1 | K46: 1 | L46: 1 | M46: 1
A47: Year first participation | B47: 2010 | C47: 2010 | D47: 2010 | E47: 2010 | F47: 2010 | G47: 2010 | H47: 2010 | I47: 2010 | J47: 2010 | K47: 2010 | L47: 2010 | M47: 2010
A48: Participation rate 2105 | B48: 1 | C48: 1 | D48: 1 | E48: 1 | F48: 1 | G48: 1 | H48: 1 | I48: 1 | J48: 1 | K48: 1 | L48: 1 | M48: 1
A49: Participation rate 2205 | B49: 1 | C49: 1 | D49: 1 | E49: 1 | F49: 1 | G49: 1 | H49: 1 | I49: 1 | J49: 1 | K49: 1 | L49: 1 | M49: 1
A50: Post-2005 increase rate (per decade) | B50: =+Parameters!F113 -> 0 | C50: =+Parameters!G113 -> 0 | D50: =+Parameters!H113 -> 0 | E50: =+Parameters!I113 -> 0 | F50: =+Parameters!J113 -> 0 | G50: =+Parameters!K113 -> 0 | H50: =+Parameters!L113 -> 0 | I50: =+Parameters!M113 -> 0 | ... M50: =+Parameters!Q113 -> 0
A52: Note on participation: These are exogenous for the runs. However, they are important policy variables and included here.
A54: EMISSIONS CONTROL VARIABLES
A55: Participation rate
A56: US | B56: =+Copen!V70 -> 0 | C56: =+Copen!X70 -> 1 | D56: =+Copen!Z70 -> 1 | E56: =+Copen!AB70 -> 1 | F56: =+Copen!AD70 -> 1 | G56: =+Copen!AF70 -> 1 | H56: =+Copen!AH70 -> 1 | I56: =+Copen!AJ70 -> 1 | J56: =+Copen!AL70 -> 1 | K56: =+Copen!AN70 -> 1 | L56: =+Copen!AP70 -> 1 | M56: =+Copen!AR70 -> 1 | N56: =+Copen!AT70 -> 1 | O56: =+Copen!AV70 -> 1 | P56: =+Copen!AX70 -> 1 | Q56: =+P56 -> 1 | R56: =+Q56 -> 1 | S56: =+R56 -> 1 | T56: =+S56 -> 1 | U56: =+T56 -> 1 | V56: =+U56 -> 1 | W56: =+V56 -> 1 | X56: =+W56 -> 1 | ... BI56: =+BH56 -> 1
A57: EU | B57: =+Copen!V71 -> 0 | C57: =+Copen!X71 -> 1 | D57: =+Copen!Z71 -> 1 | E57: =+Copen!AB71 -> 1 | F57: =+Copen!AD71 -> 1 | G57: =+Copen!AF71 -> 1 | H57: =+Copen!AH71 -> 1 | I57: =+Copen!AJ71 -> 1 | J57: =+Copen!AL71 -> 1 | K57: =+Copen!AN71 -> 1 | L57: =+Copen!AP71 -> 1 | M57: =+Copen!AR71 -> 1 | N57: =+Copen!AT71 -> 1 | O57: =+Copen!AV71 -> 1 | P57: =+Copen!AX71 -> 1 | Q57: =+P57 -> 1 | R57: =+Q57 -> 1 | S57: =+R57 -> 1 | T57: =+S57 -> 1 | U57: =+T57 -> 1 | V57: =+U57 -> 1 | W57: =+V57 -> 1 | X57: =+W57 -> 1 | ... BI57: =+BH57 -> 1
A58: Japan | B58: =+Copen!V72 -> 0 | C58: =+Copen!X72 -> 1 | D58: =+Copen!Z72 -> 1 | E58: =+Copen!AB72 -> 1 | F58: =+Copen!AD72 -> 1 | G58: =+Copen!AF72 -> 1 | H58: =+Copen!AH72 -> 1 | I58: =+Copen!AJ72 -> 1 | J58: =+Copen!AL72 -> 1 | K58: =+Copen!AN72 -> 1 | L58: =+Copen!AP72 -> 1 | M58: =+Copen!AR72 -> 1 | N58: =+Copen!AT72 -> 1 | O58: =+Copen!AV72 -> 1 | P58: =+Copen!AX72 -> 1 | Q58: =+P58 -> 1 | R58: =+Q58 -> 1 | S58: =+R58 -> 1 | T58: =+S58 -> 1 | U58: =+T58 -> 1 | V58: =+U58 -> 1 | W58: =+V58 -> 1 | X58: =+W58 -> 1 | ... BI58: =+BH58 -> 1
A59: Russia | B59: =+Copen!V73 -> 0 | C59: =+Copen!X73 -> 1 | D59: =+Copen!Z73 -> 1 | E59: =+Copen!AB73 -> 1 | F59: =+Copen!AD73 -> 1 | G59: =+Copen!AF73 -> 1 | H59: =+Copen!AH73 -> 1 | I59: =+Copen!AJ73 -> 1 | J59: =+Copen!AL73 -> 1 | K59: =+Copen!AN73 -> 1 | L59: =+Copen!AP73 -> 1 | M59: =+Copen!AR73 -> 1 | N59: =+Copen!AT73 -> 1 | O59: =+Copen!AV73 -> 1 | P59: =+Copen!AX73 -> 1 | Q59: =+P59 -> 1 | R59: =+Q59 -> 1 | S59: =+R59 -> 1 | T59: =+S59 -> 1 | U59: =+T59 -> 1 | V59: =+U59 -> 1 | W59: =+V59 -> 1 | X59: =+W59 -> 1 | ... BI59: =+BH59 -> 1
A60: Eurasia | B60: =+Copen!V74 -> 0 | C60: =+Copen!X74 -> 0 | D60: =+Copen!Z74 -> 1 | E60: =+Copen!AB74 -> 1 | F60: =+Copen!AD74 -> 1 | G60: =+Copen!AF74 -> 1 | H60: =+Copen!AH74 -> 1 | I60: =+Copen!AJ74 -> 1 | J60: =+Copen!AL74 -> 1 | K60: =+Copen!AN74 -> 1 | L60: =+Copen!AP74 -> 1 | M60: =+Copen!AR74 -> 1 | N60: =+Copen!AT74 -> 1 | O60: =+Copen!AV74 -> 1 | P60: =+Copen!AX74 -> 1 | Q60: =+P60 -> 1 | R60: =+Q60 -> 1 | S60: =+R60 -> 1 | T60: =+S60 -> 1 | U60: =+T60 -> 1 | V60: =+U60 -> 1 | W60: =+V60 -> 1 | X60: =+W60 -> 1 | ... BI60: =+BH60 -> 1
A61: China | B61: =+Copen!V75 -> 0 | C61: =+Copen!X75 -> 0 | D61: =+Copen!Z75 -> 0 | E61: =+Copen!AB75 -> 1 | F61: =+Copen!AD75 -> 1 | G61: =+Copen!AF75 -> 1 | H61: =+Copen!AH75 -> 1 | I61: =+Copen!AJ75 -> 1 | J61: =+Copen!AL75 -> 1 | K61: =+Copen!AN75 -> 1 | L61: =+Copen!AP75 -> 1 | M61: =+Copen!AR75 -> 1 | N61: =+Copen!AT75 -> 1 | O61: =+Copen!AV75 -> 1 | P61: =+Copen!AX75 -> 1 | Q61: =+P61 -> 1 | R61: =+Q61 -> 1 | S61: =+R61 -> 1 | T61: =+S61 -> 1 | U61: =+T61 -> 1 | V61: =+U61 -> 1 | W61: =+V61 -> 1 | X61: =+W61 -> 1 | ... BI61: =+BH61 -> 1
A62: India | B62: =+Copen!V76 -> 0 | C62: =+Copen!X76 -> 0 | D62: =+Copen!Z76 -> 0 | E62: =+Copen!AB76 -> 0 | F62: =+Copen!AD76 -> 1 | G62: =+Copen!AF76 -> 1 | H62: =+Copen!AH76 -> 1 | I62: =+Copen!AJ76 -> 1 | J62: =+Copen!AL76 -> 1 | K62: =+Copen!AN76 -> 1 | L62: =+Copen!AP76 -> 1 | M62: =+Copen!AR76 -> 1 | N62: =+Copen!AT76 -> 1 | O62: =+Copen!AV76 -> 1 | P62: =+Copen!AX76 -> 1 | Q62: =+P62 -> 1 | R62: =+Q62 -> 1 | S62: =+R62 -> 1 | T62: =+S62 -> 1 | U62: =+T62 -> 1 | V62: =+U62 -> 1 | W62: =+V62 -> 1 | X62: =+W62 -> 1 | ... BI62: =+BH62 -> 1
A63: Middle East | B63: =+Copen!V77 -> 0 | C63: =+Copen!X77 -> 0 | D63: =+Copen!Z77 -> 0 | E63: =+Copen!AB77 -> 0 | F63: =+Copen!AD77 -> 0 | G63: =+Copen!AF77 -> 1 | H63: =+Copen!AH77 -> 1 | I63: =+Copen!AJ77 -> 1 | J63: =+Copen!AL77 -> 1 | K63: =+Copen!AN77 -> 1 | L63: =+Copen!AP77 -> 1 | M63: =+Copen!AR77 -> 1 | N63: =+Copen!AT77 -> 1 | O63: =+Copen!AV77 -> 1 | P63: =+Copen!AX77 -> 1 | Q63: =+P63 -> 1 | R63: =+Q63 -> 1 | S63: =+R63 -> 1 | T63: =+S63 -> 1 | U63: =+T63 -> 1 | V63: =+U63 -> 1 | W63: =+V63 -> 1 | X63: =+W63 -> 1 | ... BI63: =+BH63 -> 1
A64: Africa | B64: =+Copen!V78 -> 0 | C64: =+Copen!X78 -> 0 | D64: =+Copen!Z78 -> 0 | E64: =+Copen!AB78 -> 0 | F64: =+Copen!AD78 -> 0 | G64: =+Copen!AF78 -> 0 | H64: =+Copen!AH78 -> 0 | I64: =+Copen!AJ78 -> 1 | J64: =+Copen!AL78 -> 1 | K64: =+Copen!AN78 -> 1 | L64: =+Copen!AP78 -> 1 | M64: =+Copen!AR78 -> 1 | N64: =+Copen!AT78 -> 1 | O64: =+Copen!AV78 -> 1 | P64: =+Copen!AX78 -> 1 | Q64: =+P64 -> 1 | R64: =+Q64 -> 1 | S64: =+R64 -> 1 | T64: =+S64 -> 1 | U64: =+T64 -> 1 | V64: =+U64 -> 1 | W64: =+V64 -> 1 | X64: =+W64 -> 1 | ... BI64: =+BH64 -> 1
A65: Latin America | B65: =+Copen!V79 -> 0 | C65: =+Copen!X79 -> 0 | D65: =+Copen!Z79 -> 0 | E65: =+Copen!AB79 -> 1 | F65: =+Copen!AD79 -> 1 | G65: =+Copen!AF79 -> 1 | H65: =+Copen!AH79 -> 1 | I65: =+Copen!AJ79 -> 1 | J65: =+Copen!AL79 -> 1 | K65: =+Copen!AN79 -> 1 | L65: =+Copen!AP79 -> 1 | M65: =+Copen!AR79 -> 1 | N65: =+Copen!AT79 -> 1 | O65: =+Copen!AV79 -> 1 | P65: =+Copen!AX79 -> 1 | Q65: =+P65 -> 1 | R65: =+Q65 -> 1 | S65: =+R65 -> 1 | T65: =+S65 -> 1 | U65: =+T65 -> 1 | V65: =+U65 -> 1 | W65: =+V65 -> 1 | X65: =+W65 -> 1 | ... BI65: =+BH65 -> 1
A66: OHI | B66: =+Copen!V80 -> 0 | C66: =+Copen!X80 -> 1 | D66: =+Copen!Z80 -> 1 | E66: =+Copen!AB80 -> 1 | F66: =+Copen!AD80 -> 1 | G66: =+Copen!AF80 -> 1 | H66: =+Copen!AH80 -> 1 | I66: =+Copen!AJ80 -> 1 | J66: =+Copen!AL80 -> 1 | K66: =+Copen!AN80 -> 1 | L66: =+Copen!AP80 -> 1 | M66: =+Copen!AR80 -> 1 | N66: =+Copen!AT80 -> 1 | O66: =+Copen!AV80 -> 1 | P66: =+Copen!AX80 -> 1 | Q66: =+P66 -> 1 | R66: =+Q66 -> 1 | S66: =+R66 -> 1 | T66: =+S66 -> 1 | U66: =+T66 -> 1 | V66: =+U66 -> 1 | W66: =+V66 -> 1 | X66: =+W66 -> 1 | ... BI66: =+BH66 -> 1
A67: Other | B67: =+Copen!V81 -> 0 | C67: =+Copen!X81 -> 0 | D67: =+Copen!Z81 -> 0 | E67: =+Copen!AB81 -> 0 | F67: =+Copen!AD81 -> 1 | G67: =+Copen!AF81 -> 1 | H67: =+Copen!AH81 -> 1 | I67: =+Copen!AJ81 -> 1 | J67: =+Copen!AL81 -> 1 | K67: =+Copen!AN81 -> 1 | L67: =+Copen!AP81 -> 1 | M67: =+Copen!AR81 -> 1 | N67: =+Copen!AT81 -> 1 | O67: =+Copen!AV81 -> 1 | P67: =+Copen!AX81 -> 1 | Q67: =+P67 -> 1 | R67: =+Q67 -> 1 | S67: =+R67 -> 1 | T67: =+S67 -> 1 | U67: =+T67 -> 1 | V67: =+U67 -> 1 | W67: =+V67 -> 1 | X67: =+W67 -> 1 | ... BI67: =+BH67 -> 1
A69: =+Copen!A101 -> Emission cap (actual if non-capped)
A70: US | B70: =+Copen!R102 -> 1.6621335 | C70: =+Copen!X102 -> 1.3842794 | D70: =+Copen!Z102 -> 1.3529484 | E70: =+Copen!AB102 -> 1.0650405 | F70: =+Copen!AD102 -> 0.76569264 | G70: =+Copen!AF102 -> 0.53914316 | H70: =+Copen!AH102 -> 0.4379853 | I70: =+Copen!AJ102 -> 0.3630689 | J70: =+Copen!AL102 -> 0.30766153 | K70: =+Copen!AN102 -> 0.26664261 | L70: =+Copen!AP102 -> 0.23748629 | M70: =+Copen!AR102 -> 0.21433138 | N70: =+Copen!AT102 -> 0.19343407 | O70: =+Copen!AV102 -> 0.17457425 | P70: =+Copen!AX102 -> 0.15755326 | Q70: =+Copen!AZ102 -> 0.14219182 | R70: =+Copen!BB102 -> 0.12832811 | S70: =+Copen!BD102 -> 0.11581612 | T70: =+Copen!BF102 -> 0.10452405 | U70: =+Copen!BH102 -> 0.094332956 | V70: =+Copen!BJ102 -> 0.085135493 | W70: =+Copen!BK102 -> 0.080878718 | X70: =+Copen!BL102 -> 0.076834782 | Y70: =+Copen!BM102 -> 0.072993043 | Z70: =+Copen!BN102 -> 0.069343391 | AA70: =+Copen!BO102 -> 0.065876221 | AB70: =+Copen!BP102 -> 0.06258241 | AC70: =+Copen!BQ102 -> 0.05945329 | ... BI70: =+Copen!CW102 -> 0.011516785
A71: EU | B71: =+Copen!R103 -> 1.1460506 | C71: =+Copen!X103 -> 1.0537535 | D71: =+Copen!Z103 -> 0.90645465 | E71: =+Copen!AB103 -> 0.80990097 | F71: =+Copen!AD103 -> 0.58226444 | G71: =+Copen!AF103 -> 0.40998682 | H71: =+Copen!AH103 -> 0.33306219 | I71: =+Copen!AJ103 -> 0.27609265 | J71: =+Copen!AL103 -> 0.23395859 | K71: =+Copen!AN103 -> 0.2027661 | L71: =+Copen!AP103 -> 0.18059443 | M71: =+Copen!AR103 -> 0.16298647 | N71: =+Copen!AT103 -> 0.14709529 | O71: =+Copen!AV103 -> 0.1327535 | P71: =+Copen!AX103 -> 0.11981003 | Q71: =+Copen!AZ103 -> 0.10812856 | R71: =+Copen!BB103 -> 0.097586021 | S71: =+Copen!BD103 -> 0.088071384 | T71: =+Copen!BF103 -> 0.079484424 | U71: =+Copen!BH103 -> 0.071734693 | V71: =+Copen!BJ103 -> 0.06474056 | W71: =+Copen!BK103 -> 0.061503532 | X71: =+Copen!BL103 -> 0.058428356 | Y71: =+Copen!BM103 -> 0.055506938 | Z71: =+Copen!BN103 -> 0.052731591 | AA71: =+Copen!BO103 -> 0.050095011 | AB71: =+Copen!BP103 -> 0.047590261 | AC71: =+Copen!BQ103 -> 0.045210748 | ... BI71: =+Copen!CW103 -> 0.0087578411
A72: Japan | B72: =+Copen!R104 -> 0.36996593 | C72: =+Copen!X104 -> 0.27014967 | D72: =+Copen!Z104 -> 0.26403525 | E72: =+Copen!AB104 -> 0.20784845 | F72: =+Copen!AD104 -> 0.14942909 | G72: =+Copen!AF104 -> 0.10521672 | H72: =+Copen!AH104 -> 0.085475217 | I72: =+Copen!AJ104 -> 0.070854873 | J72: =+Copen!AL104 -> 0.060041824 | K72: =+Copen!AN104 -> 0.052036759 | L72: =+Copen!AP104 -> 0.046346744 | M72: =+Copen!AR104 -> 0.041827936 | N72: =+Copen!AT104 -> 0.037749712 | O72: =+Copen!AV104 -> 0.034069115 | P72: =+Copen!AX104 -> 0.030747377 | Q72: =+Copen!AZ104 -> 0.027749507 | R72: =+Copen!BB104 -> 0.02504393 | S72: =+Copen!BD104 -> 0.022602147 | T72: =+Copen!BF104 -> 0.020398438 | U72: =+Copen!BH104 -> 0.01840959 | V72: =+Copen!BJ104 -> 0.016614655 | W72: =+Copen!BK104 -> 0.015783922 | X72: =+Copen!BL104 -> 0.014994726 | Y72: =+Copen!BM104 -> 0.01424499 | Z72: =+Copen!BN104 -> 0.01353274 | AA72: =+Copen!BO104 -> 0.012856103 | AB72: =+Copen!BP104 -> 0.012213298 | AC72: =+Copen!BQ104 -> 0.011602633 | ... BI72: =+Copen!CW104 -> 0.0022475633
A73: Russia | B73: =+Copen!R105 -> 0.43123618 | C73: =+Copen!X105 -> 0.65 | D73: =+Copen!Z105 -> 0.62712759 | E73: =+Copen!AB105 -> 0.4936746 | F73: =+Copen!AD105 -> 0.35491891 | G73: =+Copen!AF105 -> 0.2499072 | H73: =+Copen!AH105 -> 0.20301784 | I73: =+Copen!AJ105 -> 0.16829209 | J73: =+Copen!AL105 -> 0.14260931 | K73: =+Copen!AN105 -> 0.12359595 | L73: =+Copen!AP105 -> 0.11008122 | M73: =+Copen!AR105 -> 0.099348297 | N73: =+Copen!AT105 -> 0.089661838 | O73: =+Copen!AV105 -> 0.080919809 | P73: =+Copen!AX105 -> 0.073030127 | Q73: =+Copen!AZ105 -> 0.06590969 | R73: =+Copen!BB105 -> 0.059483495 | S73: =+Copen!BD105 -> 0.053683854 | T73: =+Copen!BF105 -> 0.048449679 | U73: =+Copen!BH105 -> 0.043725835 | V73: =+Copen!BJ105 -> 0.039462566 | W73: =+Copen!BK105 -> 0.037489438 | X73: =+Copen!BL105 -> 0.035614966 | Y73: =+Copen!BM105 -> 0.033834218 | Z73: =+Copen!BN105 -> 0.032142507 | AA73: =+Copen!BO105 -> 0.030535381 | AB73: =+Copen!BP105 -> 0.029008612 | AC73: =+Copen!BQ105 -> 0.027558182 | ... BI73: =+Copen!CW105 -> 0.0053383363
A74: Eurasia | B74: =+Copen!R106 -> 0.25666629 | C74: =+Copen!X106 -> 0.49278319 | D74: =+Copen!Z106 -> 0.47544298 | E74: =+Copen!AB106 -> 0.37426854 | F74: =+Copen!AD106 -> 0.26907396 | G74: =+Copen!AF106 -> 0.18946164 | H74: =+Copen!AH106 -> 0.15391351 | I74: =+Copen!AJ106 -> 0.12758695 | J74: =+Copen!AL106 -> 0.10811611 | K74: =+Copen!AN106 -> 0.093701546 | L74: =+Copen!AP106 -> 0.083455651 | M74: =+Copen!AR106 -> 0.075318725 | N74: =+Copen!AT106 -> 0.067975149 | O74: =+Copen!AV106 -> 0.061347572 | P74: =+Copen!AX106 -> 0.055366184 | Q74: =+Copen!AZ106 -> 0.049967981 | R74: =+Copen!BB106 -> 0.045096103 | S74: =+Copen!BD106 -> 0.040699233 | T74: =+Copen!BF106 -> 0.036731058 | U74: =+Copen!BH106 -> 0.033149779 | V74: =+Copen!BJ106 -> 0.029917676 | W74: =+Copen!BK106 -> 0.028421792 | X74: =+Copen!BL106 -> 0.027000703 | Y74: =+Copen!BM106 -> 0.025650667 | Z74: =+Copen!BN106 -> 0.024368134 | AA74: =+Copen!BO106 -> 0.023149727 | AB74: =+Copen!BP106 -> 0.021992241 | AC74: =+Copen!BQ106 -> 0.020892629 | ... BI74: =+Copen!CW106 -> 0.0040471422
A75: China | B75: =+Copen!R107 -> 1.6007411 | C75: =+Copen!X107 -> 2.8437372 | D75: =+Copen!Z107 -> 3.2081467 | E75: =+Copen!AB107 -> 2.5254519 | F75: =+Copen!AD107 -> 1.8156304 | G75: =+Copen!AF107 -> 1.2784304 | H75: =+Copen!AH107 -> 1.0385622 | I75: =+Copen!AJ107 -> 0.86091847 | J75: =+Copen!AL107 -> 0.72953508 | K75: =+Copen!AN107 -> 0.63226995 | L75: =+Copen!AP107 -> 0.56313371 | M75: =+Copen!AR107 -> 0.50822818 | N75: =+Copen!AT107 -> 0.45867593 | O75: =+Copen!AV107 -> 0.41395503 | P75: =+Copen!AX107 -> 0.37359441 | Q75: =+Copen!AZ107 -> 0.33716896 | R75: =+Copen!BB107 -> 0.30429498 | S75: =+Copen!BD107 -> 0.27462622 | T75: =+Copen!BF107 -> 0.24785017 | U75: =+Copen!BH107 -> 0.22368477 | V75: =+Copen!BJ107 -> 0.20187551 | W75: =+Copen!BK107 -> 0.19178173 | X75: =+Copen!BL107 -> 0.18219265 | Y75: =+Copen!BM107 -> 0.17308301 | Z75: =+Copen!BN107 -> 0.16442886 | AA75: =+Copen!BO107 -> 0.15620742 | AB75: =+Copen!BP107 -> 0.14839705 | AC75: =+Copen!BQ107 -> 0.1409772 | ... BI75: =+Copen!CW107 -> 0.027308902
A76: India | B76: =+Copen!R108 -> 0.40515159 | C76: =+Copen!X108 -> 0.72309374 | D76: =+Copen!Z108 -> 0.95176955 | E76: =+Copen!AB108 -> 1.1736542 | F76: =+Copen!AD108 -> 0.84377863 | G76: =+Copen!AF108 -> 0.59412544 | H76: =+Copen!AH108 -> 0.48265141 | I76: =+Copen!AJ108 -> 0.40009497 | J76: =+Copen!AL108 -> 0.33903712 | K76: =+Copen!AN108 -> 0.29383506 | L76: =+Copen!AP108 -> 0.26170535 | M76: =+Copen!AR108 -> 0.23618908 | N76: =+Copen!AT108 -> 0.21316064 | O76: =+Copen!AV108 -> 0.19237748 | P76: =+Copen!AX108 -> 0.17362067 | Q76: =+Copen!AZ108 -> 0.15669266 | R76: =+Copen!BB108 -> 0.14141512 | S76: =+Copen!BD108 -> 0.12762715 | T76: =+Copen!BF108 -> 0.1151835 | U76: =+Copen!BH108 -> 0.10395311 | V76: =+Copen!BJ108 -> 0.093817683 | W76: =+Copen!BK108 -> 0.089126799 | X76: =+Copen!BL108 -> 0.084670459 | Y76: =+Copen!BM108 -> 0.080436936 | Z76: =+Copen!BN108 -> 0.076415089 | AA76: =+Copen!BO108 -> 0.072594335 | AB76: =+Copen!BP108 -> 0.068964618 | AC76: =+Copen!BQ108 -> 0.065516387 | ... BI76: =+Copen!CW108 -> 0.012691277
A77: Middle East | B77: =+Copen!R109 -> 0.58967496 | C77: =+Copen!X109 -> 0.80742719 | D77: =+Copen!Z109 -> 1.0442826 | E77: =+Copen!AB109 -> 1.2745456 | F77: =+Copen!AD109 -> 1.4943414 | G77: =+Copen!AF109 -> 1.0522028 | H77: =+Copen!AH109 -> 0.85478108 | I77: =+Copen!AJ109 -> 0.70857269 | J77: =+Copen!AL109 -> 0.60043854 | K77: =+Copen!AN109 -> 0.52038519 | L77: =+Copen!AP109 -> 0.46348311 | M77: =+Copen!AR109 -> 0.41829351 | N77: =+Copen!AT109 -> 0.37750989 | O77: =+Copen!AV109 -> 0.34070268 | P77: =+Copen!AX109 -> 0.30748417 | Q77: =+Copen!AZ109 -> 0.27750446 | R77: =+Copen!BB109 -> 0.25044778 | S77: =+Copen!BD109 -> 0.22602912 | T77: =+Copen!BF109 -> 0.20399128 | U77: =+Copen!BH109 -> 0.18410213 | V77: =+Copen!BJ109 -> 0.16615217 | W77: =+Copen!BK109 -> 0.15784456 | X77: =+Copen!BL109 -> 0.14995233 | Y77: =+Copen!BM109 -> 0.14245472 | Z77: =+Copen!BN109 -> 0.13533198 | AA77: =+Copen!BO109 -> 0.12856538 | AB77: =+Copen!BP109 -> 0.12213711 | AC77: =+Copen!BQ109 -> 0.11603026 | ... BI77: =+Copen!CW109 -> 0.022476393
A78: Africa | B78: =+Copen!R110 -> 0.19137708 | C78: =+Copen!X110 -> 0.24403789 | D78: =+Copen!Z110 -> 0.3538932 | E78: =+Copen!AB110 -> 0.48200313 | F78: =+Copen!AD110 -> 0.62603054 | G78: =+Copen!AF110 -> 0.75868965 | H78: =+Copen!AH110 -> 0.87768255 | I78: =+Copen!AJ110 -> 0.72755692 | J78: =+Copen!AL110 -> 0.61652562 | K78: =+Copen!AN110 -> 0.53432745 | L78: =+Copen!AP110 -> 0.47590085 | M78: =+Copen!AR110 -> 0.42950051 | N78: =+Copen!AT110 -> 0.38762421 | O78: =+Copen!AV110 -> 0.34983085 | P78: =+Copen!AX110 -> 0.31572235 | Q78: =+Copen!AZ110 -> 0.28493942 | R78: =+Copen!BB110 -> 0.25715782 | S78: =+Copen!BD110 -> 0.23208494 | T78: =+Copen!BF110 -> 0.20945665 | U78: =+Copen!BH110 -> 0.18903463 | V78: =+Copen!BJ110 -> 0.17060375 | W78: =+Copen!BK110 -> 0.16207357 | X78: =+Copen!BL110 -> 0.15396989 | Y78: =+Copen!BM110 -> 0.14627139 | Z78: =+Copen!BN110 -> 0.13895782 | AA78: =+Copen!BO110 -> 0.13200993 | AB78: =+Copen!BP110 -> 0.12540944 | AC78: =+Copen!BQ110 -> 0.11913896 | ... BI78: =+Copen!CW110 -> 0.023078586
A79: Latin America | B79: =+Copen!R111 -> 0.4122724 | C79: =+Copen!X111 -> 0.53297093 | D79: =+Copen!Z111 -> 0.67605786 | E79: =+Copen!AB111 -> 0.53219249 | F79: =+Copen!AD111 -> 0.38261069 | G79: =+Copen!AF111 -> 0.26940567 | H79: =+Copen!AH111 -> 0.21885787 | I79: =+Copen!AJ111 -> 0.18142272 | J79: =+Copen!AL111 -> 0.15373609 | K79: =+Copen!AN111 -> 0.13323925 | L79: =+Copen!AP111 -> 0.11867006 | M79: =+Copen!AR111 -> 0.10709973 | N79: =+Copen!AT111 -> 0.096657508 | O79: =+Copen!AV111 -> 0.087233401 | P79: =+Copen!AX111 -> 0.078728145 | Q79: =+Copen!AZ111 -> 0.07105215 | R79: =+Copen!BB111 -> 0.064124566 | S79: =+Copen!BD111 -> 0.057872421 | T79: =+Copen!BF111 -> 0.05222986 | U79: =+Copen!BH111 -> 0.047137448 | V79: =+Copen!BJ111 -> 0.042541547 | W79: =+Copen!BK111 -> 0.04041447 | X79: =+Copen!BL111 -> 0.038393746 | Y79: =+Copen!BM111 -> 0.036474059 | Z79: =+Copen!BN111 -> 0.034650356 | AA79: =+Copen!BO111 -> 0.032917838 | AB79: =+Copen!BP111 -> 0.031271946 | AC79: =+Copen!BQ111 -> 0.029708349 | ... BI79: =+Copen!CW111 -> 0.0057548484
A80: OHI | B80: =+Copen!R112 -> 0.54177826 | C80: =+Copen!X112 -> 0.56968411 | D80: =+Copen!Z112 -> 0.55679019 | E80: =+Copen!AB112 -> 0.43830503 | F80: =+Copen!AD112 -> 0.3151119 | G80: =+Copen!AF112 -> 0.2218781 | H80: =+Copen!AH112 -> 0.18024776 | I80: =+Copen!AJ112 -> 0.14941678 | J80: =+Copen!AL112 -> 0.12661453 | K80: =+Copen!AN112 -> 0.10973367 | L80: =+Copen!AP112 -> 0.097734722 | M80: =+Copen!AR112 -> 0.088205587 | N80: =+Copen!AT112 -> 0.079605542 | O80: =+Copen!AV112 -> 0.071844002 | P80: =+Copen!AX112 -> 0.064839212 | Q80: =+Copen!AZ112 -> 0.058517389 | R80: =+Copen!BB112 -> 0.052811943 | S80: =+Copen!BD112 -> 0.047662779 | T80: =+Copen!BF112 -> 0.043015658 | U80: =+Copen!BH112 -> 0.038821631 | V80: =+Copen!BJ112 -> 0.035036522 | W80: =+Copen!BK112 -> 0.033284696 | X80: =+Copen!BL112 -> 0.031620461 | Y80: =+Copen!BM112 -> 0.030039438 | Z80: =+Copen!BN112 -> 0.028537466 | AA80: =+Copen!BO112 -> 0.027110593 | AB80: =+Copen!BP112 -> 0.025755063 | AC80: =+Copen!BQ112 -> 0.02446731 | ... BI80: =+Copen!CW112 -> 0.004739599
A81: Other | B81: =+Copen!R113 -> 0.3639521 | C81: =+Copen!X113 -> 0.63080748 | D81: =+Copen!Z113 -> 0.87865736 | E81: =+Copen!AB113 -> 1.1513158 | F81: =+Copen!AD113 -> 0.82771882 | G81: =+Copen!AF113 -> 0.58281733 | H81: =+Copen!AH113 -> 0.47346501 | I81: =+Copen!AJ113 -> 0.39247988 | J81: =+Copen!AL113 -> 0.33258416 | K81: =+Copen!AN113 -> 0.28824243 | L81: =+Copen!AP113 -> 0.25672426 | M81: =+Copen!AR113 -> 0.23169364 | N81: =+Copen!AT113 -> 0.20910351 | O81: =+Copen!AV113 -> 0.18871592 | P81: =+Copen!AX113 -> 0.17031612 | Q81: =+Copen!AZ113 -> 0.1537103 | R81: =+Copen!BB113 -> 0.13872354 | S81: =+Copen!BD113 -> 0.125198 | T81: =+Copen!BF113 -> 0.11299119 | U81: =+Copen!BH113 -> 0.10197455 | V81: =+Copen!BJ113 -> 0.092032032 | W81: =+Copen!BK113 -> 0.087430431 | X81: =+Copen!BL113 -> 0.083058909 | Y81: =+Copen!BM113 -> 0.078905964 | Z81: =+Copen!BN113 -> 0.074960666 | AA81: =+Copen!BO113 -> 0.071212632 | AB81: =+Copen!BP113 -> 0.067652001 | AC81: =+Copen!BQ113 -> 0.064269401 | ... BI81: =+Copen!CW113 -> 0.012449721
U82: =SUM(U70:U81) -> 1.1500611 | V82: =SUM(V70:V81) -> 1.0379302
A83: Tentative optimal taxes
A84: GLOBAL | B84: 0.001 | C84: 42.800328 | D84: 71.172417 | E84: 85.231066 | F84: 135.01205 | G84: 156.27127 | H84: 189.81414 | I84: 242.26958 | J84: 303.94808 | K84: 347.42521 | L84: 450.30712 | M84: 681.95115 | N84: 532.37218 | O84: 594.84403 | P84: 658.41468 | Q84: 663.1934 | R84: 624.65411 | S84: 614.22416 | T84: 590.92968 | U84: 587.45657 | V84: 586.22364 | W84: 577.6177 | X84: 576.85299 | Y84: 573.10939 | Z84: 570.59849 | AA84: 1200 | AB84: 1200 | AC84: 1200 | AD84: 1200 | AE84: 1200 | AF84: 1200 | AG84: 1200 | AH84: 1200 | AI84: 1200 | AJ84: 1200 | AK84: 1200 | AL84: 1200 | AM84: 1200 | AN84: 1200 | AO84: 1200 | AP84: 1200 | AQ84: 1200 | AR84: 1200 | AS84: 1200 | AT84: 1200 | AU84: 1200 | AV84: 1200 | AW84: 1200 | AX84: 1200 | AY84: 1200 | AZ84: 1200 | BA84: 1200 | BB84: 1200 | BC84: 1200 | BD84: 1200 | BE84: 1200 | BF84: 1200 | BG84: 1200 | BH84: 1200 | BI84: 1200
A86: Tentative carbon prices for T < 2 degrees
A87: GLOBAL | B87: 0.001 | C87: 92.734851 | D87: 154.88706 | E87: 248.01214 | F87: 385.45174 | G87: 578.33076 | H87: 823.63434 | I87: 1165.7471 | J87: 1245.6351 | K87: 893.50768 | L87: 1200 | M87: 900 | N87: 702.64812 | O87: 649.935 | P87: 647.09613 | Q87: 648.59072 | R87: 647.08624 | S87: 639.97912 | T87: 719.70117 | U87: 567.70708 | V87: 567.6649 | W87: 567.35468 | X87: 567.32813 | Y87: 567.30111 | Z87: 567.10493 | AA87: 1200 | AB87: 1200 | AC87: 1200 | AD87: 1200 | AE87: 1200 | AF87: 1200 | AG87: 1200 | AH87: 1200 | AI87: 1200 | AJ87: 1200 | AK87: 1200 | AL87: 1200 | AM87: 1200 | AN87: 1200 | AO87: 1200 | AP87: 1200 | AQ87: 1200 | AR87: 1200 | AS87: 1200 | AT87: 1200 | AU87: 1200 | AV87: 1200 | AW87: 1200 | AX87: 1200 | AY87: 1200 | AZ87: 1200 | BA87: 1200 | BB87: 1200 | BC87: 1200 | BD87: 1200 | BE87: 1200 | BF87: 1200 | BG87: 1200 | BH87: 1200 | BI87: 1200
A89: Base
A90: GLOBAL | B90: 0.001 | C90: 0.001 | D90: 0.001 | E90: 0.001 | F90: 0.001 | G90: 0.001 | H90: 0.001 | I90: 0.001 | J90: 0.001 | K90: 0.001 | L90: 0.001 | M90: 0.001 | N90: 0.001 | O90: 0.001 | P90: 0.001 | Q90: 0.001 | R90: 0.001 | S90: 0.001 | T90: 0.001 | U90: 0.001 | V90: 0.001 | W90: 0.001 | X90: 0.001 | Y90: 0.001 | Z90: 0.001 | AA90: 0.001 | AB90: 0.001 | AC90: 0.001 | AD90: 0.001 | AE90: 0.001 | AF90: 0.001 | AG90: 0.001 | AH90: 0.001 | AI90: 0.001 | AJ90: 0.001 | AK90: 0.001 | AL90: 0.001 | AM90: 0.001 | AN90: 0.001 | AO90: 0.001 | AP90: 0.001 | AQ90: 0.001 | AR90: 0.001 | AS90: 0.001 | AT90: 0.001 | AU90: 0.001 | AV90: 0.001 | AW90: 0.001 | AX90: 0.001 | AY90: 0.001 | AZ90: 0.001 | BA90: 0.001 | BB90: 0.001 | BC90: 0.001 | BD90: 0.001 | BE90: 0.001 | BF90: 0.001 | BG90: 0.001 | BH90: 0.001 | BI90: 0.001

Sheet Parameters
A2: Linked Parameters | B2: are linked files between this and other sheets (base, opt, …)
B3: are damage control parameters that must be carefully examined.
B6: Parameter value | D6: Notes
A8: KEY PARAMETERS
A9: Rate of social time preference (% py) | B9: 0.015 | D9: This parameter is part of the calibration for the real interest rate. It should be adjusted along with the EMUC
A10: Elasticity of MU of consumption (set) | B10: 1.5 | D10: This parameter is part of the calibration for the real interest rate. It should be adjusted along with the EMUC
A11: Damage coefficient on temperature | B11: 0.0017543802 | D11: Damage coefficients are calibrated to impact analysis and should be adjusted together
A12: Damage coefficient on temperature squared | B12: 0.0022592108 | D12: Damage coefficients are calibrated to impact analysis and should be adjusted together
A13: Exponent on damages | B13: 2 | D13: Damage coefficients are calibrated to impact analysis and should be adjusted together
A14: Price backstop technology (2005 US 000 $ per tC) | B14: 1.2 | D14: See A Question of Balance for discussion. This parameter also affects the abatement costs.
A15: Exponent of control cost function | B15: 2.8 | D15: See A Question of Balance for discussion. This parameter also affects the abatement costs.
A16: Backstop inflection year | B16: 2250 | D16: Backstop price and abatement costs fall rapidly after this year.
A17: Maximum carbon resources (GtC) | B17: 6000 | D17: See A Question of Balance for discussion.
A18: Equilibrium temperature increase for CO2 doubling | B18: 3.2 | D18: Updated from IPCC FAR, median of models, Table 8.2.
A19: Decline rate TFP (per decade) | B19: 0.1 | D19: This parameter is part of the long-run productivity growth assumptions. It generally does not need adjustment
A20: TFP convergence rate (per decade) | B20: 0.1 | D20: This parameter is part of the long-run productivity growth assumptions. It generally does not need adjustment
... A32: Exponent for catastrophic damages | B32: 6 | D32: Not used
A33: Damage rate at threshold for catastrophic damages | B33: =+A6 -> 0 | D33: Not used
A34: OUTPUT and PRODUCTION
A35: Capital share | C35: 0.3 | D35: assumed | F35: 0.3 | G35: 0.3 | H35: 0.3 | I35: 0.3 | J35: 0.3 | K35: 0.3 | L35: 0.3 | M35: 0.3 | N35: 0.3 | O35: 0.3 | P35: 0.3 | Q35: 0.3 | R35: Data
A36: Rate of depreciation (percent per year) | C36: 0.1 | D36: assumed | F36: 0.1 | G36: 0.1 | H36: 0.1 | I36: 0.1 | J36: 0.1 | K36: 0.1 | L36: 0.1 | M36: 0.1 | N36: 0.1 | O36: 0.1 | P36: 0.1 | Q36: 0.1 | R36: Data
A37: Initial output (2005 US International $, trillions) | C37: 55.34 | D37: data | E37: =SUM(F37:Q37) -> 55.378946 | F37: =+Data!C140 -> 12.3979 | G37: =+Data!D140 -> 13.031057 | H37: =+Data!E140 -> 3.8702838 | I37: =+Data!F140 -> 1.6979567 | J37: =+Data!G140 -> 0.80733505 | K37: =+Data!H140 -> 5.3332327 | L37: =+Data!I140 -> 2.4408315 | M37: =+Data!J140 -> 3.4801033 | ... Q37: =+Data!N140 -> 2.6191887
A38: Initial real interest rate (percent per decade annualized) | C38: 0.05 | D38: calibrated | F38: =+Data!C142 -> 0.062765473 | G38: =+Data!D142 -> 0.067765473 | H38: =+Data!E142 -> 0.062765473 | I38: =+Data!F142 -> 0.082765473 | J38: =+Data!G142 -> 0.077765473 | K38: =+Data!H142 -> 0.072765473 | L38: =+Data!I142 -> 0.077765473 | M38: =+Data!J142 -> 0.092765473 | ... Q38: =+Data!N142 -> 0.077765473 | R38: This is fundamental for calculation of the discount rate.
A39: Initial K | C39: 180 | D39: calculated | F39: =+Data!C143 -> 22.8511 | G39: =+Data!D143 -> 23.302275 | H39: =+Data!E143 -> 7.1334855 | I39: =+Data!F143 -> 2.7871074 | J39: =+Data!G143 -> 1.3624722 | K39: =+Data!H143 -> 9.260935 | L39: =+Data!I143 -> 4.1191883 | M39: =+Data!J143 -> 5.4160685 | ... Q39: =+Data!N143 -> 4.4201869 | R39: From production function
A40: Calculated A | D40: calculated | F40: =+Data!C144 -> 11.347695 | G40: =+Data!D144 -> 8.3478215 | H40: =+Data!E144 -> 9.0624352 | I40: =+Data!F144 -> 4.8677308 | J40: =+Data!G144 -> 2.7019694 | K40: =+Data!H144 -> 2.2708227 | L40: =+Data!I144 -> 1.498374 | M40: =+Data!J144 -> 3.8948608 | ... Q40: =+Data!N144 -> 1.7549043 | R40: From production function
A41: Initial savings rate | D41: calculated | F41: =+Data!C145 -> 0.23181398 | G41: =+Data!D145 -> 0.21696963 | H41: =+Data!E145 -> 0.21278717 | I41: =+Data!F145 -> 0.20100021 | J41: =+Data!G145 -> 0.20828063 | K41: =+Data!H145 -> 0.3110511 | L41: =+Data!I145 -> 0.27229998 | M41: =+Data!J145 -> 0.225188 | ... Q41: =+Data!N145 -> 0.24387583
A42: WELFARE
A43: Rate of social time preference (% py) | C43: 0.015 | D43: calibrated | F43: =+$C43 -> 0.015 | G43: =+$C43 -> 0.015 | H43: =+$C43 -> 0.015 | I43: =+$C43 -> 0.015 | J43: =+$C43 -> 0.015 | K43: =+$C43 -> 0.015 | L43: =+$C43 -> 0.015 | M43: =+$C43 -> 0.015 | ... Q43: =+$C43 -> 0.015 | R43: A fundamental assumption.
A44: Decline of rate of time preference (% per decade) | C44: 0 | D44: assumed | F44: =+$C44 -> 0 | G44: =+$C44 -> 0 | H44: =+$C44 -> 0 | I44: =+$C44 -> 0 | J44: =+$C44 -> 0 | K44: =+$C44 -> 0 | L44: =+$C44 -> 0 | M44: =+$C44 -> 0 | ... Q44: =+$C44 -> 0
A45: Elasticity of MU of consumption (set) | C45: =+B10 -> 1.5 | D45: calibrated | F45: =+$C45 -> 1.5 | G45: =+$C45 -> 1.5 | H45: =+$C45 -> 1.5 | I45: =+$C45 -> 1.5 | J45: =+$C45 -> 1.5 | K45: =+$C45 -> 1.5 | L45: =+$C45 -> 1.5 | M45: =+$C45 -> 1.5 | ... Q45: =+$C45 -> 1.5 | R45: This is calculated from Ramsey equation and data are RSTP and real interest rate, population growth, and p.c. consumption.
A46: Elasticity of MU of consumption (calibrated) | D46: NA
A47: POPULATION
A48: Initial population (millions) | D48: data | E48: =SUM(F48:Q48) -> 6410.8916 | F48: =+Data!C141 -> 296.84258 | G48: =+Data!D141 -> 490.08019 | H48: =+Data!E141 -> 127.773 | I48: =+Data!F141 -> 143.15 | J48: =+Data!G141 -> 155.94247 | K48: =+Data!H141 -> 1304.5 | L48: =+Data!I141 -> 1094.583 | M48: =+Data!J141 -> 412.769 | ... Q48: =+Data!N141 -> 937.19557 | R48: Data
C49: Global | F49: US | G49: EU | H49: Japan | I49: Russia | J49: Eurasia | K49: China | L49: India | M49: Middle East | N49: Africa | O49: Latin America | P49: OHI | Q49: Other non-OECD Asia
A50: DAMAGE FUNCTION | B50: If individual country damages = 1, otherwise 0 | J50: 1
A51: damage coefficient on temperature | C51: =+B11 -> 0.0017543802 | D51: DICE 2007 | F51: =IF($J$50=0,$C51,F119) -> 0 | G51: =IF($J$50=0,$C51,G119) -> 0 | H51: =IF($J$50=0,$C51,H119) -> 0 | I51: =IF($J$50=0,$C51,I119) -> 0 | J51: =IF($J$50=0,$C51,J119) -> 0 | K51: =IF($J$50=0,$C51,K119) -> 0.078458281 | L51: =IF($J$50=0,$C51,L119) -> 0.43852128 | M51: =IF($J$50=0,$C51,M119) -> 0.27798926 | ... Q51: =IF($J$50=0,$C51,Q119) -> 0.17551223 | R51: These three parameters are fundamental for optimization, but not for basic calculations of paths
A52: damage coefficient on temperature squared | C52: =+B12 -> 0.0022592108 | D52: DICE 2007 | F52: =IF($J$50=0,$C52,F120) -> 0.14141261 | G52: =IF($J$50=0,$C52,G120) -> 0.15910847 | H52: =IF($J$50=0,$C52,H120) -> 0.16172344 | I52: =IF($J$50=0,$C52,I120) -> 0.11505844 | J52: =IF($J$50=0,$C52,J120) -> 0.13047244 | K52: =IF($J$50=0,$C52,K120) -> 0.12589303 | L52: =IF($J$50=0,$C52,L120) -> 0.16887308 | M52: =IF($J$50=0,$C52,M120) -> 0.15859856 | ... Q52: =IF($J$50=0,$C52,Q120) -> 0.17344211 | R52: Ditto
A53: Exponent on damages | C53: =+B13 -> 2 | D53: DICE 2007 | F53: =IF($J$50=0,$C53,F121) -> 2 | G53: =IF($J$50=0,$C53,G121) -> 2 | H53: =IF($J$50=0,$C53,H121) -> 2 | I53: =IF($J$50=0,$C53,I121) -> 2 | J53: =IF($J$50=0,$C53,J121) -> 2 | K53: =IF($J$50=0,$C53,K121) -> 2 | L53: =IF($J$50=0,$C53,L121) -> 2 | M53: =IF($J$50=0,$C53,M121) -> 2 | ... Q53: =IF($J$50=0,$C53,Q121) -> 2 | R53: Ditto
A54: Threshold for catastrophic damages | C54: =+B31 -> 4 | D54: assumed | F54: =IF($J$50=0,$C54,F122) -> 4 | G54: =IF($J$50=0,$C54,G122) -> 4 | H54: =IF($J$50=0,$C54,H122) -> 4 | I54: =IF($J$50=0,$C54,I122) -> 4 | J54: =IF($J$50=0,$C54,J122) -> 4 | K54: =IF($J$50=0,$C54,K122) -> 4 | L54: =IF($J$50=0,$C54,L122) -> 4 | M54: =IF($J$50=0,$C54,M122) -> 4 | ... Q54: =IF($J$50=0,$C54,Q122) -> 4
A55: Exponent for catastrophic damages | C55: =+B32 -> 6 | D55: assumed | F55: =IF($J$50=0,$C55,F123) -> 6 | G55: =IF($J$50=0,$C55,G123) -> 6 | H55: =IF($J$50=0,$C55,H123) -> 6 | I55: =IF($J$50=0,$C55,I123) -> 6 | J55: =IF($J$50=0,$C55,J123) -> 6 | K55: =IF($J$50=0,$C55,K123) -> 6 | L55: =IF($J$50=0,$C55,L123) -> 6 | M55: =IF($J$50=0,$C55,M123) -> 6 | ... Q55: =IF($J$50=0,$C55,Q123) -> 6
A56: Damage rate at threshold for catastrophic damages | B56: if catast | C56: =+B33 -> 0 | D56: assumed | F56: =IF($J$50=0,$C56,F124) -> 0 | G56: =IF($J$50=0,$C56,G124) -> 0 | H56: =IF($J$50=0,$C56,H124) -> 0 | I56: =IF($J$50=0,$C56,I124) -> 0 | J56: =IF($J$50=0,$C56,J124) -> 0 | K56: =IF($J$50=0,$C56,K124) -> 0 | L56: =IF($J$50=0,$C56,L124) -> 0 | M56: =IF($J$50=0,$C56,M124) -> 0 | ... Q56: =IF($J$50=0,$C56,Q124) -> 0
A57: ABATEMENT COST | F57: =+Global!B127 -> 1259.2275
A58: Price backstop technology (2005 US 000 $ per tC) | C58: 1.26 | D58: Lab notes | F58: =+$C$58*F59 -> 1.134 | G58: =+$C$58*G59 -> 1.764 | H58: =+$C$58*H59 -> 1.764 | I58: =+$C$58*I59 -> 0.756 | J58: =+$C$58*J59 -> 0.756 | K58: =+$C$58*K59 -> 0.882 | L58: =+$C$58*L59 -> 1.386 | M58: =+$C$58*M59 -> 1.26 | ... Q58: =+$C$58*Q59 -> 1.512 | R58: Estimate
A59: Ratio of backstop to World | D59: Lab notes | F59: 0.9 | G59: 1.4 | H59: 1.4 | I59: 0.6 | J59: 0.6 | K59: 0.7 | L59: 1.1 | M59: 1 | N59: 1.1 | O59: 1.3 | P59: 1.1 | Q59: 1.2
A60: Ratio asymptotic to initial price | C60: 0.1 | D60: assumed | F60: =+$C$60 -> 0.1 | G60: =+$C$60 -> 0.1 | H60: =+$C$60 -> 0.1 | I60: =+$C$60 -> 0.1 | J60: =+$C$60 -> 0.1 | K60: =+$C$60 -> 0.1 | L60: =+$C$60 -> 0.1 | M60: =+$C$60 -> 0.1 | ... Q60: =+$C$60 -> 0.1
A61: Decline of backstop price (per decade) | C61: 0.05 | D61: assumed | F61: =+$C$61 -> 0.05 | G61: =+$C$61 -> 0.05 | H61: =+$C$61 -> 0.05 | I61: =+$C$61 -> 0.05 | J61: =+$C$61 -> 0.05 | K61: =+$C$61 -> 0.05 | L61: =+$C$61 -> 0.05 | M61: =+$C$61 -> 0.05 | ... Q61: =+$C$61 -> 0.05 | R61: Estimate
A63: Exponent of control cost function | C63: 2.8 | D63: Lat notes | R63: Estimate
A64: Backstop competitive year (pback = 0 for periods beyond) | C64: =+B16 -> 2250 | D64: assumed | F64: =+$C64 -> 2250 | G64: =+$C64 -> 2250 | H64: =+$C64 -> 2250 | I64: =+$C64 -> 2250 | J64: =+$C64 -> 2250 | K64: =+$C64 -> 2250 | L64: =+$C64 -> 2250 | M64: =+$C64 -> 2250 | ... Q64: =+$C64 -> 2250 | R64: - The year is not terribly important, but sets a limit to the time of CO2 emissions.
A65: Upper limit of control rate | C65: 1 | D65: assumed | F65: 1 | G65: 1 | H65: 1 | I65: 1 | J65: 1 | K65: 1 | L65: 1 | M65: 1 | N65: 1 | O65: 1 | P65: 1 | Q65: 1 | R65: - limmiu is generally not used, but can be if there are constraints on buildup of emissions controls.
A66: EMISSIONS
A67: CO2 emissions for 2005 | C67: 7957.7 | D67: data | E67: =SUM(F67:Q67) -> 7.971 | F67: =+Data!C150/1000 -> 1.6621335 | G67: =+Data!D150/1000 -> 1.1460506 | H67: =+Data!E150/1000 -> 0.36996593 | I67: =+Data!F150/1000 -> 0.43123618 | J67: =+Data!G150/1000 -> 0.25666629 | K67: =+Data!H150/1000 -> 1.6007411 | L67: =+Data!I150/1000 -> 0.40515159 | M67: =+Data!J150/1000 -> 0.58967496 | ... Q67: =+Data!N150/1000 -> 0.3639521 | R67: CDIAC, including cement and flaring (3 year average around 2005)
A68: Initial emissions controls | C68: 0.005 | D68: data | R68: Includes minor controls from EU
A69: Initial sigma (tC per $1000 GDP US $, 2005 prices) 2005 | D69: data | F69: =+F67/F37 -> 0.13406572 | G69: =+G67/G37 -> 0.08794763 | H69: =+H67/H37 -> 0.095591421 | I69: =+I67/I37 -> 0.2539736 | J69: =+J67/J37 -> 0.31791793 | K69: =+K67/K37 -> 0.30014462 | L69: =+L67/L37 -> 0.16598917 | M69: =+M67/M37 -> 0.1694418 | ... Q69: =+Q67/Q37 -> 0.13895604 | R69: From actual emissions, data, and controls.
A70: Initial carbon emissions from land use change (GTC per year) | C70: =+SUM(F70:Q70) -> 1.6 | D70: data | F70: 0 | G70: 0 | H70: 0 | I70: 0 | J70: 0 | K70: 0 | L70: 0 | M70: 0 | N70: 0.3 | O70: 0.6 | P70: 0 | Q70: 0.7 | R70: - These are not critical and are poorly measured.
A71: Decline rate of land emissions per decade | C71: 0.2 | D71: assumed | F71: =+$C$71 -> 0.2 | G71: =+$C$71 -> 0.2 | H71: =+$C$71 -> 0.2 | I71: =+$C$71 -> 0.2 | J71: =+$C$71 -> 0.2 | K71: =+$C$71 -> 0.2 | L71: =+$C$71 -> 0.2 | M71: =+$C$71 -> 0.2 | ... Q71: =+$C$71 -> 0.2
A72: CARBON LIMITS
A73: Maximum carbon resources (GtC) | B73: =+B17 -> 6000 | D73: data | R73: - Generally not important or binding except in exceptionally rapid growth cases. Data poorly determined.
A74: CONCENTRATIONS
A75: Initial atmospheric concentration of CO2 (GTC, 2000) | B75: 787 | D75: GISS | R75: Data
A76: Initial atmospheric concentration of CO2 (GTC, 2010) | B76: 829
A77: Initial concentration of CO2 in biosphere/shallow oceans (GTC) | B77: 1600 | D77: Calibrated | R77: Data and models
A78: Initial concentration of CO2 in deep oceans (GTC) | B78: 10010 | D78: Calibrated | R78: Data and models
A79: Carbon cycle transition coefficients (percent per decade)
A80: atmosphere to atmosphere (b11) | B80: =100-B82 -> 88 | D80: calculated | R80: Model based
A81: biosphere/shallow oceans to atmosphere (b21) | B81: =+B87*B82/B88 -> 4.704 | D81: calculated | G81: 2105 | H81: =+Global!L48 -> 372.28065 | I81: 349.73682 | J81: =+LN(H81/I81) -> 0.062467082 | R81: Model based
A82: atmosphere to biosphere/shallow oceans (b12) | B82: =+B28 -> 12 | D82: calibrated and uncertain | G82: 2305 | H82: =+Global!AF48 -> 1386.3541 | I82: 1434.2119 | J82: =+LN(H82/I82) -> -0.033938124 | R82: Model based
A83: biosphere/shallow oceans to biosphere/shallow oceans (b22) | B83: =100-B81-B85 -> 94.796 | D83: calculated | G83: 2505 | H83: =+Global!AZ48 -> 2414.637 | I83: 3204.2619 | J83: =+LN(H83/I83) -> -0.28293279 | R83: Model based
A84: deep oceans to biosphere/shallow oceans (b32) | B84: =+B85*B88/B89 -> 0.075 | D84: calculated | R84: Model based
A85: biosphere/shallow oceans to deep oceans (b23) | B85: 0.5 | D85: calibrated | R85: Model based
A86: deep oceans to deep oceans (b33) | B86: =100-B84 -> 99.925 | D86: calculated | R86: Model based
A87: Equil. conc. of CO2 in atmos. (GTC) | B87: 588 | D87: calculated
A88: Equil. conc. of CO2 in biosphere/shallow oceans (GTC) | B88: 1500 | D88: calculated
A89: Equil. conc. of CO2 in deep oceans (GTC) | B89: 10000 | D89: calculated
A90: TEMPERATURE
A91: 2000 forcings other ghg | B91: -0.06 | D91: GISS | R91: Data
A92: 2100 forcings other ghg | B92: 0.3 | D92: GISS | R92: Estimates
A93: Initial atmospheric temperature, 2005 (deg. C above 1900) | B93: 0.83 | D93: data | R93: Data
A94: Initial atmospheric temperature, 2015 (deg. C above 1900) | B94: 0.98
A95: Initial temperature of deep oceans (deg. C above 1900) | B95: 0.0068 | D95: calibrated | R95: Data
A96: Speed of adjustment parameter for atmospheric temperature | B96: 0.208 | D96: Adjusted to fit transient and equilibrium with new temperature sensitivty coefficient of 3.2 | R96: Model based
A97: Equilibrium temperature increase for CO2 doubling | B97: =+B18 -> 3.2 | D97: See above | R97: Model based
A98: FCO22x | B98: 3.8 | D98: Updated from IPCC FAR, p. 140. | R98: Model based
A99: Coefficient of heat loss from atmosphere to oceans | B99: 0.31 | D99: calibrated | R99: Model based
A100: Coefficient of heat gain by deep oceans | B100: 0.05 | D100: calibrated | R100: Model based
A101: HOTELLING PARAMETERS
A102: Coefficient of Hotelling rent on ratio | B102: 100
A103: Exponent on Hotelling | B103: 12
A104: BACKSTOP DECLINE
A105: Rate of decadal decline backstop after threshold | B105: 0.5 | D105: Assumed
A116: If damage function is on (1=yes, 0=no) | B116: 1
A118: DAMAGE FUNCTION | F118: US | G118: EU | H118: Japan | I118: Russia | J118: Eurasia | K118: China | L118: India | M118: Middle East | N118: Africa | O118: Latin America | P118: OHI | Q118: Other non-OECD Asia
A119: damage coefficient on temperature | F119: =+B146 -> 0 | G119: =+C146 -> 0 | H119: =+D146 -> 0 | I119: =+E146 -> 0 | J119: =+F146 -> 0 | K119: =+G146 -> 0.078458281 | L119: =+H146 -> 0.43852128 | M119: =+I146 -> 0.27798926 | ... Q119: =+M146 -> 0.17551223 | R119: These three parameters are fundamental for optimization, but not for basic calculations of paths
A120: damage coefficient on temperature squared | F120: =+B147 -> 0.14141261 | G120: =+C147 -> 0.15910847 | H120: =+D147 -> 0.16172344 | I120: =+E147 -> 0.11505844 | J120: =+F147 -> 0.13047244 | K120: =+G147 -> 0.12589303 | L120: =+H147 -> 0.16887308 | M120: =+I147 -> 0.15859856 | ... Q120: =+M147 -> 0.17344211 | R120: Ditto
A121: Exponent on damages | F121: 2 | G121: 2 | H121: 2 | I121: 2 | J121: 2 | K121: 2 | L121: 2 | M121: 2 | N121: 2 | O121: 2 | P121: 2 | Q121: 2 | R121: Ditto
A122: Threshold for catastrophic damages | F122: 4 | G122: 4 | H122: 4 | I122: 4 | J122: 4 | K122: 4 | L122: 4 | M122: 4 | N122: 4 | O122: 4 | P122: 4 | Q122: 4
A123: Exponent for catastrophic damages | F123: 6 | G123: 6 | H123: 6 | I123: 6 | J123: 6 | K123: 6 | L123: 6 | M123: 6 | N123: 6 | O123: 6 | P123: 6 | Q123: 6
A124: Damage rate at threshold for catastrophic damages | B124: if catast | F124: =+$C$56 -> 0 | G124: =+$C$56 -> 0 | H124: =+$C$56 -> 0 | I124: =+$C$56 -> 0 | J124: =+$C$56 -> 0 | K124: =+$C$56 -> 0 | L124: =+$C$56 -> 0 | M124: =+$C$56 -> 0 | ... Q124: =+$C$56 -> 0
A125: EXPONENT IN OMEGA FUNCTION | B125: 10
A126: SLR DAMAGES
A127: Elasticity of substitution land | B127: 4
...

Sheet Data
F1: =+E4 -> 0.015093183 | G1: =+F4 -> 0 | I1: =+Parameters!B19 -> 0.1 | L1: =+Parameters!B21 -> 0.0033 | N1: =+F1+G1 -> 0.015093183 | O1: =+$L$1+(1-$I$1)*(N1-$L$1) -> 0.013913865 | P1: =+$L$1+(1-$I$1)*(O1-$L$1) -> 0.012852479
M2: 0 | N2: 1 | O2: 2 | P2: 3 | Q2: 4 | R2: =+Q2+1 -> 5 | S2: =+R2+1 -> 6 | T2: =+S2+1 -> 7 | U2: =+T2+1 -> 8 | V2: =+U2+1 -> 9 | W2: =+V2+1 -> 10 | X2: =+W2+1 -> 11 | Y2: =+X2+1 -> 12 | ... BT2: =+BS2+1 -> 59 | BU2: 2005 | BV2: 2100 | BW2: 2200 | BX2: 2300
E3: average 95-15 | F3: adjustment | G3: Sum | H3: Sum minus long | I3: Decline rate TFP | J3: Converge ratio | K3: Converge rate | L3: Long run' | M3: 2005 | N3: =+M3+10 -> 2015 | O3: =+N3+10 -> 2025 | P3: =+O3+10 -> 2035 | Q3: =+P3+10 -> 2045 | R3: =+Q3+10 -> 2055 | S3: =+R3+10 -> 2065 | T3: =+S3+10 -> 2075 | U3: =+T3+10 -> 2085 | ... BT3: =+BS3+10 -> 2595
C4: US | E4: =+AVERAGE(E21:F21) -> 0.015093183 | F4: =+Parameters!B24 -> 0 | G4: =+E4+F4 -> 0.015093183 | H4: =+G4-L4 -> 0.011793183 | I4: =+I1 -> 0.1 | L4: =+L1 -> 0.0033 | M4: =+F108*1000 -> 41765.909 | N4: =+M4*EXP(10*(G4)) -> 48570.302 | O4: =+N4*EXP(10*$L4)*EXP(10*$H4*EXP(-$I4*(O$2-1))) -> 55852.898 | P4: =+O4*EXP(10*$L4)*EXP(10*$H4*EXP(-$I4*(P$2-1))) -> 63578.53 | Q4: =+P4*EXP(10*$L4)*EXP(10*$H4*EXP(-$I4*(Q$2-1))) -> 71710.837 | R4: =+Q4*EXP(10*$L4)*EXP(10*$H4*EXP(-$I4*(R$2-1))) -> 80213.67 | S4: =+R4*EXP(10*$L4)*EXP(10*$H4*EXP(-$I4*(S$2-1))) -> 89052.246 | T4: =+S4*EXP(10*$L4)*EXP(10*$H4*EXP(-$I4*(T$2-1))) -> 98194.047 | U4: =+T4*EXP(10*$L4)*EXP(10*$H4*EXP(-$I4*(U$2-1))) -> 107609.49 | V4: =+U4*EXP(10*$L4)*EXP(10*$H4*EXP(-$I4*(V$2-1))) -> 117272.35 | ... BT4: =+BS4*EXP(10*$L4)*EXP(10*$H4*EXP(-$I4*(BT$2-1))) -> 1007223.1 | BU4: =+M4/M$4 -> 1 | BV4: =+V4/V$4 -> 1 | BW4: =+AG4/AG$4 -> 1 | BX4: =+AQ4/AQ$4 -> 1 | BZ4: =+J4 -> 0
C5: OECD-Europe | E5: =+AVERAGE(E22:F22) -> 0.014299541 | F5: 0.002 | G5: =+E5+F5 -> 0.016299541 | H5: =+G5-L5 -> 0.012999541 | J5: =+MAX(J22+Parameters!$B$30,0.1) -> 0.9 | K5: =+Parameters!B20 -> 0.1 | L5: =+L4 -> 0.0033 | M5: =+F109*1000 -> 26589.643 | N5: =+M5*EXP(10*(G5)) -> 31296.842 | O5: =+N5*(O$4/N$4)*(N$4*$J5/N5)^$K5 -> 37212.316 | P5: =+O5*(P$4/O$4)*(O$4*$J5/O5)^$K5 -> 43652.752 | Q5: =+P5*(Q$4/P$4)*(P$4*$J5/P5)^$K5 -> 50587.134 | R5: =+Q5*(R$4/Q$4)*(Q$4*$J5/Q5)^$K5 -> 57980.558 | S5: =+R5*(S$4/R$4)*(R$4*$J5/R5)^$K5 -> 65796.036 | T5: =+S5*(T$4/S$4)*(S$4*$J5/S5)^$K5 -> 73996.091 | U5: =+T5*(U$4/T$4)*(T$4*$J5/T5)^$K5 -> 82544.106 | V5: =+U5*(V$4/U$4)*(U$4*$J5/U5)^$K5 -> 91405.396 | ... BT5: =+BS5*(BT$4/BS$4)*(BS$4*$J5/BS5)^$K5 -> 905829.04 | BU5: =+M5/M$4 -> 0.63663508 | BV5: =+V5/V$4 -> 0.77942837 | BW5: =+AG5/AG$4 -> 0.86028019 | BX5: =+AQ5/AQ$4 -> 0.88594653 | BZ5: =+J5 -> 0.9
C6: Japan | E6: =+AVERAGE(E23:F23) -> 0.010784143 | F6: 0.003 | G6: =+E6+F6 -> 0.013784143 | H6: =+G6-L6 -> 0.010484143 | J6: 0.9 | K6: =+K5 -> 0.1 | L6: =+L5 -> 0.0033 | M6: =+F110*1000 -> 30290.31 | N6: =+M6*EXP(10*(G6)) -> 34767.022 | O6: =+N6*(O$4/N$4)*(N$4*$J6/N6)^$K6 -> 40905.997 | P6: =+O6*(P$4/O$4)*(O$4*$J6/O6)^$K6 -> 47533.728 | Q6: =+P6*(Q$4/P$4)*(P$4*$J6/P6)^$K6 -> 54617.435 | R6: =+Q6*(R$4/Q$4)*(Q$4*$J6/Q6)^$K6 -> 62121.866 | S6: =+R6*(S$4/R$4)*(R$4*$J6/R6)^$K6 -> 70010.894 | T6: =+S6*(T$4/S$4)*(S$4*$J6/S6)^$K6 -> 78248.871 | U6: =+T6*(U$4/T$4)*(T$4*$J6/T6)^$K6 -> 86801.742 | V6: =+U6*(V$4/U$4)*(U$4*$J6/U6)^$K6 -> 95637.886 | ... BT6: =+BS6*(BT$4/BS$4)*(BS$4*$J6/BS6)^$K6 -> 906040.38 | BU6: =+M6/M$4 -> 0.72524005 | BV6: =+V6/V$4 -> 0.81551949 | BW6: =+AG6/AG$4 -> 0.87258723 | BX6: =+AQ6/AQ$4 -> 0.89034533 | BZ6: =+J6 -> 0.9
C7: Russia | E7: =+AVERAGE(E24:F24) -> 0.040982313 | F7: -0.015 | G7: =+E7+F7 -> 0.025982313 | H7: =+G7-L7 -> 0.022682313 | J7: 0.6 | K7: =+K6 -> 0.1 | L7: =+L6 -> 0.0033 | M7: =+F111*1000 -> 11861.381 | N7: =+M7*EXP(10*(G7)) -> 15380.661 | O7: =+N7*(O$4/N$4)*(N$4*$J7/N7)^$K7 -> 18854.049 | P7: =+O7*(P$4/O$4)*(O$4*$J7/O7)^$K7 -> 22732.575 | Q7: =+P7*(Q$4/P$4)*(P$4*$J7/P7)^$K7 -> 27002.517 | R7: =+Q7*(R$4/Q$4)*(Q$4*$J7/Q7)^$K7 -> 31644.703 | S7: =+R7*(S$4/R$4)*(R$4*$J7/R7)^$K7 -> 36635.943 | T7: =+S7*(T$4/S$4)*(S$4*$J7/S7)^$K7 -> 41950.441 | U7: =+T7*(U$4/T$4)*(T$4*$J7/T7)^$K7 -> 47561.103 | V7: =+U7*(V$4/U$4)*(U$4*$J7/U7)^$K7 -> 53440.679 | ... BT7: =+BS7*(BT$4/BS$4)*(BS$4*$J7/BS7)^$K7 -> 603477.62 | BU7: =+M7/M$4 -> 0.28399671 | BV7: =+V7/V$4 -> 0.45569719 | BW7: =+AG7/AG$4 -> 0.55037508 | BX7: =+AQ7/AQ$4 -> 0.58220835 | BZ7: =+J7 -> 0.6
C8: Non-Russia Eurasia | E8: =+AVERAGE(E25:F25) -> 0.03969822 | F8: -0.015 | G8: =+E8+F8 -> 0.02469822 | H8: =+G8-L8 -> 0.02139822 | J8: =+MAX(J25+Parameters!$B$30,0.1) -> 0.6 | K8: =+K7 -> 0.1 | L8: =+L7 -> 0.0033 | M8: =+F112*1000 -> 5177.134 | N8: =+M8*EXP(10*(G8)) -> 6627.5408 | O8: =+N8*(O$4/N$4)*(N$4*$J8/N8)^$K8 -> 8837.8023 | P8: =+O8*(P$4/O$4)*(O$4*$J8/O8)^$K8 -> 11494.612 | Q8: =+P8*(Q$4/P$4)*(P$4*$J8/P8)^$K8 -> 14617.24 | R8: =+Q8*(R$4/Q$4)*(Q$4*$J8/Q8)^$K8 -> 18214.449 | S8: =+R8*(S$4/R$4)*(R$4*$J8/R8)^$K8 -> 22284.91 | T8: =+S8*(T$4/S$4)*(S$4*$J8/S8)^$K8 -> 26818.204 | U8: =+T8*(U$4/T$4)*(T$4*$J8/T8)^$K8 -> 31796.24 | V8: =+U8*(V$4/U$4)*(U$4*$J8/U8)^$K8 -> 37194.903 | ... BT8: =+BS8*(BT$4/BS$4)*(BS$4*$J8/BS8)^$K8 -> 602351.54 | BU8: =+M8/M$4 -> 0.12395597 | BV8: =+V8/V$4 -> 0.31716686 | BW8: =+AG8/AG$4 -> 0.49121155 | BX8: =+AQ8/AQ$4 -> 0.55957349 | BZ8: =+J8 -> 0.6
C9: China | E9: =+AVERAGE(E26:F26) -> 0.081398792 | F9: -0.01 | G9: =+E9+F9 -> 0.071398792 | H9: =+G9-L9 -> 0.068098792 | J9: 0.6 | K9: =+K8 -> 0.1 | L9: =+L8 -> 0.0033 | M9: =+F113*1000 -> 4088.3348 | N9: =+M9*EXP(10*(G9)) -> 8348.8656 | O9: =+N9*(O$4/N$4)*(N$4*$J9/N9)^$K9 -> 10879.072 | P9: =+O9*(P$4/O$4)*(O$4*$J9/O9)^$K9 -> 13858.528 | Q9: =+P9*(Q$4/P$4)*(P$4*$J9/P9)^$K9 -> 17296.805 | R9: =+Q9*(R$4/Q$4)*(Q$4*$J9/Q9)^$K9 -> 21193.686 | S9: =+R9*(S$4/R$4)*(R$4*$J9/R9)^$K9 -> 25540.083 | T9: =+S9*(T$4/S$4)*(S$4*$J9/S9)^$K9 -> 30319.356 | U9: =+T9*(U$4/T$4)*(T$4*$J9/T9)^$K9 -> 35508.883 | V9: =+U9*(V$4/U$4)*(U$4*$J9/U9)^$K9 -> 41081.714 | ... BT9: =+BS9*(BT$4/BS$4)*(BS$4*$J9/BS9)^$K9 -> 602660.17 | BU9: =+M9/M$4 -> 0.097886886 | BV9: =+V9/V$4 -> 0.35031032 | BW9: =+AG9/AG$4 -> 0.5067739 | BX9: =+AQ9/AQ$4 -> 0.56569223 | BZ9: =+J9 -> 0.6
C10: India | E10: =+AVERAGE(E27:F27) -> 0.050495488 | F10: -0.005 | G10: =+E10+F10 -> 0.045495488 | H10: =+G10-L10 -> 0.042195488 | J10: 0.5 | K10: =+K9 -> 0.1 | L10: =+L9 -> 0.0033 | M10: =+F114*1000 -> 2229.9191 | N10: =+M10*EXP(10*(G10)) -> 3514.5805 | O10: =+N10*(O$4/N$4)*(N$4*$J10/N10)^$K10 -> 4903.3753 | P10: =+O10*(P$4/O$4)*(O$4*$J10/O10)^$K10 -> 6642.2002 | Q10: =+P10*(Q$4/P$4)*(P$4*$J10/P10)^$K10 -> 8761.594 | R10: =+Q10*(R$4/Q$4)*(Q$4*$J10/Q10)^$K10 -> 11283.501 | S10: =+R10*(S$4/R$4)*(R$4*$J10/R10)^$K10 -> 14220.597 | T10: =+S10*(T$4/S$4)*(S$4*$J10/S10)^$K10 -> 17576.314 | U10: =+T10*(U$4/T$4)*(T$4*$J10/T10)^$K10 -> 21345.481 | V10: =+U10*(V$4/U$4)*(U$4*$J10/U10)^$K10 -> 25515.405 | ... BT10: =+BS10*(BT$4/BS$4)*(BS$4*$J10/BS10)^$K10 -> 501456.53 | BU10: =+M10/M$4 -> 0.05339089 | BV10: =+V10/V$4 -> 0.21757393 | BW10: =+AG10/AG$4 -> 0.38509725 | BX10: =+AQ10/AQ$4 -> 0.45648868 | BZ10: =+J10 -> 0.5
C11: Middle East | E11: =+AVERAGE(E28:F28) -> 0.023533797 | F11: 0 | G11: =+E11+F11 -> 0.023533797 | H11: =+G11-L11 -> 0.020233797 | J11: 0.5 | K11: =+K10 -> 0.1 | L11: =+L10 -> 0.0033 | M11: =+F115*1000 -> 8431.116 | N11: =+M11*EXP(10*(G11)) -> 10668.198 | O11: =+N11*(O$4/N$4)*(N$4*$J11/N11)^$K11 -> 13319.592 | P11: =+O11*(P$4/O$4)*(O$4*$J11/O11)^$K11 -> 16327.067 | Q11: =+P11*(Q$4/P$4)*(P$4*$J11/P11)^$K11 -> 19684.289 | R11: =+Q11*(R$4/Q$4)*(Q$4*$J11/Q11)^$K11 -> 23379.048 | S11: =+R11*(S$4/R$4)*(R$4*$J11/R11)^$K11 -> 27394.443 | T11: =+S11*(T$4/S$4)*(S$4*$J11/S11)^$K11 -> 31710.128 | U11: =+T11*(U$4/T$4)*(T$4*$J11/T11)^$K11 -> 36303.551 | V11: =+U11*(V$4/U$4)*(U$4*$J11/U11)^$K11 -> 41151.088 | ... BT11: =+BS11*(BT$4/BS$4)*(BS$4*$J11/BS11)^$K11 -> 502693.31 | BU11: =+M11/M$4 -> 0.20186598 | BV11: =+V11/V$4 -> 0.35090188 | BW11: =+AG11/AG$4 -> 0.44741533 | BX11: =+AQ11/AQ$4 -> 0.48099779 | BZ11: =+J11 -> 0.5
C12: Africa | E12: =+AVERAGE(E29:F29) -> 0.026482695 | F12: 0.01 | G12: =+E12+F12 -> 0.036482695 | H12: =+G12-L12 -> 0.033182695 | J12: 0.4 | K12: =+K11 -> 0.1 | L12: =+L11 -> 0.0033 | M12: =+F116*1000 -> 1703.3657 | N12: =+M12*EXP(10*(G12)) -> 2453.2976 | O12: =+N12*(O$4/N$4)*(N$4*$J12/N12)^$K12 -> 3469.7102 | P12: =+O12*(P$4/O$4)*(O$4*$J12/O12)^$K12 -> 4758.1619 | Q12: =+P12*(Q$4/P$4)*(P$4*$J12/P12)^$K12 -> 6346.0963 | R12: =+Q12*(R$4/Q$4)*(Q$4*$J12/Q12)^$K12 -> 8254.3725 | S12: =+R12*(S$4/R$4)*(R$4*$J12/R12)^$K12 -> 10496.463 | T12: =+S12*(T$4/S$4)*(S$4*$J12/S12)^$K12 -> 13078.245 | U12: =+T12*(U$4/T$4)*(T$4*$J12/T12)^$K12 -> 15998.322 | V12: =+U12*(V$4/U$4)*(U$4*$J12/U12)^$K12 -> 19248.775 | ... BT12: =+BS12*(BT$4/BS$4)*(BS$4*$J12/BS12)^$K12 -> 401043.89 | BU12: =+M12/M$4 -> 0.040783638 | BV12: =+V12/V$4 -> 0.16413737 | BW12: =+AG12/AG$4 -> 0.30245556 | BX12: =+AQ12/AQ$4 -> 0.36285322 | BZ12: =+J12 -> 0.4
C13: Latin America | E13: =+AVERAGE(E30:F30) -> 0.01926661 | F13: 0.01 | G13: =+E13+F13 -> 0.02926661 | H13: =+G13-L13 -> 0.02596661 | J13: 0.7 | K13: =+K12 -> 0.1 | L13: =+L12 -> 0.0033 | M13: =+F117*1000 -> 8207.8498 | N13: =+M13*EXP(10*(G13)) -> 10998.48 | O13: =+N13*(O$4/N$4)*(N$4*$J13/N13)^$K13 -> 14158.629 | P13: =+O13*(P$4/O$4)*(O$4*$J13/O13)^$K13 -> 17840.138 | Q13: =+P13*(Q$4/P$4)*(P$4*$J13/P13)^$K13 -> 22048.221 | R13: =+Q13*(R$4/Q$4)*(Q$4*$J13/Q13)^$K13 -> 26777.38 | S13: =+R13*(S$4/R$4)*(R$4*$J13/R13)^$K13 -> 32012.708 | T13: =+S13*(T$4/S$4)*(S$4*$J13/S13)^$K13 -> 37731.558 | U13: =+T13*(U$4/T$4)*(T$4*$J13/T13)^$K13 -> 43905.405 | V13: =+U13*(V$4/U$4)*(U$4*$J13/U13)^$K13 -> 50501.713 | ... BT13: =+BS13*(BT$4/BS$4)*(BS$4*$J13/BS13)^$K13 -> 703293.05 | BU13: =+M13/M$4 -> 0.19652032 | BV13: =+V13/V$4 -> 0.43063616 | BW13: =+AG13/AG$4 -> 0.6010186 | BX13: =+AQ13/AQ$4 -> 0.6637614 | BZ13: =+J13 -> 0.7
C14: OHI | E14: =+AVERAGE(E31:F31) -> 0.023825929 | F14: -0.005 | G14: =+E14+F14 -> 0.018825929 | H14: =+G14-L14 -> 0.015525929 | J14: 0.9 | K14: =+K13 -> 0.1 | L14: =+L13 -> 0.0033 | M14: =+F118*1000 -> 29744.22 | N14: =+M14*EXP(10*(G14)) -> 35905.631 | O14: =+N14*(O$4/N$4)*(N$4*$J14/N14)^$K14 -> 42109.738 | P14: =+O14*(P$4/O$4)*(O$4*$J14/O14)^$K14 -> 48790.793 | Q14: =+P14*(Q$4/P$4)*(P$4*$J14/P14)^$K14 -> 55915.692 | R14: =+Q14*(R$4/Q$4)*(Q$4*$J14/Q14)^$K14 -> 63449.274 | S14: =+R14*(S$4/R$4)*(R$4*$J14/R14)^$K14 -> 71355.848 | T14: =+S14*(T$4/S$4)*(S$4*$J14/S14)^$K14 -> 79600.471 | U14: =+T14*(U$4/T$4)*(T$4*$J14/T14)^$K14 -> 88149.984 | V14: =+U14*(V$4/U$4)*(U$4*$J14/U14)^$K14 -> 96973.794 | ... BT14: =+BS14*(BT$4/BS$4)*(BS$4*$J14/BS14)^$K14 -> 906105.16 | BU14: =+M14/M$4 -> 0.71216503 | BV14: =+V14/V$4 -> 0.82691099 | BW14: =+AG14/AG$4 -> 0.87639397 | BX14: =+AQ14/AQ$4 -> 0.89169775 | BZ14: =+J14 -> 0.9
C15: Other non-OECD Asia | E15: =+AVERAGE(E32:F32) -> 0.027948055 | F15: 0 | G15: =+E15+F15 -> 0.027948055 | H15: =+G15-L15 -> 0.024648055 | J15: 0.6 | K15: =+K14 -> 0.1 | L15: =+L14 -> 0.0033 | M15: =+F119*1000 -> 2794.7088 | N15: =+M15*EXP(10*(G15)) -> 3695.8423 | O15: =+N15*(O$4/N$4)*(N$4*$J15/N15)^$K15 -> 5224.7943 | P15: =+O15*(P$4/O$4)*(O$4*$J15/O15)^$K15 -> 7162.2049 | Q15: =+P15*(Q$4/P$4)*(P$4*$J15/P15)^$K15 -> 9549.1025 | R15: =+Q15*(R$4/Q$4)*(Q$4*$J15/Q15)^$K15 -> 12416.623 | S15: =+R15*(S$4/R$4)*(R$4*$J15/R15)^$K15 -> 15784.819 | T15: =+S15*(T$4/S$4)*(S$4*$J15/S15)^$K15 -> 19662.355 | U15: =+T15*(U$4/T$4)*(T$4*$J15/T15)^$K15 -> 24047.007 | V15: =+U15*(V$4/U$4)*(U$4*$J15/U15)^$K15 -> 28926.785 | ... BT15: =+BS15*(BT$4/BS$4)*(BS$4*$J15/BS15)^$K15 -> 601571.59 | BU15: =+M15/M$4 -> 0.066913636 | BV15: =+V15/V$4 -> 0.2466633 | BW15: =+AG15/AG$4 -> 0.45394758 | BX15: =+AQ15/AQ$4 -> 0.54439034 | BZ15: =+J15 -> 0.6
C16: World | J16: =+AVERAGE(J5:J15) -> 0.65454545 | L16: World (2005 pop wt) | M16: =+SUMPRODUCT(M4:M15*$A$21:$A32)/SUM($A$21:$A$32) -> 8638.2595 | N16: =+SUMPRODUCT(N4:N15*$A$21:$A32)/SUM($A$21:$A$32) -> 11333.513 | O16: =+SUMPRODUCT(O4:O15*$A$21:$A32)/SUM($A$21:$A$32) -> 14042.617 | P16: =+SUMPRODUCT(P4:P15*$A$21:$A32)/SUM($A$21:$A$32) -> 17163.006 | Q16: =+SUMPRODUCT(Q4:Q15*$A$21:$A32)/SUM($A$21:$A$32) -> 20705.938 | R16: =+SUMPRODUCT(R4:R15*$A$21:$A32)/SUM($A$21:$A$32) -> 24674.922 | S16: =+SUMPRODUCT(S4:S15*$A$21:$A32)/SUM($A$21:$A$32) -> 29066 | T16: =+SUMPRODUCT(T4:T15*$A$21:$A32)/SUM($A$21:$A$32) -> 33868.454 | ... BT16: =+SUMPRODUCT(BT4:BT15*$A$21:$A32)/SUM($A$21:$A$32) -> 617571.07
J17: =+STDEV(J5:J15) -> 0.17529196
E18: [macro_072309.xlsx]newpcGDP'!E38 | M18: TFP
E19: p.c. GDP growth from data and IMF projections
A20: Population 2005 | E20: 1995-05 | F20: 2005-2015 | N20: 21c | O20: 22c
A21: 296.84258 | C21: US | E21: 0.021372937 | F21: 0.0088134301 | M21: US | N21: =+LN(W4/M4)/100 -> 0.011133661 | O21: =+LN(AG4/W4)/100 -> 0.0061818427 | P21: =+LN(AQ4/AG4)/100 -> 0.0043601707
A22: 490.08019 | C22: OECD-Europe | E22: 0.019405919 | F22: 0.0091931642 | J22: 0.9 | M22: OECD-Europe | N22: =+LN(W5/M5)/100 -> 0.013301136 | O22: =+LN(AG5/W5)/100 -> 0.0070249822 | P22: =+LN(AQ5/AG5)/100 -> 0.0046541552
A23: 127.773 | C23: Japan | E23: 0.0094777509 | F23: 0.012090535 | J23: 0.85 | M23: Japan | N23: =+LN(W6/M6)/100 -> 0.012405456 | O23: =+LN(AG6/W6)/100 -> 0.0067596463 | P23: =+LN(AQ6/AG6)/100 -> 0.0045616383
A24: 143.15 | C24: Russia | E24: 0.041235271 | F24: 0.040729354 | J24: 0.5 | M24: Russia | N24: =+LN(W7/M7)/100 -> 0.01613742 | O24: =+LN(AG7/W7)/100 -> 0.0077944564 | P24: =+LN(AQ7/AG7)/100 -> 0.0049224543
A25: 155.94247 | C25: Non-Russia Eurasia | E25: 0.038240844 | F25: 0.041155595 | J25: 0.6 | M25: Non-Russia Eurasia | N25: =+LN(W8/M8)/100 -> 0.021166178 | O25: =+LN(AG8/W8)/100 -> 0.0099188097 | P25: =+LN(AQ8/AG8)/100 -> 0.0056631705
A26: 1304.5 | C26: China | E26: 0.079109032 | F26: 0.083688552 | J26: 0.5 | M26: China | N26: =+LN(W9/M9)/100 -> 0.024421839 | O26: =+LN(AG9/W9)/100 -> 0.009336188 | P26: =+LN(AQ9/AG9)/100 -> 0.0054600229
A27: 1094.583 | C27: India | E27: 0.04589835 | F27: 0.055092625 | J27: 0.4 | M27: India | N27: =+LN(W10/M10)/100 -> 0.026014716 | O27: =+LN(AG10/W10)/100 -> 0.011059345 | P27: =+LN(AQ10/AG10)/100 -> 0.0060608507
A28: 412.769 | C28: Middle East | E28: 0.021206492 | F28: 0.025861103 | J28: 0.4 | M28: Middle East | N28: =+LN(W11/M11)/100 -> 0.017016789 | O28: =+LN(AG11/W11)/100 -> 0.0082575479 | P28: =+LN(AQ11/AG11)/100 -> 0.0050839243
A29: 763.50611 | C29: Africa | E29: 0.021621116 | F29: 0.031344274 | J29: 0.35 | M29: Africa | N29: =+LN(W12/M12)/100 -> 0.025948649 | O29: =+LN(AG12/W12)/100 -> 0.011403388 | P29: =+LN(AQ12/AG12)/100 -> 0.0061808111
A30: 555.38008 | C30: Latin America | E30: 0.013704364 | F30: 0.024828856 | J30: 0.5 | M30: Latin America | N30: =+LN(W13/M13)/100 -> 0.019464455 | O30: =+LN(AG13/W13)/100 -> 0.0090296492 | P30: =+LN(AQ13/AG13)/100 -> 0.0053531394
A31: 129.16962 | C31: OHI | E31: 0.028315553 | F31: 0.019336306 | J31: 0.85 | M31: OHI | N31: =+LN(W14/M14)/100 -> 0.012712232 | O31: =+LN(AG14/W14)/100 -> 0.0066783317 | P31: =+LN(AQ14/AG14)/100 -> 0.0045332857
A32: 937.19557 | C32: Other non-OECD Asia | E32: 0.020751458 | F32: 0.035144651 | J32: 0.5 | M32: Other non-OECD Asia | N32: =+LN(W15/M15)/100 -> 0.025068781 | O32: =+LN(AG15/W15)/100 -> 0.011392512 | P32: =+LN(AQ15/AG15)/100 -> 0.0061770187
A33: 6418.8626 | C33: World | M33: World
D34: =+LN(Parameters!B27)/20 -> 0 | E34: =+LN(Parameters!B27) -> 0
A36: Populati0n growth with uncertainty
A37: Population growth projections (Mark) | B37: 2015 | C37: 2025 | D37: 2035 | E37: 2045 | F37: 2055 | G37: 2065 | H37: 2075 | I37: 2085 | J37: 2095 | K37: 2105 | L37: 2115 | M37: 2125 | N37: 2135 | O37: 2145 | P37: 2155 | Q37: 2165 | R37: 2175 | S37: 2185 | T37: 2195 | U37: 2205 | V37: 2215 | W37: 2225 | X37: 2235 | Y37: 2245 | Z37: 2255 | AA37: 2265 | AB37: 2275 | AC37: 2285 | AD37: 2295 | AE37: 2305
A38: US | B38: =+B375 -> 0.0093279314 | C38: =+C375+LN(Parameters!$B$27)/200 -> 0.0076456914 | D38: =+D375+LN(Parameters!$B$27)/200 -> 0.0057596483 | E38: =+E375+LN(Parameters!$B$27)/200 -> 0.0043177913 | F38: =+F375+LN(Parameters!$B$27)/200 -> 0.0024627299 | G38: =+G375+LN(Parameters!$B$27)/200 -> 0.0013456355 | H38: =+H375+LN(Parameters!$B$27)/200 -> 0.0013456355 | I38: =+I375+LN(Parameters!$B$27)/200 -> 0.0013456355 | J38: =+J375+LN(Parameters!$B$27)/200 -> 0.0013456355 | ... V38: =+V375+LN(Parameters!$B$27)/200 -> 0.00047770103 | W38: 0.00047770103 | X38: 0.00047770103 | Y38: 0.00047770103 | Z38: 0.00047770103 | AA38: 0.00047770103 | AB38: 0.00047770103 | AC38: 0.00047770103 | AD38: 0.00047770103 | AE38: 0.00023885051
A39: OECD-Europe | B39: =+B376 -> 0.0043457149 | C39: =+C376+LN(Parameters!$B$27)/200 -> 0.0023580396 | D39: =+D376+LN(Parameters!$B$27)/200 -> 0.00096646886 | E39: =+E376+LN(Parameters!$B$27)/200 -> -1.0403662e-06 | F39: =+F376+LN(Parameters!$B$27)/200 -> -0.001550573 | G39: =+G376+LN(Parameters!$B$27)/200 -> -0.0023819981 | H39: =+H376+LN(Parameters!$B$27)/200 -> -0.0023819981 | I39: =+I376+LN(Parameters!$B$27)/200 -> -0.0023819981 | J39: =+J376+LN(Parameters!$B$27)/200 -> -0.0023819981 | ... V39: =+V376+LN(Parameters!$B$27)/200 -> 0.00062793446 | W39: 0.00062793446 | X39: 0.00062793446 | Y39: 0.00062793446 | Z39: 0.00062793446 | AA39: 0.00062793446 | AB39: 0.00062793446 | AC39: 0.00062793446 | AD39: 0.00062793446 | AE39: 0.00031396723
A40: Japan | B40: =+B377 -> -0.0013094485 | C40: =+C377+LN(Parameters!$B$27)/200 -> -0.0040543463 | D40: =+D377+LN(Parameters!$B$27)/200 -> -0.0060224741 | E40: =+E377+LN(Parameters!$B$27)/200 -> -0.0072870345 | F40: =+F377+LN(Parameters!$B$27)/200 -> -0.005930006 | G40: =+G377+LN(Parameters!$B$27)/200 -> -0.0039881769 | H40: =+H377+LN(Parameters!$B$27)/200 -> -0.0039881769 | I40: =+I377+LN(Parameters!$B$27)/200 -> -0.0039881769 | J40: =+J377+LN(Parameters!$B$27)/200 -> -0.0039881769 | ... V40: =+V377+LN(Parameters!$B$27)/200 -> 0.00061680665 | W40: 0.00061680665 | X40: 0.00061680665 | Y40: 0.00061680665 | Z40: 0.00061680665 | AA40: 0.00061680665 | AB40: 0.00061680665 | AC40: 0.00061680665 | AD40: 0.00061680665 | AE40: 0.00030840333
A41: Russia | B41: =+B378 -> -0.0036902246 | C41: =+C378+LN(Parameters!$B$27)/200 -> -0.004171834 | D41: =+D378+LN(Parameters!$B$27)/200 -> -0.0054007195 | E41: =+E378+LN(Parameters!$B$27)/200 -> -0.0051458271 | F41: =+F378+LN(Parameters!$B$27)/200 -> -0.0049860706 | G41: =+G378+LN(Parameters!$B$27)/200 -> -0.0048680141 | H41: =+H378+LN(Parameters!$B$27)/200 -> -0.0048680141 | I41: =+I378+LN(Parameters!$B$27)/200 -> -0.0048680141 | J41: =+J378+LN(Parameters!$B$27)/200 -> -0.0048680141 | ... V41: =+V378+LN(Parameters!$B$27)/200 -> 0.00054989085 | W41: 0.00054989085 | X41: 0.00054989085 | Y41: 0.00054989085 | Z41: 0.00054989085 | AA41: 0.00054989085 | AB41: 0.00054989085 | AC41: 0.00054989085 | AD41: 0.00054989085 | AE41: 0.00027494543
A42: Non-Russia Eurasia | B42: =+B379 -> 0.0011403127 | C42: =+C379+LN(Parameters!$B$27)/200 -> 0.00094506994 | D42: =+D379+LN(Parameters!$B$27)/200 -> -0.00090942424 | E42: =+E379+LN(Parameters!$B$27)/200 -> -0.0018225701 | F42: =+F379+LN(Parameters!$B$27)/200 -> -0.0029607997 | G42: =+G379+LN(Parameters!$B$27)/200 -> -0.0032973624 | H42: =+H379+LN(Parameters!$B$27)/200 -> -0.0032973624 | I42: =+I379+LN(Parameters!$B$27)/200 -> -0.0032973624 | J42: =+J379+LN(Parameters!$B$27)/200 -> -0.0032973624 | ... V42: =+V379+LN(Parameters!$B$27)/200 -> 0.00053425664 | W42: 0.00053425664 | X42: 0.00053425664 | Y42: 0.00053425664 | Z42: 0.00053425664 | AA42: 0.00053425664 | AB42: 0.00053425664 | AC42: 0.00053425664 | AD42: 0.00053425664 | AE42: 0.00026712832
A43: China | B43: =+B380 -> 0.0061864064 | C43: =+C380+LN(Parameters!$B$27)/200 -> 0.0040117161 | D43: =+D380+LN(Parameters!$B$27)/200 -> 0.00063186823 | E43: =+E380+LN(Parameters!$B$27)/200 -> -0.0015201627 | F43: =+F380+LN(Parameters!$B$27)/200 -> -0.0032894423 | G43: =+G380+LN(Parameters!$B$27)/200 -> -0.0033248705 | H43: =+H380+LN(Parameters!$B$27)/200 -> -0.0033248705 | I43: =+I380+LN(Parameters!$B$27)/200 -> -0.0033248705 | J43: =+J380+LN(Parameters!$B$27)/200 -> -0.0033248705 | ... V43: =+V380+LN(Parameters!$B$27)/200 -> 0.00068017783 | W43: 0.00068017783 | X43: 0.00068017783 | Y43: 0.00068017783 | Z43: 0.00068017783 | AA43: 0.00068017783 | AB43: 0.00068017783 | AC43: 0.00068017783 | AD43: 0.00068017783 | AE43: 0.00034008891
A44: Inida | B44: =+B381 -> 0.013512218 | C44: =+C381+LN(Parameters!$B$27)/200 -> 0.0100677 | D44: =+D381+LN(Parameters!$B$27)/200 -> 0.006531694 | E44: =+E381+LN(Parameters!$B$27)/200 -> 0.0042273229 | F44: =+F381+LN(Parameters!$B$27)/200 -> 0.0007548408 | G44: =+G381+LN(Parameters!$B$27)/200 -> -0.00097790212 | H44: =+H381+LN(Parameters!$B$27)/200 -> -0.00097790212 | I44: =+I381+LN(Parameters!$B$27)/200 -> -0.00097790212 | J44: =+J381+LN(Parameters!$B$27)/200 -> -0.00097790212 | ... V44: =+V381+LN(Parameters!$B$27)/200 -> 0.00050211246 | W44: 0.00050211246 | X44: 0.00050211246 | Y44: 0.00050211246 | Z44: 0.00050211246 | AA44: 0.00050211246 | AB44: 0.00050211246 | AC44: 0.00050211246 | AD44: 0.00050211246 | AE44: 0.00025105623
A45: Middle East | B45: =+B382 -> 0.019035212 | C45: =+C382+LN(Parameters!$B$27)/200 -> 0.015401214 | D45: =+D382+LN(Parameters!$B$27)/200 -> 0.011886693 | E45: =+E382+LN(Parameters!$B$27)/200 -> 0.0091450618 | F45: =+F382+LN(Parameters!$B$27)/200 -> 0.00520923 | G45: =+G382+LN(Parameters!$B$27)/200 -> 0.0034676113 | H45: =+H382+LN(Parameters!$B$27)/200 -> 0.0034676113 | I45: =+I382+LN(Parameters!$B$27)/200 -> 0.0034676113 | J45: =+J382+LN(Parameters!$B$27)/200 -> 0.0034676113 | ... V45: =+V382+LN(Parameters!$B$27)/200 -> 0.00046369668 | W45: 0.00046369668 | X45: 0.00046369668 | Y45: 0.00046369668 | Z45: 0.00046369668 | AA45: 0.00046369668 | AB45: 0.00046369668 | AC45: 0.00046369668 | AD45: 0.00046369668 | AE45: 0.00023184834
A46: Africa | B46: =+B383 -> 0.021463179 | C46: =+C383+LN(Parameters!$B$27)/200 -> 0.018421026 | D46: =+D383+LN(Parameters!$B$27)/200 -> 0.015283678 | E46: =+E383+LN(Parameters!$B$27)/200 -> 0.012573477 | F46: =+F383+LN(Parameters!$B$27)/200 -> 0.0069549831 | G46: =+G383+LN(Parameters!$B$27)/200 -> 0.0034642864 | H46: =+H383+LN(Parameters!$B$27)/200 -> 0.0034642864 | I46: =+I383+LN(Parameters!$B$27)/200 -> 0.0034642864 | J46: =+J383+LN(Parameters!$B$27)/200 -> 0.0034642864 | ... V46: =+V383+LN(Parameters!$B$27)/200 -> -0.00049261325 | W46: 0.00050738675 | X46: 0.00050738675 | Y46: 0.00050738675 | Z46: 0.00050738675 | AA46: 0.00050738675 | AB46: 0.00050738675 | AC46: 0.00050738675 | AD46: 0.00050738675 | AE46: 0.00025369337
A47: Latin America | B47: =+B384 -> 0.010561602 | C47: =+C384+LN(Parameters!$B$27)/200 -> 0.0079330626 | D47: =+D384+LN(Parameters!$B$27)/200 -> 0.0053270953 | E47: =+E384+LN(Parameters!$B$27)/200 -> 0.0027395642 | F47: =+F384+LN(Parameters!$B$27)/200 -> 4.3227803e-06 | G47: =+G384+LN(Parameters!$B$27)/200 -> -0.00093967139 | H47: =+H384+LN(Parameters!$B$27)/200 -> -0.00093967139 | I47: =+I384+LN(Parameters!$B$27)/200 -> -0.00093967139 | J47: =+J384+LN(Parameters!$B$27)/200 -> -0.00093967139 | ... V47: =+V384+LN(Parameters!$B$27)/200 -> 0.00059727257 | W47: 0.00059727257 | X47: 0.00059727257 | Y47: 0.00059727257 | Z47: 0.00059727257 | AA47: 0.00059727257 | AB47: 0.00059727257 | AC47: 0.00059727257 | AD47: 0.00059727257 | AE47: 0.00029863628
A48: OHI | B48: 0.007273531 | C48: 0.005337856 | D48: 0.003151669 | E48: 0.0009233879 | F48: -0.0013429722 | G48: =+G385+LN(Parameters!$B$27)/200 -> -0.0025633552 | H48: =+H385+LN(Parameters!$B$27)/200 -> -0.0025633552 | I48: =+I385+LN(Parameters!$B$27)/200 -> -0.0025633552 | J48: =+J385+LN(Parameters!$B$27)/200 -> -0.0025633552 | K48: =+K385+LN(Parameters!$B$27)/200 -> -0.0010205071 | L48: =+L385+LN(Parameters!$B$27)/200 -> 0.0005223409 | M48: =+M385+LN(Parameters!$B$27)/200 -> 0.0005223409 | N48: =+N385+LN(Parameters!$B$27)/200 -> 0.0005223409 | ... V48: =+V385+LN(Parameters!$B$27)/200 -> 0.00060334695 | W48: 0.00060334695 | X48: 0.00060334695 | Y48: 0.00060334695 | Z48: 0.00060334695 | AA48: 0.00060334695 | AB48: 0.00060334695 | AC48: 0.00060334695 | AD48: 0.00060334695 | AE48: 0.00030167348
A49: Other non-OECD Asia | B49: 0.014276193 | C49: 0.011656208 | D49: 0.0089367235 | E49: 0.0064426527 | F49: 0.0026853765 | G49: =+G386+LN(Parameters!$B$27)/200 -> 0.00074677572 | H49: =+H386+LN(Parameters!$B$27)/200 -> 0.00074677572 | I49: =+I386+LN(Parameters!$B$27)/200 -> 0.00074677572 | J49: =+J386+LN(Parameters!$B$27)/200 -> 0.00074677572 | K49: =+K386+LN(Parameters!$B$27)/200 -> -0.00014462912 | L49: =+L386+LN(Parameters!$B$27)/200 -> -0.001036034 | M49: =+M386+LN(Parameters!$B$27)/200 -> -0.001036034 | N49: =+N386+LN(Parameters!$B$27)/200 -> -0.001036034 | ... V49: =+V386+LN(Parameters!$B$27)/200 -> 0.00049177949 | W49: 0.00049177949 | X49: 0.00049177949 | Y49: 0.00049177949 | Z49: 0.00049177949 | AA49: 0.00049177949 | AB49: 0.00049177949 | AC49: 0.00049177949 | AD49: 0.00049177949 | AE49: 0.00024588975
A53: tfp growth
A54: US | C54: =+LN(N4/M4)*0.1*(1-Parameters!$F$35) -> 0.010565228 | D54: =+LN(O4/N4)*0.1*(1-Parameters!$F$35) -> 0.0097796395 | E54: =+LN(P4/O4)*0.1*(1-Parameters!$F$35) -> 0.0090688094 | F54: =+LN(Q4/P4)*0.1*(1-Parameters!$F$35) -> 0.0084256236 | G54: =+LN(R4/Q4)*0.1*(1-Parameters!$F$35) -> 0.0078436451 | H54: =+LN(S4/R4)*0.1*(1-Parameters!$F$35) -> 0.0073170491 | I54: =+LN(T4/S4)*0.1*(1-Parameters!$F$35) -> 0.0068405654 | J54: =+LN(U4/T4)*0.1*(1-Parameters!$F$35) -> 0.0064094251 | ... BI54: =+LN(BT4/BS4)*0.1*(1-Parameters!$F$35) -> 0.0023349932
A55: OECD-Europe | C55: =+LN(N5/M5)*0.1*(1-Parameters!$F$35) -> 0.011409679 | D55: =+LN(O5/N5)*0.1*(1-Parameters!$F$35) -> 0.012118581 | E55: =+LN(P5/O5)*0.1*(1-Parameters!$F$35) -> 0.011173857 | F55: =+LN(Q5/P5)*0.1*(1-Parameters!$F$35) -> 0.010320167 | G55: =+LN(R5/Q5)*0.1*(1-Parameters!$F$35) -> 0.0095487337 | H55: =+LN(S5/R5)*0.1*(1-Parameters!$F$35) -> 0.0088516289 | I55: =+LN(T5/S5)*0.1*(1-Parameters!$F$35) -> 0.0082216872 | J55: =+LN(U5/T5)*0.1*(1-Parameters!$F$35) -> 0.0076524347 | ... BI55: =+LN(BT5/BS5)*0.1*(1-Parameters!$F$35) -> 0.0023407587
A56: Japan | C56: =+LN(N6/M6)*0.1*(1-Parameters!$F$35) -> 0.0096489002 | D56: =+LN(O6/N6)*0.1*(1-Parameters!$F$35) -> 0.011382517 | E56: =+LN(P6/O6)*0.1*(1-Parameters!$F$35) -> 0.010511399 | F56: =+LN(Q6/P6)*0.1*(1-Parameters!$F$35) -> 0.0097239542 | G56: =+LN(R6/Q6)*0.1*(1-Parameters!$F$35) -> 0.0090121426 | H56: =+LN(S6/R6)*0.1*(1-Parameters!$F$35) -> 0.0083686969 | I56: =+LN(T6/S6)*0.1*(1-Parameters!$F$35) -> 0.0077870484 | J56: =+LN(U6/T6)*0.1*(1-Parameters!$F$35) -> 0.0072612598 | ... BI56: =+LN(BT6/BS6)*0.1*(1-Parameters!$F$35) -> 0.0023389443
A57: Russia | C57: =+LN(N7/M7)*0.1*(1-Parameters!$F$35) -> 0.018187619 | D57: =+LN(O7/N7)*0.1*(1-Parameters!$F$35) -> 0.014253169 | E57: =+LN(P7/O7)*0.1*(1-Parameters!$F$35) -> 0.013094986 | F57: =+LN(Q7/P7)*0.1*(1-Parameters!$F$35) -> 0.012049183 | G57: =+LN(R7/Q7)*0.1*(1-Parameters!$F$35) -> 0.011104848 | H57: =+LN(S7/R7)*0.1*(1-Parameters!$F$35) -> 0.010252132 | I57: =+LN(T7/S7)*0.1*(1-Parameters!$F$35) -> 0.00948214 | J57: =+LN(U7/T7)*0.1*(1-Parameters!$F$35) -> 0.0087868423 | ... BI57: =+LN(BT7/BS7)*0.1*(1-Parameters!$F$35) -> 0.0023460206
A58: Non-Russia Eurasia | C58: =+LN(N8/M8)*0.1*(1-Parameters!$F$35) -> 0.017288754 | D58: =+LN(O8/N8)*0.1*(1-Parameters!$F$35) -> 0.020146309 | E58: =+LN(P8/O8)*0.1*(1-Parameters!$F$35) -> 0.018398812 | F58: =+LN(Q8/P8)*0.1*(1-Parameters!$F$35) -> 0.016822626 | G58: =+LN(R8/Q8)*0.1*(1-Parameters!$F$35) -> 0.015400947 | H58: =+LN(S8/R8)*0.1*(1-Parameters!$F$35) -> 0.014118621 | I58: =+LN(T8/S8)*0.1*(1-Parameters!$F$35) -> 0.01296198 | J58: =+LN(U8/T8)*0.1*(1-Parameters!$F$35) -> 0.011918698 | ... BI58: =+LN(BT8/BS8)*0.1*(1-Parameters!$F$35) -> 0.0023605474
A59: China | C59: =+LN(N9/M9)*0.1*(1-Parameters!$F$35) -> 0.049979155 | D59: =+LN(O9/N9)*0.1*(1-Parameters!$F$35) -> 0.018530066 | E59: =+LN(P9/O9)*0.1*(1-Parameters!$F$35) -> 0.016944194 | F59: =+LN(Q9/P9)*0.1*(1-Parameters!$F$35) -> 0.015513469 | G59: =+LN(R9/Q9)*0.1*(1-Parameters!$F$35) -> 0.014222706 | H59: =+LN(S9/R9)*0.1*(1-Parameters!$F$35) -> 0.013058204 | I59: =+LN(T9/S9)*0.1*(1-Parameters!$F$35) -> 0.012007605 | J59: =+LN(U9/T9)*0.1*(1-Parameters!$F$35) -> 0.011059761 | ... BI59: =+LN(BT9/BS9)*0.1*(1-Parameters!$F$35) -> 0.0023565633
A60: India | C60: =+LN(N10/M10)*0.1*(1-Parameters!$F$35) -> 0.031846841 | D60: =+LN(O10/N10)*0.1*(1-Parameters!$F$35) -> 0.023310254 | E60: =+LN(P10/O10)*0.1*(1-Parameters!$F$35) -> 0.021246362 | F60: =+LN(Q10/P10)*0.1*(1-Parameters!$F$35) -> 0.019385421 | G60: =+LN(R10/Q10)*0.1*(1-Parameters!$F$35) -> 0.017707463 | H60: =+LN(S10/R10)*0.1*(1-Parameters!$F$35) -> 0.016194485 | I60: =+LN(T10/S10)*0.1*(1-Parameters!$F$35) -> 0.014830258 | J60: =+LN(U10/T10)*0.1*(1-Parameters!$F$35) -> 0.013600148 | ... BI60: =+LN(BT10/BS10)*0.1*(1-Parameters!$F$35) -> 0.0023683466
A61: Middle East | C61: =+LN(N11/M11)*0.1*(1-Parameters!$F$35) -> 0.016473658 | D61: =+LN(O11/N11)*0.1*(1-Parameters!$F$35) -> 0.015537825 | E61: =+LN(P11/O11)*0.1*(1-Parameters!$F$35) -> 0.014251177 | F61: =+LN(Q11/P11)*0.1*(1-Parameters!$F$35) -> 0.013089754 | G61: =+LN(R11/Q11)*0.1*(1-Parameters!$F$35) -> 0.012041362 | H61: =+LN(S11/R11)*0.1*(1-Parameters!$F$35) -> 0.011094995 | I61: =+LN(T11/S11)*0.1*(1-Parameters!$F$35) -> 0.010240717 | J61: =+LN(U11/T11)*0.1*(1-Parameters!$F$35) -> 0.0094695611 | ... BI61: =+LN(BT11/BS11)*0.1*(1-Parameters!$F$35) -> 0.0023491873
A62: Africa | C62: =+LN(N12/M12)*0.1*(1-Parameters!$F$35) -> 0.025537887 | D62: =+LN(O12/N12)*0.1*(1-Parameters!$F$35) -> 0.024264659 | E62: =+LN(P12/O12)*0.1*(1-Parameters!$F$35) -> 0.022105327 | F62: =+LN(Q12/P12)*0.1*(1-Parameters!$F$35) -> 0.020158489 | G62: =+LN(R12/Q12)*0.1*(1-Parameters!$F$35) -> 0.018403224 | H62: =+LN(S12/R12)*0.1*(1-Parameters!$F$35) -> 0.01682067 | I62: =+LN(T12/S12)*0.1*(1-Parameters!$F$35) -> 0.015393824 | J62: =+LN(U12/T12)*0.1*(1-Parameters!$F$35) -> 0.014107358 | ... BI62: =+LN(BT12/BS12)*0.1*(1-Parameters!$F$35) -> 0.0023706992
A63: Latin America | C63: =+LN(N13/M13)*0.1*(1-Parameters!$F$35) -> 0.020486627 | D63: =+LN(O13/N13)*0.1*(1-Parameters!$F$35) -> 0.017679701 | E63: =+LN(P13/O13)*0.1*(1-Parameters!$F$35) -> 0.016178865 | F63: =+LN(Q13/P13)*0.1*(1-Parameters!$F$35) -> 0.014824674 | G63: =+LN(R13/Q13)*0.1*(1-Parameters!$F$35) -> 0.01360279 | H63: =+LN(S13/R13)*0.1*(1-Parameters!$F$35) -> 0.01250028 | I63: =+LN(T13/S13)*0.1*(1-Parameters!$F$35) -> 0.011505473 | J63: =+LN(U13/T13)*0.1*(1-Parameters!$F$35) -> 0.010607842 | ... BI63: =+LN(BT13/BS13)*0.1*(1-Parameters!$F$35) -> 0.0023544671
A64: OHI | C64: =+LN(N14/M14)*0.1*(1-Parameters!$F$35) -> 0.013178151 | D64: =+LN(O14/N14)*0.1*(1-Parameters!$F$35) -> 0.011156943 | E64: =+LN(P14/O14)*0.1*(1-Parameters!$F$35) -> 0.010308382 | F64: =+LN(Q14/P14)*0.1*(1-Parameters!$F$35) -> 0.0095412394 | G64: =+LN(R14/Q14)*0.1*(1-Parameters!$F$35) -> 0.0088476992 | H64: =+LN(S14/R14)*0.1*(1-Parameters!$F$35) -> 0.0082206979 | I64: =+LN(T14/S14)*0.1*(1-Parameters!$F$35) -> 0.0076538493 | J64: =+LN(U14/T14)*0.1*(1-Parameters!$F$35) -> 0.0071413806 | ... BI64: =+LN(BT14/BS14)*0.1*(1-Parameters!$F$35) -> 0.0023383883
A65: Other non-OECD Asia | C65: =+LN(N15/M15)*0.1*(1-Parameters!$F$35) -> 0.019563638 | D65: =+LN(O15/N15)*0.1*(1-Parameters!$F$35) -> 0.024234487 | E65: =+LN(P15/O15)*0.1*(1-Parameters!$F$35) -> 0.022078172 | F65: =+LN(Q15/P15)*0.1*(1-Parameters!$F$35) -> 0.02013405 | G65: =+LN(R15/Q15)*0.1*(1-Parameters!$F$35) -> 0.018381229 | H65: =+LN(S15/R15)*0.1*(1-Parameters!$F$35) -> 0.016800874 | I65: =+LN(T15/S15)*0.1*(1-Parameters!$F$35) -> 0.015376008 | J65: =+LN(U15/T15)*0.1*(1-Parameters!$F$35) -> 0.014091324 | ... BI65: =+LN(BT15/BS15)*0.1*(1-Parameters!$F$35) -> 0.0023706249
A66: GLOBAL | C66: =+SUMPRODUCT(C54:C65*$B108:$B119)/SUM($B108:$B119) -> 0.017911794 | D66: =+SUMPRODUCT(D54:D65*$B108:$B119)/SUM($B108:$B119) -> 0.014300905 | E66: =+SUMPRODUCT(E54:E65*$B108:$B119)/SUM($B108:$B119) -> 0.013137948 | F66: =+SUMPRODUCT(F54:F65*$B108:$B119)/SUM($B108:$B119) -> 0.012087848 | G66: =+SUMPRODUCT(G54:G65*$B108:$B119)/SUM($B108:$B119) -> 0.011139647 | H66: =+SUMPRODUCT(H54:H65*$B108:$B119)/SUM($B108:$B119) -> 0.010283451 | I66: =+SUMPRODUCT(I54:I65*$B108:$B119)/SUM($B108:$B119) -> 0.0095103272 | J66: =+SUMPRODUCT(J54:J65*$B108:$B119)/SUM($B108:$B119) -> 0.0088122108 | ... AF66: =+SUMPRODUCT(AF54:AF65*$B108:$B119)/SUM($B108:$B119) -> 0.0030008486
A70: Sigma growth
A71: g(sigma) | B71: average 95-06 | C71: adjustment | D71: Total growth rate sigma | E71: Decline rate sigma growth | F71: Trend sigma growth | G71: data 1995-2006 | H71: 2015 | I71: =+H71+10 -> 2025 | J71: =+I71+10 -> 2035 | K71: =+J71+10 -> 2045 | L71: =+K71+10 -> 2055 | M71: =+L71+10 -> 2065 | N71: =+M71+10 -> 2075 | O71: =+N71+10 -> 2085 | P71: =+O71+10 -> 2095 | ... S71: =+R71+10 -> 2125
A72: US | B72: -0.022475677 | C72: 0.005 | D72: =+B72+C72 -> -0.017475677 | E72: =+Parameters!B22 -> 0.1 | F72: =+Parameters!B23 -> -0.0025 | G72: =+B72 -> -0.022475677 | H72: =+$F72+($D72-$F72) -> -0.017475677 | I72: =+$F72+(H72-$F72)*(1-$E72) -> -0.015978109 | J72: =+$F72+(I72-$F72)*(1-$E72) -> -0.014630298 | K72: =+$F72+(J72-$F72)*(1-$E72) -> -0.013417268 | L72: =+$F72+(K72-$F72)*(1-$E72) -> -0.012325541 | M72: =+$F72+(L72-$F72)*(1-$E72) -> -0.011342987 | N72: =+$F72+(M72-$F72)*(1-$E72) -> -0.010458689 | O72: =+$F72+(N72-$F72)*(1-$E72) -> -0.0096628197 | P72: =+$F72+(O72-$F72)*(1-$E72) -> -0.0089465377 | ... BN72: =+$F72+(BM72-$F72)*(1-$E72) -> -0.002533224
A73: EU | B73: -0.016957232 | C73: 0.0025 | D73: =+B73+C73 -> -0.014457232 | E73: =+E72 -> 0.1 | F73: =+F72 -> -0.0025 | G73: =+B73 -> -0.016957232 | H73: =+$F73+($D73-$F73) -> -0.014457232 | I73: =+$F73+(H73-$F73)*(1-$E73) -> -0.013261509 | J73: =+$F73+(I73-$F73)*(1-$E73) -> -0.012185358 | K73: =+$F73+(J73-$F73)*(1-$E73) -> -0.011216822 | L73: =+$F73+(K73-$F73)*(1-$E73) -> -0.01034514 | M73: =+$F73+(L73-$F73)*(1-$E73) -> -0.0095606262 | N73: =+$F73+(M73-$F73)*(1-$E73) -> -0.0088545636 | O73: =+$F73+(N73-$F73)*(1-$E73) -> -0.0082191072 | P73: =+$F73+(O73-$F73)*(1-$E73) -> -0.0076471965 | ... BN73: =+$F73+(BM73-$F73)*(1-$E73) -> -0.0025265275
A74: Japan | B74: -0.0024892489 | C74: -0.015 | D74: =+B74+C74 -> -0.017489249 | E74: =+E73 -> 0.1 | F74: =+F73 -> -0.0025 | G74: =+B74 -> -0.0024892489 | H74: =+$F74+($D74-$F74) -> -0.017489249 | I74: =+$F74+(H74-$F74)*(1-$E74) -> -0.015990324 | J74: =+$F74+(I74-$F74)*(1-$E74) -> -0.014641292 | K74: =+$F74+(J74-$F74)*(1-$E74) -> -0.013427162 | L74: =+$F74+(K74-$F74)*(1-$E74) -> -0.012334446 | M74: =+$F74+(L74-$F74)*(1-$E74) -> -0.011351002 | N74: =+$F74+(M74-$F74)*(1-$E74) -> -0.010465901 | O74: =+$F74+(N74-$F74)*(1-$E74) -> -0.0096693113 | P74: =+$F74+(O74-$F74)*(1-$E74) -> -0.0089523801 | ... BN74: =+$F74+(BM74-$F74)*(1-$E74) -> -0.0025332541
A75: Russia | B75: -0.037272564 | C75: 0.02 | D75: =+B75+C75 -> -0.017272564 | E75: =+E74 -> 0.1 | F75: =+F74 -> -0.0025 | G75: =+B75 -> -0.037272564 | H75: =+$F75+($D75-$F75) -> -0.017272564 | I75: =+$F75+(H75-$F75)*(1-$E75) -> -0.015795307 | J75: =+$F75+(I75-$F75)*(1-$E75) -> -0.014465777 | K75: =+$F75+(J75-$F75)*(1-$E75) -> -0.013269199 | L75: =+$F75+(K75-$F75)*(1-$E75) -> -0.012192279 | M75: =+$F75+(L75-$F75)*(1-$E75) -> -0.011223051 | N75: =+$F75+(M75-$F75)*(1-$E75) -> -0.010350746 | O75: =+$F75+(N75-$F75)*(1-$E75) -> -0.0095656714 | P75: =+$F75+(O75-$F75)*(1-$E75) -> -0.0088591043 | ... BN75: =+$F75+(BM75-$F75)*(1-$E75) -> -0.0025327734
A76: Eurasia | B76: -0.038000677 | C76: 0.014 | D76: =+B76+C76 -> -0.024000677 | E76: =+E75 -> 0.1 | F76: =+F75 -> -0.0025 | G76: =+B76 -> -0.038000677 | H76: =+$F76+($D76-$F76) -> -0.024000677 | I76: =+$F76+(H76-$F76)*(1-$E76) -> -0.021850609 | J76: =+$F76+(I76-$F76)*(1-$E76) -> -0.019915548 | K76: =+$F76+(J76-$F76)*(1-$E76) -> -0.018173993 | L76: =+$F76+(K76-$F76)*(1-$E76) -> -0.016606594 | M76: =+$F76+(L76-$F76)*(1-$E76) -> -0.015195935 | N76: =+$F76+(M76-$F76)*(1-$E76) -> -0.013926341 | O76: =+$F76+(N76-$F76)*(1-$E76) -> -0.012783707 | P76: =+$F76+(O76-$F76)*(1-$E76) -> -0.011755336 | ... BN76: =+$F76+(BM76-$F76)*(1-$E76) -> -0.0025476999
A77: China | B77: -0.022861473 | C77: -0.002 | D77: =+B77+C77 -> -0.024861473 | E77: =+E76 -> 0.1 | F77: =+F76 -> -0.0025 | G77: =+B77 -> -0.022861473 | H77: =+$F77+($D77-$F77) -> -0.024861473 | I77: =+$F77+(H77-$F77)*(1-$E77) -> -0.022625326 | J77: =+$F77+(I77-$F77)*(1-$E77) -> -0.020612793 | K77: =+$F77+(J77-$F77)*(1-$E77) -> -0.018801514 | L77: =+$F77+(K77-$F77)*(1-$E77) -> -0.017171363 | M77: =+$F77+(L77-$F77)*(1-$E77) -> -0.015704226 | N77: =+$F77+(M77-$F77)*(1-$E77) -> -0.014383804 | O77: =+$F77+(N77-$F77)*(1-$E77) -> -0.013195423 | P77: =+$F77+(O77-$F77)*(1-$E77) -> -0.012125881 | ... BN77: =+$F77+(BM77-$F77)*(1-$E77) -> -0.0025496096
A78: India | B78: -0.029578995 | C78: 0.0075 | D78: =+B78+C78 -> -0.022078995 | E78: =+E77 -> 0.1 | F78: =+F77 -> -0.0025 | G78: =+B78 -> -0.029578995 | H78: =+$F78+($D78-$F78) -> -0.022078995 | I78: =+$F78+(H78-$F78)*(1-$E78) -> -0.020121095 | J78: =+$F78+(I78-$F78)*(1-$E78) -> -0.018358986 | K78: =+$F78+(J78-$F78)*(1-$E78) -> -0.016773087 | L78: =+$F78+(K78-$F78)*(1-$E78) -> -0.015345778 | M78: =+$F78+(L78-$F78)*(1-$E78) -> -0.014061201 | N78: =+$F78+(M78-$F78)*(1-$E78) -> -0.012905081 | O78: =+$F78+(N78-$F78)*(1-$E78) -> -0.011864572 | P78: =+$F78+(O78-$F78)*(1-$E78) -> -0.010928115 | ... BN78: =+$F78+(BM78-$F78)*(1-$E78) -> -0.0025434366
A79: Middle East | B79: 0.027370024 | C79: -0.045 | D79: =+B79+C79 -> -0.017629976 | E79: =+E78 -> 0.1 | F79: =+F78 -> -0.0025 | G79: =+B79 -> 0.027370024 | H79: =+$F79+($D79-$F79) -> -0.017629976 | I79: =+$F79+(H79-$F79)*(1-$E79) -> -0.016116979 | J79: =+$F79+(I79-$F79)*(1-$E79) -> -0.014755281 | K79: =+$F79+(J79-$F79)*(1-$E79) -> -0.013529753 | L79: =+$F79+(K79-$F79)*(1-$E79) -> -0.012426777 | M79: =+$F79+(L79-$F79)*(1-$E79) -> -0.0114341 | N79: =+$F79+(M79-$F79)*(1-$E79) -> -0.01054069 | O79: =+$F79+(N79-$F79)*(1-$E79) -> -0.0097366207 | P79: =+$F79+(O79-$F79)*(1-$E79) -> -0.0090129586 | ... BN79: =+$F79+(BM79-$F79)*(1-$E79) -> -0.0025335663
A80: Africa | B80: -0.024620078 | C80: 0.0025 | D80: =+B80+C80 -> -0.022120078 | E80: =+E79 -> 0.1 | F80: =+F79 -> -0.0025 | G80: =+B80 -> -0.024620078 | H80: =+$F80+($D80-$F80) -> -0.022120078 | I80: =+$F80+(H80-$F80)*(1-$E80) -> -0.02015807 | J80: =+$F80+(I80-$F80)*(1-$E80) -> -0.018392263 | K80: =+$F80+(J80-$F80)*(1-$E80) -> -0.016803037 | L80: =+$F80+(K80-$F80)*(1-$E80) -> -0.015372733 | M80: =+$F80+(L80-$F80)*(1-$E80) -> -0.01408546 | N80: =+$F80+(M80-$F80)*(1-$E80) -> -0.012926914 | O80: =+$F80+(N80-$F80)*(1-$E80) -> -0.011884223 | P80: =+$F80+(O80-$F80)*(1-$E80) -> -0.0109458 | ... BN80: =+$F80+(BM80-$F80)*(1-$E80) -> -0.0025435278
A81: Latin America | B81: -0.0039660588 | C81: -0.011 | D81: =+B81+C81 -> -0.014966059 | E81: =+E80 -> 0.1 | F81: =+F80 -> -0.0025 | G81: =+B81 -> -0.0039660588 | H81: =+$F81+($D81-$F81) -> -0.014966059 | I81: =+$F81+(H81-$F81)*(1-$E81) -> -0.013719453 | J81: =+$F81+(I81-$F81)*(1-$E81) -> -0.012597508 | K81: =+$F81+(J81-$F81)*(1-$E81) -> -0.011587757 | L81: =+$F81+(K81-$F81)*(1-$E81) -> -0.010678981 | M81: =+$F81+(L81-$F81)*(1-$E81) -> -0.009861083 | N81: =+$F81+(M81-$F81)*(1-$E81) -> -0.0091249747 | O81: =+$F81+(N81-$F81)*(1-$E81) -> -0.0084624773 | P81: =+$F81+(O81-$F81)*(1-$E81) -> -0.0078662295 | ... BN81: =+$F81+(BM81-$F81)*(1-$E81) -> -0.0025276563
A82: OHI | B82: -0.0086771428 | C82: -0.01 | D82: =+B82+C82 -> -0.018677143 | E82: =+E81 -> 0.1 | F82: =+F81 -> -0.0025 | G82: =+B82 -> -0.0086771428 | H82: =+$F82+($D82-$F82) -> -0.018677143 | I82: =+$F82+(H82-$F82)*(1-$E82) -> -0.017059429 | J82: =+$F82+(I82-$F82)*(1-$E82) -> -0.015603486 | K82: =+$F82+(J82-$F82)*(1-$E82) -> -0.014293137 | L82: =+$F82+(K82-$F82)*(1-$E82) -> -0.013113823 | M82: =+$F82+(L82-$F82)*(1-$E82) -> -0.012052441 | N82: =+$F82+(M82-$F82)*(1-$E82) -> -0.011097197 | O82: =+$F82+(N82-$F82)*(1-$E82) -> -0.010237477 | P82: =+$F82+(O82-$F82)*(1-$E82) -> -0.0094637295 | ... BN82: =+$F82+(BM82-$F82)*(1-$E82) -> -0.0025358895
A83: Other non-OECD Asia | B83: -0.0010467712 | C83: -0.018 | D83: =+B83+C83 -> -0.019046771 | E83: =+E82 -> 0.1 | F83: =+F82 -> -0.0025 | G83: =+B83 -> -0.0010467712 | H83: =+$F83+($D83-$F83) -> -0.019046771 | I83: =+$F83+(H83-$F83)*(1-$E83) -> -0.017392094 | J83: =+$F83+(I83-$F83)*(1-$E83) -> -0.015902885 | K83: =+$F83+(J83-$F83)*(1-$E83) -> -0.014562596 | L83: =+$F83+(K83-$F83)*(1-$E83) -> -0.013356337 | M83: =+$F83+(L83-$F83)*(1-$E83) -> -0.012270703 | N83: =+$F83+(M83-$F83)*(1-$E83) -> -0.011293633 | O83: =+$F83+(N83-$F83)*(1-$E83) -> -0.010414269 | P83: =+$F83+(O83-$F83)*(1-$E83) -> -0.0096228425 | ... BN83: =+$F83+(BM83-$F83)*(1-$E83) -> -0.0025367095
A84: World (2005 wts) | H84: =+SUMPRODUCT(H72:H83*$F$89:$F$100)/$F$101 -> -0.019105156 | I84: =+SUMPRODUCT(I72:I83*$F$89:$F$100)/$F$101 -> -0.017444641 | J84: =+SUMPRODUCT(J72:J83*$F$89:$F$100)/$F$101 -> -0.015950177 | K84: =+SUMPRODUCT(K72:K83*$F$89:$F$100)/$F$101 -> -0.014605159
A85: From RICE uncontrolled | H85: =+LN(Global!C57/Global!B57)/10 -> -0.015609139 | I85: =+LN(Global!D57/Global!C57)/10 -> -0.016519717 | J85: =+LN(Global!E57/Global!D57)/10 -> -0.015513126 | K85: =+LN(Global!F57/Global!E57)/10 -> -0.014405216 | L85: =+LN(Global!G57/Global!F57)/10 -> -0.013351005 | M85: =+LN(Global!H57/Global!G57)/10 -> -0.012274455 | U85: -0.006923618 | V85: -0.0064812562 | W85: -0.0060831306 | X85: -0.0057248175 | Y85: -0.0054023358 | Z85: -0.0051121022 | AA85: -0.004850892 | AB85: -0.0046158028 | AC85: -0.0044042225 | AD85: -0.0042138003 | AE85: -0.0040424202 | AF85: -0.0038881782 | AG85: -0.0037493604 | AH85: -0.0036244243 | AI85: -0.0035119819 | AJ85: -0.0034107837 | AK85: -0.0033197053 | AL85: -0.0032377348 | AM85: -0.0031639613 | AN85: -0.0030975652 | AO85: -0.0030378087 | AP85: -0.0029840278 | AQ85: -0.002935625 | AR85: -0.0028920625 | AS85: -0.0028528563 | AT85: -0.0028175706 | AU85: -0.0027858136 | AV85: -0.0027572322 | AW85: -0.002731509 | AX85: -0.0027083581 | AY85: -0.0026875223 | AZ85: -0.0026687701 | BA85: -0.0026518931 | BB85: -0.0026367038 | BC85: -0.0026230334 | BD85: -0.00261073 | BE85: -0.002599657 | BF85: -0.0025896913 | BG85: -0.0025807222 | BH85: -0.00257265 | BI85: -0.002565385 | BJ85: -0.0025588465 | BK85: -0.0025529618 | BL85: -0.0025476657 | BM85: -0.0025428991 | BN85: -0.0025386092
A86: CO2 emissions, 2005 [revised 12/14/09; checked 3/29/10]
D87: 3/39/10 | E87: 3/39/10 | K87: values uncontrolled
C88: 40161 | D88: CO2 only, 2005 (CDIAC/Rice) | E88: 2005, including all | F88: 2005, CO2 total* | G88: 2015 addfactor | H88: Ratio new to old | I88: 2005 model | J88: 2015 model | K88: 2005 model | L88: 2015 model | M88: From projection
A89: US | C89: 1661.4294 | D89: 1593.086 | E89: =+D89+15 -> 1608.086 | F89: 1662.1335 | G89: 0.90306386 | H89: =+F89/C89 -> 1.0004238 | I89: =+B413 -> 1.661414 | J89: =+C413 -> 1.6230896 | K89: 1.661414 | L89: 1.6221018 | M89: =+AP398/1000000 -> 1.6221018 | N89: =+M89/J89 -> 0.99939146
A90: EU | C90: 1243.7388 | D90: 1088.162 | E90: =+D90*$E$102 -> 1135.497 | F90: 1146.0506 | G90: 0.77147185 | H90: =+F90/C90 -> 0.92145605 | I90: =+B414 -> 1.1456625 | J90: =+C414 -> 0.99377439 | K90: 1.1456625 | L90: 0.99299305 | M90: =+AP399/1000000 -> 0.98966237 | N90: =+M90/J90 -> 0.99586222
A91: Japan | C91: 354.597 | D91: 354.597 | E91: =+D91+10 -> 364.597 | F91: 369.96593 | G91: 1.0758359 | H91: =+F91/C91 -> 1.043342 | I91: =+B415 -> 0.36984064 | J91: =+C415 -> 0.38197401 | K91: 0.36984064 | L91: 0.38187441 | M91: =+AP400/1000000 -> 0.38187441 | N91: =+M91/J91 -> 0.99973924
A92: Russia | C92: 413.322 | D92: 413.322 | E92: =+D92*$E$102 -> 431.30151 | F92: 431.23618 | G92: 0.88158499 | H92: =+F92/C92 -> 1.043342 | I92: =+B416 -> 0.43100237 | J92: =+C416 -> 0.42305074 | K92: 0.43100237 | L92: 0.4228121 | M92: =+AP401/1000000 -> 0.4228121 | N92: =+M92/J92 -> 0.99943591
A93: Eurasia | C93: 328.83015 | D93: 234.435 | E93: =+D93*$E$102 -> 244.63292 | F93: 256.66629 | G93: 0.85396887 | H93: =+F93/C93 -> 0.78054367 | I93: =+B417 -> 0.25652713 | J93: =+C417 -> 0.23333917 | K93: 0.25652713 | L93: 0.23330376 | M93: =+AP402/1000000 -> 0.23330376 | N93: =+M93/J93 -> 0.99984827
A94: China | C94: 1534.244 | D94: 1534.244 | E94: =+D94+163 -> 1697.244 | F94: 1600.7411 | G94: 1.017367 | H94: =+F94/C94 -> 1.043342 | I94: =+B418 -> 1.5999444 | J94: =+C418 -> 2.8420865 | K94: 1.5999444 | L94: 2.842414 | M94: =+AP403/1000000 -> 2.842414 | N94: =+M94/J94 -> 1.0001152
A95: India | C95: 388.321 | D95: 388.321 | E95: =+D95+22 -> 410.321 | F95: 405.15159 | G95: 1.1806415 | H95: =+F95/C95 -> 1.043342 | I95: =+B419 -> 0.40499472 | J95: =+C419 -> 0.72268116 | K95: 0.40499472 | L95: 0.72298207 | M95: =+AP404/1000000 -> 0.72298207 | N95: =+M95/J95 -> 1.0004164
A96: Middle East | C96: 406.81333 | D96: 549.457 | E96: =+D96*$E$102 -> 573.35838 | F96: 589.67496 | G96: 0.98546507 | H96: =+F96/C96 -> 1.4494976 | I96: =+B420 -> 0.58943424 | J96: =+C420 -> 0.8069851 | K96: 0.58943424 | L96: 0.80627491 | M96: =+AP405/1000000 -> 0.80627491 | N96: =+M96/J96 -> 0.99911995
A97: Africa | C97: 297.59467 | D97: 183.325 | E97: =+D97*$E$102 -> 191.29964 | F97: 191.37708 | G97: 0.84200862 | H97: =+F97/C97 -> 0.64307968 | I97: =+B421 -> 0.19130299 | J97: =+C421 -> 0.24390148 | K97: 0.19130299 | L97: 0.24378286 | M97: =+AP406/1000000 -> 0.24378286 | N97: =+M97/J97 -> 0.99951366
A98: Latin America | C98: 425.06953 | D98: 393.85 | E98: =+D98*$E$102 -> 410.98248 | F98: 412.2724 | G98: 0.9615959 | H98: =+F98/C98 -> 0.96989402 | I98: =+B422 -> 0.41212692 | J98: =+C422 -> 0.53274365 | K98: 0.41212692 | L98: 0.53245637 | M98: =+AP407/1000000 -> 0.53245637 | N98: =+M98/J98 -> 0.99946077
A99: OHI | C99: 585.75021 | D99: 519.27 | E99: =+D99*$E$102 -> 541.85825 | F99: 541.77826 | G99: 0.95585923 | H99: =+F99/C99 -> 0.92493054 | I99: =+B423 -> 0.5415685 | J99: =+C423 -> 0.56942681 | K99: 0.5415685 | L99: 0.56885595 | M99: =+AP408/1000000 -> 0.56885595 | N99: =+M99/J99 -> 0.99899747
A100: Other non-OECD Asia | C100: 331.62576 | D100: 347.159 | E100: =+D100*$E$102 -> 362.26042 | F100: 363.9521 | G100: 1.3139916 | H100: =+F100/C100 -> 1.0974784 | I100: =+B424 -> 0.36381784 | J100: =+C424 -> 0.63050158 | K100: 0.36381784 | L100: 0.63087697 | M100: =+AP409/1000000 -> 0.63087697 | N100: =+M100/J100 -> 1.0005954
A101: World | C101: 7971.3358 | D101: =SUM(D89:D100) -> 7599.228 | E101: =SUM(E89:E100) -> 7971.4386 | F101: =SUM(F89:F100) -> 7971 | H101: =+F101/C101 -> 0.99995788 | I101: =SUM(I89:I100) -> 7.9676364 | J101: =SUM(J89:J100) -> 10.003554 | K101: 7.9676364 | L101: 10.000728 | M101: =SUM(M89:M100) -> 9.9973976
E102: 1.0435 | F102: *Source: This takes the 2006 total and scales it back t0 2005 by global ratio.
E103: 7971000 | F103: ** Control total is CDIAC
E104: =+(E101/E103-1)^2 -> 0.99800089
A105: Calibration | B105: macro_071309a.xlsx
A106: Region | B106: GDP | C106: Pop | D106: delta | E106: alpha | F106: pcGDP | G106: Pure r | H106: Excess risk | I106: mkt r | J106: PSRTP | K106: alpha | L106: n pop | M106: g(pcGDP) | AB106: 4 | AC106: new K
L107: 1995-2006 | M107: 0 | N107: net MPK | O107: gross MPK | P107: k | Q107: A | R107: y(2) | S107: K | T107: s | U107: Y pf | V107: Yact | W107: y calc | X107: y act | Y107: g(2005-2105) | Z107: g(2005-2055) | AA107: desired change s | AB107: adjustment factor
...

Sheet Copen
A1: This is a calculation of emissions limits by regions | BR1: NEW BASELINE
BS2: 2005 | BT2: =+BS2+10 -> 2015 | BU2: =+BT2+10 -> 2025 | BV2: =+BU2+10 -> 2035 | BW2: =+BV2+10 -> 2045 | BX2: =+BW2+10 -> 2055 | BY2: =+BX2+10 -> 2065 | BZ2: =+BY2+10 -> 2075 | CA2: =+BZ2+10 -> 2085 | ... DZ2: =+DY2+10 -> 2595
A3: Baseline industrial emissions | C3: 1990 | D3: 1991 | E3: 1992 | F3: 1993 | G3: 1994 | H3: 1995 | I3: 1996 | J3: 1997 | K3: 1998 | L3: 1999 | M3: 2000 | N3: 2001 | O3: 2002 | P3: 2003 | Q3: 2004 | R3: 2005 | S3: 2006 | T3: 2007 | U3: 2008 | V3: 2009 | W3: 2010 | X3: 2015 | Y3: 2020 | Z3: 2025 | AA3: =+Z3+5 -> 2030 | AB3: =+AA3+5 -> 2035 | AC3: =+AB3+5 -> 2040 | AD3: =+AC3+5 -> 2045 | AE3: =+AD3+5 -> 2050 | AF3: =+AE3+5 -> 2055 | AG3: =+AF3+5 -> 2060 | AH3: =+AG3+5 -> 2065 | ... BL3: =+BK3+5 -> 2215 | BR3: US | BS3: =+BS22*BS35 -> 1.6621335 | BT3: =+BT22*BT35 -> 1.623889 | BU3: =+BU22*BU35 -> 1.7936993 | BV3: =+BV22*BV35 -> 1.9159712 | BW3: =+BW22*BW35 -> 2.0064006 | BX3: =+BX22*BX35 -> 2.0633899 | BY3: =+BY22*BY35 -> 2.0996013 | BZ3: =+BZ22*BZ35 -> 2.1359058 | ... DZ3: =+DZ22*DZ35 -> 3.566312
A4: US | B4: CO2 | C4: 1.3721369 | D4: 1.3594361 | E4: 1.3862585 | F4: 1.4163666 | G4: 1.4379934 | H4: 1.4532129 | I4: 1.5042551 | J4: 1.5262424 | K4: 1.5337064 | L4: 1.5508817 | M4: 1.5993053 | N4: 1572.6163 | O4: 1589.1217 | P4: 1603.9216 | Q4: 1628.7599 | R4: =+Data!F89/1000 -> 1.6621335 | S4: 1.6242076 | T4: =+S4*($X4/$S4)^(0.111111111111111) -> 1.6241722 | U4: =+T4*($X4/$S4)^(0.111111111111111) -> 1.6241368 | V4: =+U4*($X4/$S4)^(0.111111111111111) -> 1.6241014 | W4: =+V4*($X4/$S4)^(0.111111111111111) -> 1.624066 | X4: =+BT3 -> 1.623889 | Y4: =+(X4*Z4)^0.5 -> 1.7066835 | Z4: =+BU3 -> 1.7936993 | AA4: =+(Z4*AB4)^0.5 -> 1.8538274 | AB4: =+BV3 -> 1.9159712 | AC4: =+(AB4*AD4)^0.5 -> 1.9606646 | AD4: =+BW3 -> 2.0064006 | AE4: =+(AD4*AF4)^0.5 -> 2.0346958 | AF4: =+BX3 -> 2.0633899 | AG4: =+(AF4*AH4)^0.5 -> 2.0814169 | AH4: =+BY3 -> 2.0996013 | AI4: =+(AH4*AJ4)^0.5 -> 2.1176757 | AJ4: =+BZ3 -> 2.1359058 | AK4: =+(AJ4*AL4)^0.5 -> 2.1548765 | AL4: =+CA3 -> 2.1740157 | AM4: =+(AL4*AN4)^0.5 -> 2.1944381 | AN4: =+CB3 -> 2.2150523 | AO4: =+(AN4*AP4)^0.5 -> 2.2340551 | AP4: =+CC3 -> 2.2532209 | AQ4: =+(AP4*AR4)^0.5 -> 2.2694385 | AR4: =+CD3 -> 2.2857729 | AS4: =+(AR4*AT4)^0.5 -> 2.3009849 | AT4: =+CE3 -> 2.3162981 | AU4: =+(AT4*AV4)^0.5 -> 2.3415799 | AV4: =+CF3 -> 2.3671376 | AW4: =+(AV4*AX4)^0.5 -> 2.386809 | AX4: =+CG3 -> 2.4066439 | AY4: =+(AX4*AZ4)^0.5 -> 2.423671 | AZ4: =+CH3 -> 2.4408186 | BA4: =+(AZ4*BB4)^0.5 -> 2.4567258 | BB4: =+CI3 -> 2.4727368 | BC4: =+(BB4*BD4)^0.5 -> 2.4883025 | BD4: =+CJ3 -> 2.5039662 | BE4: =+(BD4*BF4)^0.5 -> 2.5195815 | BF4: =+CK3 -> 2.5352941 | BG4: =+(BF4*BH4)^0.5 -> 2.5511487 | BH4: =+CL3 -> 2.5671025 | BI4: =+(BH4*BJ4)^0.5 -> 2.5821675 | BJ4: =+CM3 -> 2.5973209 | BK4: =+(BJ4*BL4)^0.5 -> 2.6113617 | BL4: =+CN3 -> 2.6254785 | BR4: EU | BS4: =+BS23*BS36 -> 1.1460506 | BT4: =+BT23*BT36 -> 0.99417388 | BU4: =+BU23*BU36 -> 1.1065871 | BV4: =+BV23*BV36 -> 1.1896401 | BW4: =+BW23*BW36 -> 1.2528505 | BX4: =+BX23*BX36 -> 1.293256 | BY4: =+BY23*BY36 -> 1.3187353 | BZ4: =+BZ23*BZ36 -> 1.3389633 | ... DZ4: =+DZ23*DZ36 -> 2.627593
A5: EU | B5: CO2 | C5: 1.1330683 | D5: 1.1302015 | E5: 1.1028089 | F5: 1.1073034 | G5: 1.095643 | H5: 1.1089181 | I5: 1.1450598 | J5: 1.1493936 | K5: 1.1496953 | L5: 1.1431401 | M5: 1.158012 | N5: 1170.4459 | O5: 1162.5325 | P5: 1200.1058 | Q5: 1209.0135 | R5: =+Data!F90/1000 -> 1.1460506 | S5: 1.2456868 | T5: =+S5*($X5/$S5)^(0.111111111111111) -> 1.2148591 | U5: =+T5*($X5/$S5)^(0.111111111111111) -> 1.1847943 | V5: =+U5*($X5/$S5)^(0.111111111111111) -> 1.1554736 | W5: =+V5*($X5/$S5)^(0.111111111111111) -> 1.1268784 | X5: =+BT4 -> 0.99417388 | Y5: =+(X5*Z5)^0.5 -> 1.0488756 | Z5: =+BU4 -> 1.1065871 | AA5: =+(Z5*AB5)^0.5 -> 1.1473624 | AB5: =+BV4 -> 1.1896401 | AC5: =+(AB5*AD5)^0.5 -> 1.2208363 | AD5: =+BW4 -> 1.2528505 | AE5: =+(AD5*AF5)^0.5 -> 1.2728929 | AF5: =+BX4 -> 1.293256 | AG5: =+(AF5*AH5)^0.5 -> 1.3059335 | AH5: =+BY4 -> 1.3187353 | AI5: =+(AH5*AJ5)^0.5 -> 1.3288108 | AJ5: =+BZ4 -> 1.3389633 | AK5: =+(AJ5*AL5)^0.5 -> 1.3470843 | AL5: =+CA4 -> 1.3552546 | AM5: =+(AL5*AN5)^0.5 -> 1.3618172 | AN5: =+CB4 -> 1.3684116 | AO5: =+(AN5*AP5)^0.5 -> 1.3836713 | AP5: =+CC4 -> 1.3991011 | AQ5: =+(AP5*AR5)^0.5 -> 1.4231837 | AR5: =+CD4 -> 1.4476807 | AS5: =+(AR5*AT5)^0.5 -> 1.4704785 | AT5: =+CE4 -> 1.4936354 | AU5: =+(AT5*AV5)^0.5 -> 1.5197558 | AV5: =+CF4 -> 1.5463329 | AW5: =+(AV5*AX5)^0.5 -> 1.5689006 | AX5: =+CG4 -> 1.5917976 | AY5: =+(AX5*AZ5)^0.5 -> 1.6121794 | AZ5: =+CH4 -> 1.6328222 | BA5: =+(AZ5*BB5)^0.5 -> 1.6517663 | BB5: =+CI4 -> 1.6709302 | BC5: =+(BB5*BD5)^0.5 -> 1.6888498 | BD5: =+CJ4 -> 1.7069617 | BE5: =+(BD5*BF5)^0.5 -> 1.7240922 | BF5: =+CK4 -> 1.7413946 | BG5: =+(BF5*BH5)^0.5 -> 1.7578759 | BH5: =+CL4 -> 1.7745132 | BI5: =+(BH5*BJ5)^0.5 -> 1.7910236 | BJ5: =+CM4 -> 1.8076877 | BK5: =+(BJ5*BL5)^0.5 -> 1.824441 | BL5: =+CN4 -> 1.8413496 | BN5: These are GDP times baseline sigma. | BR5: Japan | BS5: =+BS24*BS37 -> 0.36996593 | BT5: =+BT24*BT37 -> 0.3821269 | BU5: =+BU24*BU37 -> 0.38413432 | BV5: =+BV24*BV37 -> 0.37226152 | BW5: =+BW24*BW37 -> 0.34678852 | BX5: =+BX24*BX37 -> 0.33340003 | BY5: =+BY24*BY37 -> 0.32645083 | BZ5: =+BZ24*BZ37 -> 0.31908299 | ... DZ5: =+DZ24*DZ37 -> 0.53567144
A6: Japan | B6: CO2 | C6: 0.28739327 | D6: 0.29282076 | E6: 0.29413074 | F6: 0.2923795 | G6: 0.30724282 | H6: 0.30534201 | I6: 0.31042222 | J6: 0.3166974 | K6: 0.30431593 | L6: 0.31579449 | M6: 0.32828451 | N6: 326.49504 | O6: 328.18093 | P6: 341.80733 | Q6: 343.06196 | R6: =+Data!F91/1000 -> 0.36996593 | S6: 0.34947436 | T6: =+S6*($X6/$S6)^(0.111111111111111) -> 0.35296006 | U6: =+T6*($X6/$S6)^(0.111111111111111) -> 0.35648054 | V6: =+U6*($X6/$S6)^(0.111111111111111) -> 0.36003613 | W6: =+V6*($X6/$S6)^(0.111111111111111) -> 0.36362718 | X6: =+BT5 -> 0.3821269 | Y6: =+(X6*Z6)^0.5 -> 0.38312929 | Z6: =+BU5 -> 0.38413432 | AA6: =+(Z6*AB6)^0.5 -> 0.37815133 | AB6: =+BV5 -> 0.37226152 | AC6: =+(AB6*AD6)^0.5 -> 0.35929935 | AD6: =+BW5 -> 0.34678852 | AE6: =+(AD6*AF6)^0.5 -> 0.34002838 | AF6: =+BX5 -> 0.33340003 | AG6: =+(AF6*AH6)^0.5 -> 0.32990714 | AH6: =+BY5 -> 0.32645083 | AI6: =+(AH6*AJ6)^0.5 -> 0.32274589 | AJ6: =+BZ5 -> 0.31908299 | AK6: =+(AJ6*AL6)^0.5 -> 0.31533253 | AL6: =+CA5 -> 0.31162614 | AM6: =+(AL6*AN6)^0.5 -> 0.30793007 | AN6: =+CB5 -> 0.30427782 | AO6: =+(AN6*AP6)^0.5 -> 0.30412953 | AP6: =+CC5 -> 0.3039813 | AQ6: =+(AP6*AR6)^0.5 -> 0.30714788 | AR6: =+CD5 -> 0.31034745 | AS6: =+(AR6*AT6)^0.5 -> 0.31330668 | AT6: =+CE5 -> 0.31629412 | AU6: =+(AT6*AV6)^0.5 -> 0.32050378 | AV6: =+CF5 -> 0.32476946 | AW6: =+(AV6*AX6)^0.5 -> 0.32816189 | AX6: =+CG5 -> 0.33158975 | AY6: =+(AX6*AZ6)^0.5 -> 0.33455197 | AZ6: =+CH5 -> 0.33754066 | BA6: =+(AZ6*BB6)^0.5 -> 0.34027599 | BB6: =+CI5 -> 0.34303349 | BC6: =+(BB6*BD6)^0.5 -> 0.34564929 | BD6: =+CJ5 -> 0.34828503 | BE6: =+(BD6*BF6)^0.5 -> 0.35083832 | BF6: =+CK5 -> 0.35341034 | BG6: =+(BF6*BH6)^0.5 -> 0.35593174 | BH6: =+CL5 -> 0.35847113 | BI6: =+(BH6*BJ6)^0.5 -> 0.36104768 | BJ6: =+CM5 -> 0.36364276 | BK6: =+(BJ6*BL6)^0.5 -> 0.36630116 | BL6: =+CN5 -> 0.368979 | BR6: Russia | BS6: =+BS25*BS38 -> 0.43123618 | BT6: =+BT25*BT38 -> 0.4233036 | BU6: =+BU25*BU38 -> 0.44350907 | BV6: =+BV25*BV38 -> 0.44937555 | BW6: =+BW25*BW38 -> 0.45134077 | BX6: =+BX25*BX38 -> 0.45182364 | BY6: =+BY25*BY38 -> 0.45092789 | BZ6: =+BZ25*BZ38 -> 0.44798158 | ... DZ6: =+DZ25*DZ38 -> 0.97052474
A7: Russia | B7: CO2 | C7: 0.65 | D7: 0.61184829 | E7: 0.56087893 | F7: 0.52136945 | G7: 0.47046207 | H7: 0.44683469 | I7: 0.4409178 | J7: 0.40442462 | K7: 0.40431502 | L7: 0.42557105 | M7: 0.43155591 | N7: 428.49464 | O7: 428.66667 | P7: 443.69014 | Q7: 453.66629 | R7: =+Data!F92/1000 -> 0.43123618 | S7: 0.47766632 | T7: =+S7*($X7/$S7)^(0.111111111111111) -> 0.47129662 | U7: =+T7*($X7/$S7)^(0.111111111111111) -> 0.46501186 | V7: =+U7*($X7/$S7)^(0.111111111111111) -> 0.45881091 | W7: =+V7*($X7/$S7)^(0.111111111111111) -> 0.45269265 | X7: =+BT6 -> 0.4233036 | Y7: =+(X7*Z7)^0.5 -> 0.43328857 | Z7: =+BU6 -> 0.44350907 | AA7: =+(Z7*AB7)^0.5 -> 0.44643267 | AB7: =+BV6 -> 0.44937555 | AC7: =+(AB7*AD7)^0.5 -> 0.45035709 | AD7: =+BW6 -> 0.45134077 | AE7: =+(AD7*AF7)^0.5 -> 0.45158214 | AF7: =+BX6 -> 0.45182364 | AG7: =+(AF7*AH7)^0.5 -> 0.45137554 | AH7: =+BY6 -> 0.45092789 | AI7: =+(AH7*AJ7)^0.5 -> 0.44945233 | AJ7: =+BZ6 -> 0.44798158 | AK7: =+(AJ7*AL7)^0.5 -> 0.44578074 | AL7: =+CA6 -> 0.44359071 | AM7: =+(AL7*AN7)^0.5 -> 0.44088161 | AN7: =+CB6 -> 0.43818905 | AO7: =+(AN7*AP7)^0.5 -> 0.44144314 | AP7: =+CC6 -> 0.44472141 | AQ7: =+(AP7*AR7)^0.5 -> 0.453921 | AR7: =+CD6 -> 0.4633109 | AS7: =+(AR7*AT7)^0.5 -> 0.47219469 | AT7: =+CE6 -> 0.48124882 | AU7: =+(AT7*AV7)^0.5 -> 0.49158188 | AV7: =+CF6 -> 0.5021368 | AW7: =+(AV7*AX7)^0.5 -> 0.51140736 | AX7: =+CG6 -> 0.52084907 | AY7: =+(AX7*AZ7)^0.5 -> 0.5294963 | AZ7: =+CH6 -> 0.5382871 | BA7: =+(AZ7*BB7)^0.5 -> 0.54654896 | BB7: =+CI6 -> 0.55493762 | BC7: =+(BB7*BD7)^0.5 -> 0.56294552 | BD7: =+CJ6 -> 0.57106897 | BE7: =+(BD7*BF7)^0.5 -> 0.57889771 | BF7: =+CK6 -> 0.58683378 | BG7: =+(BF7*BH7)^0.5 -> 0.59452808 | BH7: =+CL6 -> 0.60232327 | BI7: =+(BH7*BJ7)^0.5 -> 0.6095731 | BJ7: =+CM6 -> 0.61691019 | BK7: =+(BJ7*BL7)^0.5 -> 0.62364124 | BL7: =+CN6 -> 0.63044573 | BR7: Eurasia | BS7: =+BS26*BS39 -> 0.25666629 | BT7: =+BT26*BT39 -> 0.2334799 | BU7: =+BU26*BU39 -> 0.26366164 | BV7: =+BV26*BV39 -> 0.28548422 | BW7: =+BW26*BW39 -> 0.30222282 | BX7: =+BX26*BX39 -> 0.31418853 | BY7: =+BY26*BY39 -> 0.32360864 | BZ7: =+BZ26*BZ39 -> 0.3312876 | ... DZ7: =+DZ26*DZ39 -> 0.78473696
A8: Eurasia | B8: CO2 | C8: 0.49278319 | D8: 0.44153092 | E8: 0.40771385 | F8: 0.36873947 | G8: 0.31200542 | H8: 0.30759703 | I8: 0.29745264 | J8: 0.28464316 | K8: 0.2775503 | L8: 0.27185485 | M8: 0.27836626 | N8: 278.49712 | O8: 284.89924 | P8: 303.94116 | Q8: 310.17162 | R8: =+Data!F93/1000 -> 0.25666629 | S8: 0.32641456 | T8: =+S8*($X8/$S8)^(0.111111111111111) -> 0.3144855 | U8: =+T8*($X8/$S8)^(0.111111111111111) -> 0.3029924 | V8: =+U8*($X8/$S8)^(0.111111111111111) -> 0.29191932 | W8: =+V8*($X8/$S8)^(0.111111111111111) -> 0.28125092 | X8: =+BT7 -> 0.2334799 | Y8: =+(X8*Z8)^0.5 -> 0.24811226 | Z8: =+BU7 -> 0.26366164 | AA8: =+(Z8*AB8)^0.5 -> 0.27435604 | AB8: =+BV7 -> 0.28548422 | AC8: =+(AB8*AD8)^0.5 -> 0.29373431 | AD8: =+BW7 -> 0.30222282 | AE8: =+(AD8*AF8)^0.5 -> 0.3081476 | AF8: =+BX7 -> 0.31418853 | AG8: =+(AF8*AH8)^0.5 -> 0.3188638 | AH8: =+BY7 -> 0.32360864 | AI8: =+(AH8*AJ8)^0.5 -> 0.32742561 | AJ8: =+BZ7 -> 0.3312876 | AK8: =+(AJ8*AL8)^0.5 -> 0.33441249 | AL8: =+CA7 -> 0.33756686 | AM8: =+(AL8*AN8)^0.5 -> 0.34012764 | AN8: =+CB7 -> 0.34270784 | AO8: =+(AN8*AP8)^0.5 -> 0.34767296 | AP8: =+CC7 -> 0.35271001 | AQ8: =+(AP8*AR8)^0.5 -> 0.36018994 | AR8: =+CD7 -> 0.36782849 | AS8: =+(AR8*AT8)^0.5 -> 0.37495338 | AT8: =+CE7 -> 0.38221627 | AU8: =+(AT8*AV8)^0.5 -> 0.38991112 | AV8: =+CF7 -> 0.39776089 | AW8: =+(AV8*AX8)^0.5 -> 0.40469564 | AX8: =+CG7 -> 0.4117513 | AY8: =+(AX8*AZ8)^0.5 -> 0.4181554 | AZ8: =+CH7 -> 0.42465911 | BA8: =+(AZ8*BB8)^0.5 -> 0.4306588 | BB8: =+CI7 -> 0.43674325 | BC8: =+(BB8*BD8)^0.5 -> 0.442411 | BD8: =+CJ7 -> 0.4481523 | BE8: =+(BD8*BF8)^0.5 -> 0.45353262 | BF8: =+CK7 -> 0.45897753 | BG8: =+(BF8*BH8)^0.5 -> 0.46410041 | BH8: =+CL7 -> 0.46928046 | BI8: =+(BH8*BJ8)^0.5 -> 0.47461179 | BJ8: =+CM7 -> 0.48000369 | BK8: =+(BJ8*BL8)^0.5 -> 0.48568286 | BL8: =+CN7 -> 0.49142922 | BR8: China | BS8: =+BS27*BS40 -> 1.6007411 | BT8: =+BT27*BT40 -> 2.8437372 | BU8: =+BU27*BU40 -> 3.2081467 | BV8: =+BV27*BV40 -> 3.4276862 | BW8: =+BW27*BW40 -> 3.5457433 | BX8: =+BX27*BX40 -> 3.5874954 | BY8: =+BY27*BY40 -> 3.6144994 | BZ8: =+BZ27*BZ40 -> 3.6262201 | ... DZ8: =+DZ27*DZ40 -> 4.7411556
A9: China | B9: CO2 | C9: 0.6254707 | D9: 0.65491687 | E9: 0.67507297 | F9: 0.72020511 | G9: 0.77884801 | H9: 0.79183438 | I9: 0.8009954 | J9: 0.8544924 | K9: 0.82614492 | L9: 0.81603302 | M9: 0.80905105 | N9: 847.63441 | O9: 938.3461 | P9: 1107.7219 | Q9: 1322.0005 | R9: =+Data!F94/1000 -> 1.6007411 | S9: 1.8049916 | T9: =+S9*($X9/$S9)^(0.111111111111111) -> 1.8984978 | U9: =+T9*($X9/$S9)^(0.111111111111111) -> 1.9968481 | V9: =+U9*($X9/$S9)^(0.111111111111111) -> 2.1002933 | W9: =+V9*($X9/$S9)^(0.111111111111111) -> 2.2090974 | X9: =+BT8 -> 2.8437372 | Y9: =+(X9*Z9)^0.5 -> 3.0204513 | Z9: =+BU8 -> 3.2081467 | AA9: =+(Z9*AB9)^0.5 -> 3.3161002 | AB9: =+BV8 -> 3.4276862 | AC9: =+(AB9*AD9)^0.5 -> 3.4862151 | AD9: =+BW8 -> 3.5457433 | AE9: =+(AD9*AF9)^0.5 -> 3.5665582 | AF9: =+BX8 -> 3.5874954 | AG9: =+(AF9*AH9)^0.5 -> 3.6009721 | AH9: =+BY8 -> 3.6144994 | AI9: =+(AH9*AJ9)^0.5 -> 3.620355 | AJ9: =+BZ8 -> 3.6262201 | AK9: =+(AJ9*AL9)^0.5 -> 3.6264298 | AL9: =+CA8 -> 3.6266396 | AM9: =+(AL9*AN9)^0.5 -> 3.6217952 | AN9: =+CB8 -> 3.6169572 | AO9: =+(AN9*AP9)^0.5 -> 3.6399494 | AP9: =+CC8 -> 3.6630877 | AQ9: =+(AP9*AR9)^0.5 -> 3.7157695 | AR9: =+CD8 -> 3.7692089 | AS9: =+(AR9*AT9)^0.5 -> 3.8227498 | AT9: =+CE8 -> 3.8770512 | AU9: =+(AT9*AV9)^0.5 -> 3.9157743 | AV9: =+CF8 -> 3.9548843 | AW9: =+(AV9*AX9)^0.5 -> 3.9935063 | AX9: =+CG8 -> 4.0325055 | AY9: =+(AX9*AZ9)^0.5 -> 4.069863 | AZ9: =+CH8 -> 4.1075665 | BA9: =+(AZ9*BB9)^0.5 -> 4.1430371 | BB9: =+CI8 -> 4.1788141 | BC9: =+(BB9*BD9)^0.5 -> 4.2121016 | BD9: =+CJ8 -> 4.2456543 | BE9: =+(BD9*BF9)^0.5 -> 4.2766349 | BF9: =+CK8 -> 4.3078414 | BG9: =+(BF9*BH9)^0.5 -> 4.3364817 | BH9: =+CL8 -> 4.3653125 | BI9: =+(BH9*BJ9)^0.5 -> 4.3956157 | BJ9: =+CM8 -> 4.4261294 | BK9: =+(BJ9*BL9)^0.5 -> 4.4591005 | BL9: =+CN8 -> 4.4923171 | BR9: India | BS9: =+BS28*BS41 -> 0.40515159 | BT9: =+BT28*BT41 -> 0.72309374 | BU9: =+BU28*BU41 -> 0.95176955 | BV9: =+BV28*BV41 -> 1.1736542 | BW9: =+BW28*BW41 -> 1.3875149 | BX9: =+BX28*BX41 -> 1.5656464 | BY9: =+BY28*BY41 -> 1.7181345 | BZ9: =+BZ28*BZ41 -> 1.8663056 | ... DZ9: =+DZ28*DZ41 -> 5.3413525
A10: India | B10: CO2 | C10: 0.15906719 | D10: 0.17074799 | E10: 0.18135275 | F10: 0.19005721 | G10: 0.20195824 | H10: 0.23957308 | I10: 0.22777229 | J10: 0.23940651 | K10: 0.24932186 | L10: 0.26484964 | M10: 0.2760937 | N10: 282.38705 | O10: 281.87084 | P10: 285.84978 | Q10: 313.99888 | R10: =+Data!F95/1000 -> 0.40515159 | S10: 0.37448305 | T10: =+S10*($X10/$S10)^(0.111111111111111) -> 0.40288727 | U10: =+T10*($X10/$S10)^(0.111111111111111) -> 0.43344593 | V10: =+U10*($X10/$S10)^(0.111111111111111) -> 0.46632243 | W10: =+V10*($X10/$S10)^(0.111111111111111) -> 0.5016926 | X10: =+BT9 -> 0.72309374 | Y10: =+(X10*Z10)^0.5 -> 0.82958942 | Z10: =+BU9 -> 0.95176955 | AA10: =+(Z10*AB10)^0.5 -> 1.0569051 | AB10: =+BV9 -> 1.1736542 | AC10: =+(AB10*AD10)^0.5 -> 1.2761124 | AD10: =+BW9 -> 1.3875149 | AE10: =+(AD10*AF10)^0.5 -> 1.473892 | AF10: =+BX9 -> 1.5656464 | AG10: =+(AF10*AH10)^0.5 -> 1.6401192 | AH10: =+BY9 -> 1.7181345 | AI10: =+(AH10*AJ10)^0.5 -> 1.7906882 | AJ10: =+BZ9 -> 1.8663056 | AK10: =+(AJ10*AL10)^0.5 -> 1.9369635 | AL10: =+CA9 -> 2.0102965 | AM10: =+(AL10*AN10)^0.5 -> 2.0790806 | AN10: =+CB9 -> 2.1502183 | AO10: =+(AN10*AP10)^0.5 -> 2.2164386 | AP10: =+CC9 -> 2.2846983 | AQ10: =+(AP10*AR10)^0.5 -> 2.347605 | AR10: =+CD9 -> 2.4122438 | AS10: =+(AR10*AT10)^0.5 -> 2.471467 | AT10: =+CE9 -> 2.5321442 | AU10: =+(AT10*AV10)^0.5 -> 2.5905336 | AV10: =+CF9 -> 2.6502696 | AW10: =+(AV10*AX10)^0.5 -> 2.7033098 | AX10: =+CG9 -> 2.7574115 | AY10: =+(AX10*AZ10)^0.5 -> 2.8057602 | AZ10: =+CH9 -> 2.8549567 | BA10: =+(AZ10*BB10)^0.5 -> 2.8990036 | BB10: =+CI9 -> 2.9437301 | BC10: =+(BB10*BD10)^0.5 -> 2.983738 | BD10: =+CJ9 -> 3.0242896 | BE10: =+(BD10*BF10)^0.5 -> 3.0604658 | BF10: =+CK9 -> 3.0970748 | BG10: =+(BF10*BH10)^0.5 -> 3.1296065 | BH10: =+CL9 -> 3.1624799 | BI10: =+(BH10*BJ10)^0.5 -> 3.2005924 | BJ10: =+CM9 -> 3.2391643 | BK10: =+(BJ10*BL10)^0.5 -> 3.2855102 | BL10: =+CN9 -> 3.3325193 | BR10: Middle East | BS10: =+BS29*BS42 -> 0.58967496 | BT10: =+BT29*BT42 -> 0.80742719 | BU10: =+BU29*BU42 -> 1.0442826 | BV10: =+BV29*BV42 -> 1.2745456 | BW10: =+BW29*BW42 -> 1.4943414 | BX10: =+BX29*BX42 -> 1.6740554 | BY10: =+BY29*BY42 -> 1.833119 | BZ10: =+BZ29*BZ42 -> 1.996089 | ... DZ10: =+DZ29*DZ42 -> 4.5027007
A11: Middle East | B11: CO2 | C11: 0.20049331 | D11: 0.2152186 | E11: 0.22396094 | F11: 0.23110308 | G11: 0.24328161 | H11: 0.24774751 | I11: 0.25684861 | J11: 0.27153551 | K11: 0.27999073 | L11: 0.29031549 | M11: 0.30034675 | N11: 307.34831 | O11: 322.76706 | P11: 340.50429 | Q11: 365.10009 | R11: =+Data!F96/1000 -> 0.58967496 | S11: 0.42395284 | T11: =+S11*($X11/$S11)^(0.111111111111111) -> 0.45541241 | U11: =+T11*($X11/$S11)^(0.111111111111111) -> 0.48920645 | V11: =+U11*($X11/$S11)^(0.111111111111111) -> 0.52550819 | W11: =+V11*($X11/$S11)^(0.111111111111111) -> 0.56450371 | X11: =+BT10 -> 0.80742719 | Y11: =+(X11*Z11)^0.5 -> 0.91824951 | Z11: =+BU10 -> 1.0442826 | AA11: =+(Z11*AB11)^0.5 -> 1.1536836 | AB11: =+BV10 -> 1.2745456 | AC11: =+(AB11*AD11)^0.5 -> 1.3800747 | AD11: =+BW10 -> 1.4943414 | AE11: =+(AD11*AF11)^0.5 -> 1.581648 | AF11: =+BX10 -> 1.6740554 | AG11: =+(AF11*AH11)^0.5 -> 1.7517828 | AH11: =+BY10 -> 1.833119 | AI11: =+(AH11*AJ11)^0.5 -> 1.9128692 | AJ11: =+BZ10 -> 1.996089 | AK11: =+(AJ11*AL11)^0.5 -> 2.0785026 | AL11: =+CA10 -> 2.1643189 | AM11: =+(AL11*AN11)^0.5 -> 2.2499193 | AN11: =+CB10 -> 2.3389054 | AO11: =+(AN11*AP11)^0.5 -> 2.4011882 | AP11: =+CC10 -> 2.4651296 | AQ11: =+(AP11*AR11)^0.5 -> 2.4986748 | AR11: =+CD10 -> 2.5326765 | AS11: =+(AR11*AT11)^0.5 -> 2.5618657 | AT11: =+CE10 -> 2.5913913 | AU11: =+(AT11*AV11)^0.5 -> 2.6268888 | AV11: =+CF10 -> 2.6628725 | AW11: =+(AV11*AX11)^0.5 -> 2.6909357 | AX11: =+CG10 -> 2.7192946 | AY11: =+(AX11*AZ11)^0.5 -> 2.7423751 | AZ11: =+CH10 -> 2.7656515 | BA11: =+(AZ11*BB11)^0.5 -> 2.7851148 | BB11: =+CI10 -> 2.804715 | BC11: =+(BB11*BD11)^0.5 -> 2.8213489 | BD11: =+CJ10 -> 2.8380815 | BE11: =+(BD11*BF11)^0.5 -> 2.8523681 | BF11: =+CK10 -> 2.8667266 | BG11: =+(BF11*BH11)^0.5 -> 2.878984 | BH11: =+CL10 -> 2.8912939 | BI11: =+(BH11*BJ11)^0.5 -> 2.9094176 | BJ11: =+CM10 -> 2.9276548 | BK11: =+(BJ11*BL11)^0.5 -> 2.9536377 | BL11: =+CN10 -> 2.9798512 | BR11: Africa | BS11: =+BS30*BS43 -> 0.19137708 | BT11: =+BT30*BT43 -> 0.24403789 | BU11: =+BU30*BU43 -> 0.3538932 | BV11: =+BV30*BV43 -> 0.48200313 | BW11: =+BW30*BW43 -> 0.62603054 | BX11: =+BX30*BX43 -> 0.75868965 | BY11: =+BY30*BY43 -> 0.87768255 | BZ11: =+BZ30*BZ43 -> 1.0040365 | ... DZ11: =+DZ30*DZ43 -> 2.802829
A12: Africa | B12: CO2 | C12: 0.19854607 | D12: 0.20450956 | E12: 0.2081464 | F12: 0.21226851 | G12: 0.22228027 | H12: 0.22588339 | I12: 0.23072492 | J12: 0.23774204 | K12: 0.23471544 | L12: 0.23909989 | M12: 0.24329177 | N12: 251.60479 | O12: 252.02775 | P12: 265.83088 | Q12: 279.49586 | R12: =+Data!F97/1000 -> 0.19137708 | S12: 0.29617554 | T12: =+S12*($X12/$S12)^(0.111111111111111) -> 0.28987158 | U12: =+T12*($X12/$S12)^(0.111111111111111) -> 0.2837018 | V12: =+U12*($X12/$S12)^(0.111111111111111) -> 0.27766334 | W12: =+V12*($X12/$S12)^(0.111111111111111) -> 0.2717534 | X12: =+BT11 -> 0.24403789 | Y12: =+(X12*Z12)^0.5 -> 0.29387642 | Z12: =+BU11 -> 0.3538932 | AA12: =+(Z12*AB12)^0.5 -> 0.41301045 | AB12: =+BV11 -> 0.48200313 | AC12: =+(AB12*AD12)^0.5 -> 0.54931656 | AD12: =+BW11 -> 0.62603054 | AE12: =+(AD12*AF12)^0.5 -> 0.68917552 | AF12: =+BX11 -> 0.75868965 | AG12: =+(AF12*AH12)^0.5 -> 0.81602002 | AH12: =+BY11 -> 0.87768255 | AI12: =+(AH12*AJ12)^0.5 -> 0.93873603 | AJ12: =+BZ11 -> 1.0040365 | AK12: =+(AJ12*AL12)^0.5 -> 1.0688661 | AL12: =+CA11 -> 1.1378816 | AM12: =+(AL12*AN12)^0.5 -> 1.206489 | AN12: =+CB11 -> 1.279233 | AO12: =+(AN12*AP12)^0.5 -> 1.3328655 | AP12: =+CC11 -> 1.3887466 | AQ12: =+(AP12*AR12)^0.5 -> 1.4223626 | AR12: =+CD11 -> 1.4567924 | AS12: =+(AR12*AT12)^0.5 -> 1.4877433 | AT12: =+CE11 -> 1.5193518 | AU12: =+(AT12*AV12)^0.5 -> 1.546771 | AV12: =+CF11 -> 1.5746849 | AW12: =+(AV12*AX12)^0.5 -> 1.5989417 | AX12: =+CG11 -> 1.6235722 | AY12: =+(AX12*AZ12)^0.5 -> 1.6447034 | AZ12: =+CH11 -> 1.6661096 | BA12: =+(AZ12*BB12)^0.5 -> 1.6841923 | BB12: =+CI11 -> 1.7024713 | BC12: =+(BB12*BD12)^0.5 -> 1.7176166 | BD12: =+CJ11 -> 1.7328966 | BE12: =+(BD12*BF12)^0.5 -> 1.7452417 | BF12: =+CK11 -> 1.7576747 | BG12: =+(BF12*BH12)^0.5 -> 1.7673762 | BH12: =+CL11 -> 1.7771312 | BI12: =+(BH12*BJ12)^0.5 -> 1.7895603 | BJ12: =+CM11 -> 1.8020764 | BK12: =+(BJ12*BL12)^0.5 -> 1.8186495 | BL12: =+CN11 -> 1.835375 | BR12: Latin America | BS12: =+BS31*BS44 -> 0.4122724 | BT12: =+BT31*BT44 -> 0.53297093 | BU12: =+BU31*BU44 -> 0.67605786 | BV12: =+BV31*BV44 -> 0.81226941 | BW12: =+BW31*BW44 -> 0.9344028 | BX12: =+BX31*BX44 -> 1.0349445 | BY12: =+BY31*BY44 -> 1.1250175 | BZ12: =+BZ31*BZ44 -> 1.2118046 | ... DZ12: =+DZ31*DZ44 -> 3.5519327
A13: Latin America | B13: CO2 | C13: 0.27824259 | D13: 0.28635761 | E13: 0.28869316 | F13: 0.30063826 | G13: 0.31365956 | H13: 0.32197631 | I13: 0.33752403 | J13: 0.35467966 | K13: 0.36754044 | L13: 0.36771921 | M13: 0.37550306 | N13: 380.85493 | O13: 378.92025 | P13: 385.19699 | Q13: 395.76855 | R13: =+Data!F98/1000 -> 0.4122724 | S13: 1.2005105 | T13: =+S13*($X13/$S13)^(0.111111111111111) -> 1.0969359 | U13: =+T13*($X13/$S13)^(0.111111111111111) -> 1.0022972 | V13: =+U13*($X13/$S13)^(0.111111111111111) -> 0.91582356 | W13: =+V13*($X13/$S13)^(0.111111111111111) -> 0.83681045 | X13: =+BT12 -> 0.53297093 | Y13: =+(X13*Z13)^0.5 -> 0.60026593 | Z13: =+BU12 -> 0.67605786 | AA13: =+(Z13*AB13)^0.5 -> 0.74104057 | AB13: =+BV12 -> 0.81226941 | AC13: =+(AB13*AD13)^0.5 -> 0.87119849 | AD13: =+BW12 -> 0.9344028 | AE13: =+(AD13*AF13)^0.5 -> 0.98338957 | AF13: =+BX12 -> 1.0349445 | AG13: =+(AF13*AH13)^0.5 -> 1.0790416 | AH13: =+BY12 -> 1.1250175 | AI13: =+(AH13*AJ13)^0.5 -> 1.167605 | AJ13: =+BZ12 -> 1.2118046 | AK13: =+(AJ13*AL13)^0.5 -> 1.2529998 | AL13: =+CA12 -> 1.2955956 | AM13: =+(AL13*AN13)^0.5 -> 1.3355077 | AN13: =+CB12 -> 1.3766494 | AO13: =+(AN13*AP13)^0.5 -> 1.4162167 | AP13: =+CC12 -> 1.4569213 | AQ13: =+(AP13*AR13)^0.5 -> 1.4956193 | AR13: =+CD12 -> 1.5353451 | AS13: =+(AR13*AT13)^0.5 -> 1.5713752 | AT13: =+CE12 -> 1.6082507 | AU13: =+(AT13*AV13)^0.5 -> 1.6473425 | AV13: =+CF12 -> 1.6873844 | AW13: =+(AV13*AX13)^0.5 -> 1.7218478 | AX13: =+CG12 -> 1.7570151 | AY13: =+(AX13*AZ13)^0.5 -> 1.7880495 | AZ13: =+CH12 -> 1.819632 | BA13: =+(AZ13*BB13)^0.5 -> 1.8479104 | BB13: =+CI12 -> 1.8766283 | BC13: =+(BB13*BD13)^0.5 -> 1.902547 | BD13: =+CJ12 -> 1.9288237 | BE13: =+(BD13*BF13)^0.5 -> 1.9526343 | BF13: =+CK12 -> 1.9767389 | BG13: =+(BF13*BH13)^0.5 -> 1.9986186 | BH13: =+CL12 -> 2.0207405 | BI13: =+(BH13*BJ13)^0.5 -> 2.0455892 | BJ13: =+CM12 -> 2.0707433 | BK13: =+(BJ13*BL13)^0.5 -> 2.0999905 | BL13: =+CN12 -> 2.1296507 | BR13: OHI | BS13: =+BS32*BS45 -> 0.54177826 | BT13: =+BT32*BT45 -> 0.56968411 | BU13: =+BU32*BU45 -> 0.6201888 | BV13: =+BV32*BV45 -> 0.65030377 | BW13: =+BW32*BW45 -> 0.66267477 | BX13: =+BX32*BX45 -> 0.6599133 | BY13: =+BY32*BY45 -> 0.64909067 | BZ13: =+BZ32*BZ45 -> 0.63786769 | ... DZ13: =+DZ32*DZ45 -> 0.91560295
A14: OHI | B14: CO2 | C14: 0.33677458 | D14: 0.34238599 | E14: 0.36256086 | F14: 0.38394934 | G14: 0.39767069 | H14: 0.4176195 | I14: 0.43891958 | J14: 0.46641929 | K14: 0.45946358 | L14: 0.48737326 | M14: 0.49725585 | N14: 502.10272 | O14: 522.20783 | P14: 538.80828 | Q14: 552.33803 | R14: =+Data!F99/1000 -> 0.54177826 | S14: 0.59205349 | T14: =+S14*($X14/$S14)^(0.111111111111111) -> 0.58952525 | U14: =+T14*($X14/$S14)^(0.111111111111111) -> 0.5870078 | V14: =+U14*($X14/$S14)^(0.111111111111111) -> 0.5845011 | W14: =+V14*($X14/$S14)^(0.111111111111111) -> 0.58200511 | X14: =+BT13 -> 0.56968411 | Y14: =+(X14*Z14)^0.5 -> 0.59440029 | Z14: =+BU13 -> 0.6201888 | AA14: =+(Z14*AB14)^0.5 -> 0.6350678 | AB14: =+BV13 -> 0.65030377 | AC14: =+(AB14*AD14)^0.5 -> 0.65646013 | AD14: =+BW13 -> 0.66267477 | AE14: =+(AD14*AF14)^0.5 -> 0.66129259 | AF14: =+BX13 -> 0.6599133 | AG14: =+(AF14*AH14)^0.5 -> 0.65447961 | AH14: =+BY13 -> 0.64909067 | AI14: =+(AH14*AJ14)^0.5 -> 0.64345471 | AJ14: =+BZ13 -> 0.63786769 | AK14: =+(AJ14*AL14)^0.5 -> 0.63230443 | AL14: =+CA13 -> 0.6267897 | AM14: =+(AL14*AN14)^0.5 -> 0.62140316 | AN14: =+CB13 -> 0.61606292 | AO14: =+(AN14*AP14)^0.5 -> 0.61576176 | AP14: =+CC13 -> 0.61546075 | AQ14: =+(AP14*AR14)^0.5 -> 0.61992658 | AR14: =+CD13 -> 0.6244248 | AS14: =+(AR14*AT14)^0.5 -> 0.62873696 | AT14: =+CE13 -> 0.63307889 | AU14: =+(AT14*AV14)^0.5 -> 0.63895669 | AV14: =+CF13 -> 0.64488907 | AW14: =+(AV14*AX14)^0.5 -> 0.64958664 | AX14: =+CG13 -> 0.65431843 | AY14: =+(AX14*AZ14)^0.5 -> 0.65841664 | AZ14: =+CH13 -> 0.66254051 | BA14: =+(AZ14*BB14)^0.5 -> 0.6663418 | BB14: =+CI13 -> 0.6701649 | BC14: =+(BB14*BD14)^0.5 -> 0.67382414 | BD14: =+CJ13 -> 0.67750335 | BE14: =+(BD14*BF14)^0.5 -> 0.68109882 | BF14: =+CK13 -> 0.68471337 | BG14: =+(BF14*BH14)^0.5 -> 0.68828363 | BH14: =+CL13 -> 0.69187252 | BI14: =+(BH14*BJ14)^0.5 -> 0.69553428 | BJ14: =+CM13 -> 0.69921542 | BK14: =+(BJ14*BL14)^0.5 -> 0.70299927 | BL14: =+CN13 -> 0.70680359 | BR14: Other non-OECD Asia | BS14: =+BS33*BS46 -> 0.3639521 | BT14: =+BT33*BT46 -> 0.63080748 | BU14: =+BU33*BU46 -> 0.87865736 | BV14: =+BV33*BV46 -> 1.1513158 | BW14: =+BW33*BW46 -> 1.4382782 | BX14: =+BX33*BX46 -> 1.7044021 | BY14: =+BY33*BY46 -> 1.9543915 | BZ14: =+BZ33*BZ46 -> 2.2122581 | ... DZ14: =+DZ33*DZ46 -> 5.4401024
A15: Other non-OECD Asia | B15: CO2 | C15: 0.16534354 | D15: 0.16964405 | E15: 0.1748069 | F15: 0.19063363 | G15: 0.20038327 | H15: 0.21093045 | I15: 0.22882929 | J15: 0.23439201 | K15: 0.22954883 | L15: 0.24609386 | M15: 0.25130829 | N15: 266.12022 | O15: 280.46252 | P15: 290.98783 | Q15: 313.90175 | R15: =+Data!F100/1000 -> 0.3639521 | S15: 0.69318938 | T15: =+S15*($X15/$S15)^(0.111111111111111) -> 0.68596402 | U15: =+T15*($X15/$S15)^(0.111111111111111) -> 0.67881398 | V15: =+U15*($X15/$S15)^(0.111111111111111) -> 0.67173846 | W15: =+V15*($X15/$S15)^(0.111111111111111) -> 0.66473669 | X15: =+BT14 -> 0.63080748 | Y15: =+(X15*Z15)^0.5 -> 0.74448884 | Z15: =+BU14 -> 0.87865736 | AA15: =+(Z15*AB15)^0.5 -> 1.0057893 | AB15: =+BV14 -> 1.1513158 | AC15: =+(AB15*AD15)^0.5 -> 1.2868226 | AD15: =+BW14 -> 1.4382782 | AE15: =+(AD15*AF15)^0.5 -> 1.5656961 | AF15: =+BX14 -> 1.7044021 | AG15: =+(AF15*AH15)^0.5 -> 1.8251216 | AH15: =+BY14 -> 1.9543915 | AI15: =+(AH15*AJ15)^0.5 -> 2.0793313 | AJ15: =+BZ14 -> 2.2122581 | AK15: =+(AJ15*AL15)^0.5 -> 2.3409478 | AL15: =+CA14 -> 2.4771236 | AM15: =+(AL15*AN15)^0.5 -> 2.6090692 | AN15: =+CB14 -> 2.748043 | AO15: =+(AN15*AP15)^0.5 -> 2.8697884 | AP15: =+CC14 -> 2.9969274 | AQ15: =+(AP15*AR15)^0.5 -> 3.1048868 | AR15: =+CD14 -> 3.2167352 | AS15: =+(AR15*AT15)^0.5 -> 3.3232863 | AT15: =+CE14 -> 3.4333667 | AU15: =+(AT15*AV15)^0.5 -> 3.5258238 | AV15: =+CF14 -> 3.6207706 | AW15: =+(AV15*AX15)^0.5 -> 3.7101276 | AX15: =+CG14 -> 3.8016898 | AY15: =+(AX15*AZ15)^0.5 -> 3.8864537 | AZ15: =+CH14 -> 3.9731076 | BA15: =+(AZ15*BB15)^0.5 -> 4.0523948 | BB15: =+CI14 -> 4.1332643 | BC15: =+(BB15*BD15)^0.5 -> 4.2065698 | BD15: =+CJ14 -> 4.2811754 | BE15: =+(BD15*BF15)^0.5 -> 4.3482341 | BF15: =+CK14 -> 4.4163432 | BG15: =+(BF15*BH15)^0.5 -> 4.4770477 | BH15: =+CL14 -> 4.5385866 | BI15: =+(BH15*BJ15)^0.5 -> 4.6052325 | BJ15: =+CM14 -> 4.672857 | BK15: =+(BJ15*BL15)^0.5 -> 4.7490584 | BL15: =+CN14 -> 4.8265025
A16: World | B16: CO2 | C16: =SUM(C4:C15) -> 5.8993197 | D16: =SUM(D4:D15) -> 5.8796183 | E16: =SUM(E4:E15) -> 5.8663849 | F16: =SUM(F4:F15) -> 5.9350135 | G16: =SUM(G4:G15) -> 5.9814283 | H16: =SUM(H4:H15) -> 6.0774693 | I16: =SUM(I4:I15) -> 6.2197216 | J16: =SUM(J4:J15) -> 6.3400686 | ... M16: =SUM(M4:M15) -> 6.5483745 | N16: 6614.6014 | O16: 6770.0034 | P16: 7108.366 | Q16: 7487.2771 | R16: =SUM(R4:R15) -> 7.971 | S16: =SUM(S4:S15) -> 9.408806 | T16: =SUM(T4:T15) -> 9.3968677 | U16: =SUM(U4:U15) -> 9.4047371 | V16: =SUM(V4:V15) -> 9.4321917 | W16: =SUM(W4:W15) -> 9.4791145 | X16: =SUM(X4:X15) -> 10.008732 | Y16: =+(X16*Z16)^0.5 -> 10.83274 | Z16: =SUM(Z4:Z15) -> 11.724588 | AA16: =+(Z16*AB16)^0.5 -> 0 | AB16: =+BV15 -> 0 | AC16: =+(AB16*AD16)^0.5 -> 0 | AD16: =SUM(AD4:AD15) -> 14.448589 | AE16: =+(AD16*AF16)^0.5 -> 14.936654 | AF16: =SUM(AF4:AF15) -> 15.441205 | AG16: =+(AF16*AH16)^0.5 -> 15.860538 | AH16: =SUM(AH4:AH15) -> 16.291259 | AI16: =+(AH16*AJ16)^0.5 -> 16.704295 | AJ16: =SUM(AJ4:AJ15) -> 17.127803 | AK16: =+(AJ16*AL16)^0.5 -> 17.539308 | AL16: =SUM(AL4:AL15) -> 17.960699 | AM16: =+(AL16*AN16)^0.5 -> 18.372972 | AN16: =SUM(AN4:AN15) -> 18.794708 | AO16: =+(AN16*AP16)^0.5 -> 19.205224 | AP16: =SUM(AP4:AP15) -> 19.624706 | AQ16: =+(AP16*AR16)^0.5 -> 20.019564 | AR16: =SUM(AR4:AR15) -> 20.422367 | AS16: =+(AR16*AT16)^0.5 -> 20.799858 | AT16: =SUM(AT4:AT15) -> 21.184327 | AU16: =+(AT16*AV16)^0.5 -> 21.555852 | AV16: =SUM(AV4:AV15) -> 21.933893 | AW16: =+(AV16*AX16)^0.5 -> 22.268612 | AX16: =SUM(AX4:AX15) -> 22.608439 | AY16: =+(AX16*AZ16)^0.5 -> 22.914001 | AZ16: =SUM(AZ4:AZ15) -> 23.223692 | BA16: =+(AZ16*BB16)^0.5 -> 23.504236 | BB16: =SUM(BB4:BB15) -> 23.788169 | BC16: =+(BB16*BD16)^0.5 -> 24.046115 | BD16: =SUM(BD4:BD15) -> 24.306859 | BE16: =+(BD16*BF16)^0.5 -> 24.543786 | BF16: =SUM(BF4:BF15) -> 24.783023 | BG16: =+(BF16*BH16)^0.5 -> 25.000115 | BH16: =SUM(BH4:BH15) -> 25.219108 | BI16: =+(BH16*BJ16)^0.5 -> 25.460105 | BJ16: =SUM(BJ4:BJ15) -> 25.703406 | BK16: =+(BJ16*BL16)^0.5 -> 25.980559 | BL16: =SUM(BL4:BL15) -> 26.260701
T17: =+LN(T16/S16) -> -0.0012696456 | U17: =+LN(U16/T16) -> 0.00083710533 | V17: =+LN(V16/U16) -> 0.0029149715 | W17: =+LN(W16/V16) -> 0.0049624231 | X17: =+LN(X16/W16)/5 -> 0.010873397 | Y17: =+LN(Y16/X16)/5 -> 0.015823024 | Z17: =+LN(Z16/Y16)/5 -> 0.015823024 | AA17: =+LN(AA16/Z16)/5 -> #NUM! | AB17: =+LN(AB16/AA16)/5 -> #DIV/0! | AC17: =+LN(AC16/AB16)/5 -> #DIV/0! | AD17: =+LN(AD16/AC16)/5 -> #DIV/0! | BE17: =SUM(BF5:BF16) -> 47.030753
A19: Comparison with EIA forecast of summer 2009 | BR19: THESE HAVE BEEN VALUED FROM the relevant cells shown at left
A21: stimulus.d041409a | S21: 2006 | W21: 2010 | X21: 2015 | Y21: 2020 | Z21: 2025 | AA21: 2030 | BR21: sigma
BR22: US | BS22: =+US!B40 -> 0.13406572 | BT22: =+US!C40 -> 0.10165771 | BU22: =+US!D40 -> 0.086645951 | BV22: =+US!E40 -> 0.074853084 | BW22: =+US!F40 -> 0.065454459 | BX22: =+US!G40 -> 0.057864219 | BY22: =+US!H40 -> 0.051659254 | BZ22: =+US!I40 -> 0.046529311 | ... DZ22: =+US!BI40 -> 0.006213912
A23: Reference case | BR23: EU | BS23: =+EU!B40 -> 0.08794763 | BT23: =+EU!C40 -> 0.060688422 | BU23: =+EU!D40 -> 0.05315105 | BV23: =+EU!E40 -> 0.047053454 | BW23: =+EU!F40 -> 0.042060794 | BX23: =+EU!G40 -> 0.037927052 | BY23: =+EU!H40 -> 0.034468931 | BZ23: =+EU!I40 -> 0.03154808 | ... DZ23: =+EU!BI40 -> 0.0048646243
A24: Energy Use & Related Statistics | BR24: Japan | BS24: =+Japan!B40 -> 0.095591421 | BT24: =+Japan!C40 -> 0.086339617 | BU24: =+Japan!D40 -> 0.073580888 | BV24: =+Japan!E40 -> 0.063559241 | BW24: =+Japan!F40 -> 0.055573183 | BX24: =+Japan!G40 -> 0.049124422 | BY24: =+Japan!H40 -> 0.043853139 | BZ24: =+Japan!I40 -> 0.039495521 | ... DZ24: =+Japan!BI40 -> 0.0052711525
A25: EIA reference | BR25: Russia | BS25: =+Russia!B40 -> 0.2539736 | BT25: =+Russia!C40 -> 0.18838181 | BU25: =+Russia!D40 -> 0.16085732 | BV25: =+Russia!E40 -> 0.1391928 | BW25: =+Russia!F40 -> 0.12189597 | BX25: =+Russia!G40 -> 0.10790435 | BY25: =+Russia!H40 -> 0.096449032 | BZ25: =+Russia!I40 -> 0.086965131 | ... DZ25: =+Russia!BI40 -> 0.011726951
A26: Delivered Energy Use | S26: 72.870499 | W26: 71.260292 | X26: 73.134995 | Y26: 74.432426 | Z26: 77.080086 | AA26: 78.997147 | BR26: Eurasia | BS26: =+Eurasia!B40 -> 0.31791793 | BT26: =+Eurasia!C40 -> 0.21356174 | BU26: =+Eurasia!D40 -> 0.17164354 | BV26: =+Eurasia!E40 -> 0.14064858 | BW26: =+Eurasia!F40 -> 0.11727534 | BX26: =+Eurasia!G40 -> 0.099331082 | BY26: =+Eurasia!H40 -> 0.085327704 | BZ26: =+Eurasia!I40 -> 0.074235003 | ... DZ26: =+Eurasia!BI40 -> 0.0072656521
A27: Total Energy Use | S27: 100.01835 | W27: 99.06131 | X27: 102.07816 | Y27: 104.67168 | Z27: 108.1548 | AA27: 110.9539 | BR27: China | BS27: =+China!B40 -> 0.30014462 | BT27: =+China!C40 -> 0.23814212 | BU27: =+China!D40 -> 0.18992217 | BV27: =+China!E40 -> 0.15454517 | BW27: =+China!F40 -> 0.12805646 | BX27: =+China!G40 -> 0.10785176 | BY27: =+China!H40 -> 0.092177439 | BZ27: =+China!I40 -> 0.079828243 | ... DZ27: =+China!BI40 -> 0.0074992266
A28: Ethanol Consumed in Motor Gasoline and E85 | S28: 0.47111 | W28: 1.09329 | X28: 1.238586 | Y28: 1.594389 | Z28: 1.857317 | AA28: 2.22468 | BR28: India | BS28: =+India!B40 -> 0.16598917 | BT28: =+India!C40 -> 0.15714839 | BU28: =+India!D40 -> 0.12850651 | BV28: =+India!E40 -> 0.10695303 | BW28: =+India!F40 -> 0.090437487 | BX28: =+India!G40 -> 0.077571577 | BY28: =+India!H40 -> 0.067396229 | BZ28: =+India!I40 -> 0.059236522 | ... DZ28: =+India!BI40 -> 0.0063534014
A29: Population (millions) | S29: 299.56595 | W29: 311.37262 | X29: 326.6973 | Y29: 342.55277 | Z29: 358.61899 | AA29: 374.66974 | BR29: Middle East | BS29: =+MidEast!B40 -> 0.1694418 | BT29: =+MidEast!C40 -> 0.1399896 | BU29: =+MidEast!D40 -> 0.1191518 | BV29: =+MidEast!E40 -> 0.10280619 | BW29: =+MidEast!F40 -> 0.08979668 | BX29: =+MidEast!G40 -> 0.079303339 | BY29: =+MidEast!H40 -> 0.07073491 | BZ29: =+MidEast!I40 -> 0.063658467 | ... DZ29: =+MidEast!BI40 -> 0.0084392314
A30: US GDP (billion 2000 dollars) | S30: 11294.875 | W30: 11599.082 | X30: 13450.768 | Y30: 15398.42 | Z30: 17548.301 | AA30: 19875.029 | BR30: Africa | BS30: =+Africa!B40 -> 0.14715313 | BT30: =+Africa!C40 -> 0.099316127 | BU30: =+Africa!D40 -> 0.081184737 | BV30: =+Africa!E40 -> 0.067545715 | BW30: =+Africa!F40 -> 0.057098295 | BX30: =+Africa!G40 -> 0.048962119 | BY30: =+Africa!H40 -> 0.04252926 | BZ30: =+Africa!I40 -> 0.037372053 | ... DZ30: =+Africa!BI40 -> 0.0040004962
A31: Carbon Dioxide Emissions (million metric tons) | S31: 5906.7803 | W31: 5745.9419 | X31: 5829.6899 | Y31: 5904.5942 | Z31: 6047.0762 | AA31: 6207.1416 | BR31: Latin America | BS31: =+LatAm!B40 -> 0.090440835 | BT31: =+LatAm!C40 -> 0.074879062 | BU31: =+LatAm!D40 -> 0.065279613 | BV31: =+LatAm!E40 -> 0.05755291 | BW31: =+LatAm!F40 -> 0.051255716 | BX31: =+LatAm!G40 -> 0.046064258 | BY31: =+LatAm!H40 -> 0.041738606 | BZ31: =+LatAm!I40 -> 0.03809857 | ... DZ31: =+LatAm!BI40 -> 0.0057340271
A32: sigma | S32: =+S31/S30 -> 0.5229611 | W32: =+W31/W30 -> 0.49537902 | X32: =+X31/X30 -> 0.43340946 | Y32: =+Y31/Y30 -> 0.38345455 | Z32: =+Z31/Z30 -> 0.34459611 | AA32: =+AA31/AA30 -> 0.31230855 | BR32: OHI | BS32: =+OHI!B40 -> 0.14101282 | BT32: =+OHI!C40 -> 0.11182495 | BU32: =+OHI!D40 -> 0.094286729 | BV32: =+OHI!E40 -> 0.080665066 | BW32: =+OHI!F40 -> 0.069921572 | BX32: =+OHI!G40 -> 0.061327968 | BY32: =+OHI!H40 -> 0.054364511 | BZ32: =+OHI!I40 -> 0.048654271 | ... DZ32: =+OHI!BI40 -> 0.0061362999
A33: g(sigma) | W33: =+LN(W32/S32)/5 -> -0.010836784 | X33: =+LN(X32/W32)/5 -> -0.026728049 | Y33: =+LN(Y32/X32)/5 -> -0.024492362 | Z33: =+LN(Z32/Y32)/5 -> -0.021369615 | AA33: =+LN(AA32/Z32)/5 -> -0.019676278 | BR33: Other non-OECD Asia | BS33: =+OthAsia!B40 -> 0.13895604 | BT33: =+OthAsia!C40 -> 0.15092144 | BU33: =+OthAsia!D40 -> 0.12682884 | BV33: =+OthAsia!E40 -> 0.10818142 | BW33: =+OthAsia!F40 -> 0.093520782 | BX33: =+OthAsia!G40 -> 0.081828068 | BY33: =+OthAsia!H40 -> 0.072378789 | BZ33: =+OthAsia!I40 -> 0.064649279 | ... DZ33: =+OthAsia!BI40 -> 0.0080113067
A34: RICE | BO34: BASELINE GDP | BR34: THESE HAVE BEEN VALUED FROM the relevant cells shown below
A35: Delivered Energy Use | BO35: These need to be copied | BR35: US | BS35: 12.3979 | BT35: 15.974087 | BU35: 20.701479 | BV35: 25.596423 | BW35: 30.653383 | BX35: 35.659169 | BY35: 40.643275 | BZ35: 45.904522 | CA35: 51.463717 | CB35: 57.34252 | CC35: 63.379846 | CD35: 69.456899 | CE35: 75.638675 | CF35: 82.679744 | CG35: 89.531683 | CH35: 96.346626 | CI35: 103.21127 | CJ35: 110.17595 | CK35: 117.27101 | CL35: 124.5159 | CM35: 131.8106 | CN35: 139.12261 | CO35: 146.55098 | CP35: 154.11719 | CQ35: 161.83706 | CR35: 169.72383 | CS35: 177.7919 | CT35: 186.0659 | CU35: 194.64584 | CV35: 203.53661 | CW35: 212.38102 | CX35: 221.05634 | CY35: 229.84955 | CZ35: 238.80273 | DA35: 247.94102 | DB35: 257.28146 | DC35: 266.83733 | DD35: 276.62035 | DE35: 286.64179 | DF35: 296.91287 | DG35: 307.44504 | DH35: 318.24995 | DI35: 329.33952 | DJ35: 340.7259 | DK35: 352.42142 | DL35: 364.43861 | DM35: 376.79019 | DN35: 389.48903 | DO35: 402.54821 | DP35: 415.98096 | DQ35: 429.80073 | DR35: 444.02117 | DS35: 458.65612 | DT35: 473.7197 | DU35: 489.22623 | DV35: 505.1903 | DW35: 521.62679 | DX35: 538.55086 | DY35: 555.97794 | DZ35: 573.9238
A36: Total Energy Use | BO36: from a base run | BR36: EU | BS36: 13.031057 | BT36: 16.381607 | BU36: 20.819666 | BV36: 25.282737 | BW36: 29.786659 | BX36: 34.09851 | BY36: 38.258664 | BZ36: 42.441989 | CA36: 46.638341 | CB36: 50.833532 | CC36: 55.815987 | CD36: 61.737121 | CE36: 67.806543 | CF36: 74.448137 | CG36: 81.00202 | CH36: 87.555632 | CI36: 94.157016 | CJ36: 100.83196 | CK36: 107.59432 | CL36: 114.45193 | CM36: 121.48973 | CN36: 128.74287 | CO36: 136.15265 | CP36: 143.71456 | CQ36: 151.42927 | CR36: 159.30107 | CS36: 167.33941 | CT36: 175.56546 | CU36: 184.09376 | CV36: 192.92972 | CW36: 201.62797 | CX36: 210.03391 | CY36: 218.50665 | CZ36: 227.09957 | DA36: 235.84241 | DB36: 244.75417 | DC36: 253.84881 | DD36: 263.13807 | DE36: 272.63291 | DF36: 282.34409 | DG36: 292.28252 | DH36: 302.45931 | DI36: 312.88578 | DJ36: 323.57347 | DK36: 334.53411 | DL36: 345.77958 | DM36: 357.32191 | DN36: 369.17328 | DO36: 381.34601 | DP36: 393.85256 | DQ36: 406.70554 | DR36: 419.91773 | DS36: 433.50208 | DT36: 447.47173 | DU36: 461.84 | DV36: 476.62045 | DW36: 491.82683 | DX36: 507.47318 | DY36: 523.57373 | DZ36: 540.14304
A37: Ethanol Consumed in Motor Gasoline and E85 | BO37: below | BR37: Japan | BS37: 3.8702838 | BT37: 4.4258582 | BU37: 5.220572 | BV37: 5.8569221 | BW37: 6.2402133 | BX37: 6.7868489 | BY37: 7.444184 | BZ37: 8.0789665 | CA37: 8.6911915 | CB37: 9.281014 | CC37: 10.075102 | CD37: 11.112358 | CE37: 12.171239 | CF37: 13.367853 | CG37: 14.537571 | CH37: 15.702414 | CI37: 16.874745 | CJ37: 18.061572 | CK37: 19.266986 | CL37: 20.493535 | CM37: 21.751474 | CN37: 23.045551 | CO37: 24.37048 | CP37: 25.726708 | CQ37: 27.115243 | CR37: 28.537559 | CS37: 29.99593 | CT37: 31.494184 | CU37: 33.053223 | CV37: 34.673603 | CW37: 36.276448 | CX37: 37.834042 | CY37: 39.409321 | CZ37: 41.011419 | DA37: 42.64575 | DB37: 44.315898 | DC37: 46.024596 | DD37: 47.774212 | DE37: 49.566996 | DF37: 51.405193 | DG37: 53.291085 | DH37: 55.227015 | DI37: 57.215383 | DJ37: 59.258645 | DK37: 61.359311 | DL37: 63.519943 | DM37: 65.743148 | DN37: 68.031583 | DO37: 70.387955 | DP37: 72.815021 | DQ37: 75.315592 | DR37: 77.892535 | DS37: 80.548777 | DT37: 83.287311 | DU37: 86.111195 | DV37: 89.023561 | DW37: 92.027616 | DX37: 95.126647 | DY37: 98.324025 | DZ37: 101.62321
A38: Population (millions) | S38: 296.73387 | W38: =+(S38*X38)^0.5 -> 310.90125 | X38: 325.74504 | Y38: =+(X38*Z38)^0.5 -> 338.43886 | Z38: 351.62733 | AA38: =+(Z38*AB38)^0.5 -> 361.9008 | AB38: 372.47443 | AC38: =+(AB38*AD38)^0.5 -> 380.60319 | AD38: 388.90936 | AE38: =+(AD38*AF38)^0.5 -> 393.72786 | AF38: 398.60606 | BR38: Russia | BS38: 1.6979567 | BT38: 2.2470513 | BU38: 2.7571582 | BV38: 3.2284397 | BW38: 3.7026717 | BX38: 4.1872605 | BY38: 4.6752973 | BZ38: 5.1512782 | CA38: 5.6128117 | CB38: 6.0580681 | CC38: 6.6753423 | CD38: 7.5073274 | CE38: 8.374769 | CF38: 9.3411909 | CG38: 10.314713 | CH38: 11.305598 | CI38: 12.319422 | CJ38: 13.359198 | CK38: 14.426593 | CL38: 15.522627 | CM38: 16.629587 | CN38: 17.740445 | CO38: 18.870106 | CP38: 20.021388 | CQ38: 21.196378 | CR38: 22.396865 | CS38: 23.624752 | CT38: 24.881991 | CU38: 26.182256 | CV38: 27.525803 | CW38: 28.857117 | CX38: 30.156828 | CY38: 31.470019 | CZ38: 32.80374 | DA38: 34.162377 | DB38: 35.548968 | DC38: 36.96589 | DD38: 38.415222 | DE38: 39.898931 | DF38: 41.418958 | DG38: 42.97726 | DH38: 44.575833 | DI38: 46.216708 | DJ38: 47.901962 | DK38: 49.63371 | DL38: 51.414107 | DM38: 53.24535 | DN38: 55.129676 | DO38: 57.069361 | DP38: 59.066729 | DQ38: 61.124146 | DR38: 63.24403 | DS38: 65.428846 | DT38: 67.681118 | DU38: 70.003423 | DV38: 72.398403 | DW38: 74.868761 | DX38: 77.417271 | DY38: 80.046775 | DZ38: 82.760194
A39: US GDP (billion 2000 dollars) | S39: 11294.875 | W39: =+(S39*X39)^0.5 -> 13206.953 | X39: 15442.722 | Y39: =+(X39*Z39)^0.5 -> 17297.906 | Z39: 19375.96 | AA39: =+(Z39*AB39)^0.5 -> 21395.399 | AB39: 23625.312 | AC39: =+(AB39*AD39)^0.5 -> 25722.237 | AD39: 28005.28 | AE39: =+(AD39*AF39)^0.5 -> 30102.148 | AF39: 32356.017 | BR39: Eurasia | BS39: 0.80733505 | BT39: 1.0932665 | BU39: 1.5361 | BV39: 2.0297697 | BW39: 2.5770365 | BX39: 3.1630435 | BY39: 3.7925389 | BZ39: 4.4626872 | CA39: 5.1673754 | CB39: 5.9004756 | CC39: 6.7672778 | CD39: 7.7993289 | CE39: 8.8895722 | CF39: 10.079137 | CG39: 11.298703 | CH39: 12.550266 | CI39: 13.833159 | CJ39: 15.145408 | CK39: 16.484533 | CL39: 17.848032 | CM39: 19.269638 | CN39: 20.763458 | CO39: 22.301131 | CP39: 23.878117 | CQ39: 25.492043 | CR39: 27.142003 | CS39: 28.828423 | CT39: 30.554593 | CU39: 32.334411 | CV39: 34.169017 | CW39: 35.991151 | CX39: 37.776042 | CY39: 39.57743 | CZ39: 41.403483 | DA39: 43.259318 | DB39: 45.148554 | DC39: 47.074126 | DD39: 49.038697 | DE39: 51.044864 | DF39: 53.09525 | DG39: 55.192543 | DH39: 57.339505 | DI39: 59.53897 | DJ39: 61.793842 | DK39: 64.107087 | DL39: 66.481731 | DM39: 68.920854 | DN39: 71.427592 | DO39: 74.005136 | DP39: 76.656731 | DQ39: 79.385683 | DR39: 82.19536 | DS39: 85.089192 | DT39: 88.070682 | DU39: 91.143404 | DV39: 94.311013 | DW39: 97.577245 | DX39: 100.94593 | DY39: 104.42097 | DZ39: 108.0064
A40: Carbon Dioxide Emissions (million metric tons) | S40: =+S4*3.666*1000 -> 5954.3449 | W40: =+W4*3.666*1000 -> 5953.8259 | X40: =+X4*3.666*1000 -> 5953.1772 | Y40: =+Y4*3.666*1000 -> 6256.7018 | Z40: =+Z4*3.666*1000 -> 6575.7016 | AA40: =+AA4*3.666*1000 -> 6796.1314 | AB40: =+AB4*3.666*1000 -> 7023.9504 | AC40: =+(AB40*AD40)^0.5 -> 7187.7965 | AD40: =+AD4*3.666*1000 -> 7355.4647 | AE40: =+AE4*3.666*1000 -> 7459.1947 | AF40: =+AF4*3.666*1000 -> 7564.3875 | BR40: China | BS40: 5.3332327 | BT40: 11.941345 | BU40: 16.891902 | BV40: 22.179187 | BW40: 27.688905 | BX40: 33.263207 | BY40: 39.212408 | BZ40: 45.425278 | CA40: 51.838786 | CB40: 58.365449 | CC40: 66.09085 | CD40: 75.381257 | CE40: 85.280093 | CF40: 95.009126 | CG40: 105.13543 | CH40: 115.56673 | CI40: 126.22741 | CJ40: 137.05603 | CK40: 148.00166 | CL40: 159.02154 | CM40: 170.38872 | CN40: 182.20126 | CO40: 194.19252 | CP40: 206.30276 | CQ40: 218.49315 | CR40: 230.73659 | CS40: 243.01694 | CT40: 255.3398 | CU40: 267.85135 | CV40: 280.55832 | CW40: 292.76057 | CX40: 304.22159 | CY40: 315.52301 | CZ40: 326.7612 | DA40: 337.9787 | DB40: 349.19812 | DC40: 360.43234 | DD40: 371.68926 | DE40: 382.97431 | DF40: 394.2915 | DG40: 405.64401 | DH40: 417.0344 | DI40: 428.4647 | DJ40: 439.93652 | DK40: 451.4511 | DL40: 463.00941 | DM40: 474.61231 | DN40: 486.26079 | DO40: 497.95618 | DP40: 509.70062 | DQ40: 521.49743 | DR40: 533.35175 | DS40: 545.27123 | DT40: 557.26697 | DU40: 569.35453 | DV40: 581.5553 | DW40: 593.89806 | DX40: 606.42086 | DY40: 619.1733 | DZ40: 632.21927
A41: sigma | S41: =+S40/S39 -> 0.52717227 | W41: =+W40/W39 -> 0.45080995 | X41: =+X40/X39 -> 0.38550052 | Y41: =+Y40/Y39 -> 0.36170284 | Z41: =+Z40/Z39 -> 0.33937424 | AA41: =+AA40/AA39 -> 0.31764453 | AB41: =+AB40/AB39 -> 0.29730614 | AC41: =+AC40/AC39 -> 0.27943901 | AD41: =+AD40/AD39 -> 0.26264564 | ... AF41: =+AF40/AF39 -> 0.23378611 | BR41: India | BS41: 2.4408315 | BT41: 4.6013435 | BU41: 7.4063915 | BV41: 10.973549 | BW41: 15.342254 | BX41: 20.183248 | BY41: 25.493036 | BZ41: 31.505996 | CA41: 38.211822 | CB41: 45.591134 | CC41: 53.58295 | CD41: 62.104721 | CE41: 71.077587 | CF41: 80.613315 | CG41: 90.383529 | CH41: 100.34526 | CI41: 110.44847 | CJ41: 120.64206 | CK41: 130.87754 | CL41: 141.11111 | CM41: 152.16337 | CN41: 164.37846 | CO41: 177.08352 | CP41: 190.16794 | CQ41: 203.56524 | CR41: 217.2366 | CS41: 231.16535 | CT41: 245.37135 | CU41: 260.02404 | CV41: 275.12231 | CW41: 290.14146 | CX41: 304.8757 | CY41: 319.71696 | CZ41: 334.71498 | DA41: 349.89788 | DB41: 365.28457 | DC41: 380.89058 | DD41: 396.73075 | DE41: 412.82041 | DF41: 429.17578 | DG41: 445.81393 | DH41: 462.75268 | DI41: 480.01044 | DJ41: 497.606 | DK41: 515.55843 | DL41: 533.88694 | DM41: 552.61082 | DN41: 571.74935 | DO41: 591.3218 | DP41: 611.3474 | DQ41: 631.84528 | DR41: 652.83454 | DS41: 674.33419 | DT41: 696.36317 | DU41: 718.94037 | DV41: 742.08463 | DW41: 765.81474 | DX41: 790.14945 | DY41: 815.10749 | DZ41: 840.70755
W42: =+LN(W41/S41)/5 -> -0.031296307 | X42: =+LN(X41/W41)/5 -> -0.031300665 | Y42: =+LN(Y41/X41)/5 -> -0.012743908 | Z42: =+LN(Z41/Y41)/5 -> -0.012743908 | AA42: =+LN(AA41/Z41)/5 -> -0.013234108 | AB42: =+LN(AB41/AA41)/5 -> -0.013234108 | AC42: =+LN(AC41/AB41)/5 -> -0.012395662 | AD42: =+LN(AD41/AC41)/5 -> -0.012395662 | AE42: =+LN(AE41/AD41)/5 -> -0.011639911 | AF42: =+LN(AF41/AE41)/5 -> -0.011639911 | BR42: Middle East | BS42: 3.4801033 | BT42: 5.7677656 | BU42: 8.7643038 | BV42: 12.397558 | BW42: 16.641388 | BX42: 21.10952 | BY42: 25.915336 | BZ42: 31.356222 | CA42: 37.475779 | CB42: 44.318481 | CC42: 50.783919 | CD42: 56.394237 | CE42: 62.039091 | CF42: 68.217884 | CG42: 74.227313 | CH42: 80.129851 | CI42: 85.955131 | CJ42: 91.715185 | CK42: 97.413323 | CL42: 103.0491 | CM42: 109.19568 | CN42: 116.07165 | CO42: 123.22505 | CP42: 130.59203 | CQ42: 138.13904 | CR42: 145.8505 | CS42: 153.72431 | CT42: 161.77227 | CU42: 170.11278 | CV42: 178.74432 | CW42: 187.35603 | CX42: 195.8342 | CY42: 204.41904 | CZ42: 213.14394 | DA42: 222.02879 | DB42: 231.08753 | DC42: 240.33175 | DD42: 249.77241 | DE42: 259.4206 | DF42: 269.28786 | DG42: 279.3862 | DH42: 289.72812 | DI42: 300.3265 | DJ42: 311.19458 | DK42: 322.3459 | DL42: 333.79425 | DM42: 345.55365 | DN42: 357.63834 | DO42: 370.06279 | DP42: 382.84169 | DQ42: 395.98995 | DR42: 409.52275 | DS42: 423.4555 | DT42: 437.80392 | DU42: 452.58403 | DV42: 467.81214 | DW42: 483.50496 | DX42: 499.6795 | DY42: 516.35321 | DZ42: 533.54393
S43: 911.03129 | BR43: Africa | BS43: 1.3005301 | BT43: 2.4571829 | BU43: 4.35911 | BV43: 7.1359542 | BW43: 10.964085 | BX43: 15.495442 | BY43: 20.637146 | BZ43: 26.865972 | CA43: 34.289619 | CB43: 43.008294 | CC43: 51.652889 | CD43: 59.489067 | CE43: 67.654186 | CF43: 75.989371 | CG43: 84.439787 | CH43: 92.924346 | CI43: 101.3694 | CJ43: 109.71006 | CK43: 117.89086 | CL43: 125.86584 | CM43: 134.37838 | CN43: 143.71357 | CO43: 154.31415 | CP43: 165.36748 | CQ43: 176.73417 | CR43: 188.33458 | CS43: 200.12805 | CT43: 212.13931 | CU43: 224.50289 | CV43: 237.22849 | CW43: 249.86114 | CX43: 262.22179 | CY43: 274.65202 | CZ43: 287.19464 | DA43: 299.87088 | DB43: 312.69433 | DC43: 325.67615 | DD43: 338.8274 | DE43: 352.15991 | DF43: 365.68659 | DG43: 379.42127 | DH43: 393.37857 | DI43: 407.57371 | DJ43: 422.02227 | DK43: 436.74013 | DL43: 451.74326 | DM43: 467.0477 | DN43: 482.66948 | DO43: 498.62458 | DP43: 514.92892 | DQ43: 531.59831 | DR43: 548.6485 | DS43: 566.09513 | DT43: 583.95376 | DU43: 602.23987 | DV43: 620.96887 | DW43: 640.15614 | DX43: 659.81696 | DY43: 679.96661 | DZ43: 700.62033
A44: Ratio RICE/EIA | BR44: Latin America | BS44: 4.5584763 | BT44: 7.1177565 | BU44: 10.35634 | BV44: 14.113438 | BW44: 18.230217 | BX44: 22.467409 | BY44: 26.953884 | BZ44: 31.807088 | CA44: 37.009469 | CB44: 42.54312 | CC44: 48.447813 | CD44: 54.673729 | CE44: 61.062323 | CF44: 68.042696 | CG44: 74.982836 | CH44: 81.924283 | CI44: 88.881533 | CJ44: 95.855117 | CK44: 102.83912 | CL44: 109.82546 | CM44: 117.35174 | CN44: 125.63512 | CO44: 134.25189 | CP44: 143.14154 | CQ44: 152.27187 | CR44: 161.62801 | CS44: 171.20803 | CT44: 181.0194 | CU44: 191.1686 | CV44: 201.65533 | CW44: 212.03322 | CX44: 222.14012 | CY44: 232.33059 | CZ44: 242.65787 | DA44: 253.15455 | DB44: 263.84295 | DC44: 274.74048 | DD44: 285.8625 | DE44: 297.22361 | DF44: 308.83841 | DG44: 320.7217 | DH44: 332.88861 | DI44: 345.35462 | DJ44: 358.13551 | DK44: 371.24738 | DL44: 384.70661 | DM44: 398.52984 | DN44: 412.73397 | DO44: 427.33616 | DP44: 442.35387 | DQ44: 457.8048 | DR44: 473.70698 | DS44: 490.07875 | DT44: 506.93881 | DU44: 524.30619 | DV44: 542.20033 | DW44: 560.64108 | DX44: 579.64873 | DY44: 599.24402 | DZ44: 619.4482
A45: Population (millions) | S45: =+S38/S29 -> 0.99054606 | W45: =+W38/W29 -> 0.99848615 | X45: =+X38/X29 -> 0.9970852 | Y45: =+Y38/Y29 -> 0.98799044 | Z45: =+Z38/Z29 -> 0.98050395 | AA45: =+AA38/AA29 -> 0.96591949 | BR45: OHI | BS45: 3.8420498 | BT45: 5.0944274 | BU45: 6.5776892 | BV45: 8.061777 | BW45: 9.4774009 | BX45: 10.760397 | BY45: 11.939603 | BZ45: 13.110209 | CA45: 14.271239 | CB45: 15.419325 | CC45: 16.815771 | CD45: 18.507631 | CE45: 20.241053 | CF45: 22.128916 | CG45: 23.987218 | CH45: 25.842406 | CI45: 27.709247 | CJ45: 29.59583 | CK45: 31.506636 | CL45: 33.444275 | CM45: 35.420498 | CN45: 37.440473 | CO45: 39.497488 | CP45: 41.591677 | CQ45: 43.723918 | CR45: 45.895697 | CS45: 48.109709 | CT45: 50.371672 | CU45: 52.714915 | CV45: 55.140792 | CW45: 57.527082 | CX45: 59.831986 | CY45: 62.154433 | CZ45: 64.509221 | DA45: 66.904339 | DB45: 69.3448 | DC45: 71.834216 | DD45: 74.375581 | DE45: 76.971656 | DF45: 79.625149 | DG45: 82.338789 | DH45: 85.115346 | DI45: 87.957641 | DJ45: 90.868535 | DK45: 93.850926 | DL45: 96.90774 | DM45: 100.04193 | DN45: 103.25646 | DO45: 106.55434 | DP45: 109.93857 | DQ45: 113.41218 | DR45: 116.97825 | DS45: 120.63985 | DT45: 124.40008 | DU45: 128.2621 | DV45: 132.22906 | DW45: 136.30416 | DX45: 140.49066 | DY45: 144.7918 | DZ45: 149.21092
A46: US GDP (billion 2000 dollars) | S46: =+S39/S30 -> 1 | W46: =+W39/W30 -> 1.1386206 | X46: =+X39/X30 -> 1.1480922 | Y46: =+Y39/Y30 -> 1.1233559 | Z46: =+Z39/Z30 -> 1.1041502 | AA46: =+AA39/AA30 -> 1.0764965 | BR46: Other non-OECD Asia | BS46: 2.6191887 | BT46: 4.1797076 | BU46: 6.9278985 | BV46: 10.642454 | BW46: 15.379236 | BX46: 20.829064 | BY46: 27.002269 | BZ46: 34.219378 | CA46: 42.521892 | CB46: 51.937365 | CC46: 61.919959 | CD46: 72.191115 | CE46: 83.214107 | CF46: 94.282482 | CG46: 105.85962 | CH46: 117.80968 | CI46: 130.01603 | CJ46: 142.37713 | CK46: 154.8039 | CL46: 167.21803 | CM46: 180.51354 | CN46: 195.05357 | CO46: 210.05586 | CP46: 225.3652 | CQ46: 240.87551 | CR46: 256.50943 | CS46: 272.21188 | CT46: 287.94593 | CU46: 303.9164 | CV46: 320.0875 | CW46: 335.84037 | CX46: 350.93433 | CY46: 365.81028 | CZ46: 380.5165 | DA46: 395.06874 | DB46: 409.46947 | DC46: 423.71437 | DD46: 437.79543 | DE46: 451.70217 | DF46: 465.42193 | DG46: 478.93991 | DH46: 492.23887 | DI46: 505.29891 | DJ46: 518.09736 | DK46: 530.60863 | DL46: 542.80443 | DM46: 554.65412 | DN46: 566.12554 | DO46: 577.18639 | DP46: 587.80653 | DQ46: 597.96133 | DR46: 607.63683 | DS46: 616.83713 | DT46: 625.59479 | DU46: 633.98519 | DV46: 642.14592 | DW46: 650.30213 | DX46: 658.79921 | DY46: 668.14365 | DZ46: 679.05307
A47: Carbon Dioxide Emissions (million metric tons) | S47: =+S40/S31 -> 1.0080526 | W47: =+W40/W31 -> 1.0361793 | X47: =+X40/X31 -> 1.0211825 | Y47: =+Y40/Y31 -> 1.0596328 | Z47: =+Z40/Z31 -> 1.0874184 | AA47: =+AA40/AA31 -> 1.0948891 | BR47: World | BS47: 55.378946 | BT47: 81.281398 | BU47: 112.31861 | BV47: 147.49821 | BW47: 186.68345 | BX47: 228.00312 | BY47: 271.96764 | BZ47: 320.32959 | CA47: 373.19204 | CB47: 430.59878 | CC47: 492.00771 | CD47: 556.35479 | CE47: 623.44924 | CF47: 694.19985 | CG47: 765.70043 | CH47: 838.00309 | CI47: 911.00282 | CJ47: 984.52551 | CK47: 1058.3765 | CL47: 1132.3674 | CM47: 1210.363 | CN47: 1293.9091 | CO47: 1380.8658 | CP47: 1469.9866 | CQ47: 1560.8729 | CR47: 1653.2927 | CS47: 1747.1447 | CT47: 1842.5219 | CU47: 1940.6005 | CV47: 2041.3718 | CW47: 2140.6536 | CX47: 2236.9169 | CY47: 2333.4193 | CZ47: 2430.6193 | DA47: 2528.7548 | DB47: 2627.9708 | DC47: 2728.3706 | DD47: 2830.0399 | DE47: 2933.0582 | DF47: 3037.5036 | DG47: 3143.4543 | DH47: 3250.9882 | DI47: 3360.1829 | DJ47: 3471.1146 | DK47: 3583.8581 | DL47: 3698.4866 | DM47: 3815.0718 | DN47: 3933.6851 | DO47: 4054.3989 | DP47: 4177.2896 | DQ47: 4302.441 | DR47: 4429.9504 | DS47: 4559.9368 | DT47: 4692.552 | DU47: 4827.9965 | DV47: 4966.54 | DW47: 5108.5485 | DX47: 5254.5192 | DY47: 5405.1235 | DZ47: 5561.2599
A48: sigma | S48: =+S41/S32 -> 1.0080526 | W48: =+W41/W32 -> 0.91003037 | X48: =+X41/X32 -> 0.88946031 | Y48: =+Y41/Y32 -> 0.94327434 | Z48: =+Z41/Z32 -> 0.98484641 | AA48: =+AA41/AA32 -> 1.0170856 | BO48: GDP (from program) | BR48: GDP
BR49: US | BS49: =+US!B61 -> 12.3979 | BT49: =+US!C61 -> 15.973315 | BU49: =+US!D61 -> 20.699509 | BV49: =+US!E61 -> 25.594789 | BW49: =+US!F61 -> 30.652531 | BX49: =+US!G61 -> 35.659639 | BY49: =+US!H61 -> 40.645458 | BZ49: =+US!I61 -> 45.908382 | ... DZ49: =+US!BI61 -> 574.17705
A50: US calculations | BR50: EU | BS50: =+EU!B61 -> 13.031057 | BT50: =+EU!C61 -> 16.380715 | BU50: =+EU!D61 -> 20.817756 | BV50: =+EU!E61 -> 25.281421 | BW50: =+EU!F61 -> 29.786472 | BX50: =+EU!G61 -> 34.10007 | BY50: =+EU!H61 -> 38.26237 | BZ50: =+EU!I61 -> 42.447804 | ... DZ50: =+EU!BI61 -> 540.46274
A51: Posts 2050: | BR51: Japan | BS51: =+Japan!B61 -> 3.8702838 | BT51: =+Japan!C61 -> 4.4256249 | BU51: =+Japan!D61 -> 5.2201233 | BV51: =+Japan!E61 -> 5.856621 | BW51: =+Japan!F61 -> 6.2401633 | BX51: =+Japan!G61 -> 6.7870776 | BY51: =+Japan!H61 -> 7.4447808 | BZ51: =+Japan!I61 -> 8.0799235 | ... DZ51: =+Japan!BI61 -> 101.64023
A52: Rate per 5 years | B52: 0.2 | BR52: Russia | BS52: =+Russia!B61 -> 1.6979567 | BT52: =+Russia!C61 -> 2.2469589 | BU52: =+Russia!D61 -> 2.7568682 | BV52: =+Russia!E61 -> 3.2281653 | BW52: =+Russia!F61 -> 3.7024679 | BX52: =+Russia!G61 -> 4.1871699 | BY52: =+Russia!H61 -> 4.6753718 | BZ52: =+Russia!I61 -> 5.1515268 | ... DZ52: =+Russia!BI61 -> 82.765476
A53: Maximum reduction | B53: 0.95 | BR53: Eurasia | BS53: =+Eurasia!B61 -> 0.80733505 | BT53: =+Eurasia!C61 -> 1.0932156 | BU53: =+Eurasia!D61 -> 1.535946 | BV53: =+Eurasia!E61 -> 2.0296142 | BW53: =+Eurasia!F61 -> 2.5769289 | BX53: =+Eurasia!G61 -> 3.1630366 | BY53: =+Eurasia!H61 -> 3.7926815 | BZ53: =+Eurasia!I61 -> 4.4630012 | ... DZ53: =+Eurasia!BI61 -> 108.01191
A54: Increase of cap rate post 2050 | B54: 0.1 | BR54: China | BS54: =+China!B61 -> 5.3332327 | BT54: =+China!C61 -> 11.94051 | BU54: =+China!D61 -> 16.89017 | BV54: =+China!E61 -> 22.177631 | BW54: =+China!F61 -> 27.688503 | BX54: =+China!G61 -> 33.265086 | BY54: =+China!H61 -> 39.217014 | BZ54: =+China!I61 -> 45.433179 | ... DZ54: =+China!BI61 -> 633.99451
A55: Share of CO2 emissions that are covered | X55: 0.7 | Y55: 0.8 | Z55: 0.85 | AA55: 0.85 | AB55: 0.85 | AC55: 0.85 | AD55: 0.85 | AE55: 0.85 | AF55: =+AE55+$B$54*(1-AE55) -> 0.865 | AG55: =+AF55+$B$54*(1-AF55) -> 0.8785 | AH55: =+AG55+$B$54*(1-AG55) -> 0.89065 | AI55: =+AH55+$B$54*(1-AH55) -> 0.901585 | AJ55: =+AI55+$B$54*(1-AI55) -> 0.9114265 | AK55: =+AJ55+$B$54*(1-AJ55) -> 0.92028385 | AL55: =+AK55+$B$54*(1-AK55) -> 0.92825546 | AM55: =+AL55+$B$54*(1-AL55) -> 0.93542992 | ... BI55: =+BH55+$B$54*(1-BH55) -> 0.99364133 | BR55: India | BS55: =+India!B61 -> 2.4408315 | BT55: =+India!C61 -> 4.6005455 | BU55: =+India!D61 -> 7.4062545 | BV55: =+India!E61 -> 10.973937 | BW55: =+India!F61 -> 15.343782 | BX55: =+India!G61 -> 20.186342 | BY55: =+India!H61 -> 25.498039 | BZ55: =+India!I61 -> 31.513112 | ... DZ55: =+India!BI61 -> 841.45046
A56: Covered CO2 emissions | S56: =+S4*$Y$55 -> 1.2993661 | T56: =+T4*$Y$55 -> 1.2993377 | U56: =+U4*$Y$55 -> 1.2993094 | X56: =+X4*X55 -> 1.1367223 | Y56: =+Y4*Y55 -> 1.3653468 | Z56: =+Z4*Z55 -> 1.5246444 | AA56: =+AA4*AA55 -> 1.5757533 | AB56: =+AB4*AB55 -> 1.6285755 | AC56: =+AC4*AC55 -> 1.6665649 | AD56: =+AD4*AD55 -> 1.7054405 | AE56: =+AE4*AE55 -> 1.7294914 | ... BI56: =+BI4*BI55 -> 2.5657483 | BR56: Middle East | BS56: =+MidEast!B61 -> 3.4801033 | BT56: =+MidEast!C61 -> 5.7670229 | BU56: =+MidEast!D61 -> 8.763857 | BV56: =+MidEast!E61 -> 12.397563 | BW56: =+MidEast!F61 -> 16.642289 | BX56: =+MidEast!G61 -> 21.11171 | BY56: =+MidEast!H61 -> 25.919157 | BZ56: =+MidEast!I61 -> 31.361885 | ... DZ56: =+MidEast!BI61 -> 533.69417
A57: Capped emissions | X57: =+X191 -> 0.0825 | Y57: =+X192 -> 0.17 | Z57: =+X193 -> 0.295 | AA57: =+X194 -> 0.42 | AB57: =+X195 -> 0.5225 | AC57: =+X196 -> 0.625 | AD57: =+X197 -> 0.7275 | AE57: =+X198 -> 0.83 | AF57: =+AE57+$B$52*($B$53-AE57) -> 0.854 | AG57: =+AF57+$B$52*($B$53-AF57) -> 0.8732 | AH57: =+AG57+$B$52*($B$53-AG57) -> 0.88856 | AI57: =+AH57+$B$52*($B$53-AH57) -> 0.900848 | AJ57: =+AI57+$B$52*($B$53-AI57) -> 0.9106784 | AK57: =+AJ57+$B$52*($B$53-AJ57) -> 0.91854272 | AL57: =+AK57+$B$52*($B$53-AK57) -> 0.92483418 | AM57: =+AL57+$B$52*($B$53-AL57) -> 0.92986734 | ... AO57: =+AN57+$B$52*($B$53-AN57) -> 0.9371151 | AP57: =+AO57+0.1*(1-AO57) -> 0.94340359 | AQ57: =+AP57+0.1*(1-AP57) -> 0.94906323 | AR57: =+AQ57+0.1*(1-AQ57) -> 0.95415691 | AS57: =+AR57+0.1*(1-AR57) -> 0.95874122 | AT57: =+AS57+0.1*(1-AS57) -> 0.96286709 | AU57: =+AT57+0.1*(1-AT57) -> 0.96658038 | AV57: =+AU57+0.1*(1-AU57) -> 0.96992235 | AW57: =+AV57+0.1*(1-AV57) -> 0.97293011 | ... BI57: =+BH57+0.1*(1-BH57) -> 0.99235466 | BR57: Africa | BS57: =+Africa!B61 -> 1.3005301 | BT57: =+Africa!C61 -> 2.4567853 | BU57: =+Africa!D61 -> 4.3589948 | BV57: =+Africa!E61 -> 7.1362204 | BW57: =+Africa!F61 -> 10.965295 | BX57: =+Africa!G61 -> 15.498159 | BY57: =+Africa!H61 -> 20.641995 | BZ57: =+Africa!I61 -> 26.87349 | ... DZ57: =+Africa!BI61 -> 701.38181
A58: CO2 cap (C) | S58: =+S56*(1-S57) -> 1.2993661 | T58: =+T56*(1-T57) -> 1.2993377 | U58: =+U56*(1-U57) -> 1.2993094 | V58: =+V56*(1-V57) -> 0 | W58: =+W56*(1-W57) -> 0 | X58: =+X56*(1-X57) -> 1.0429427 | Y58: =+Y56*(1-Y57) -> 1.1332379 | Z58: =+Z56*(1-Z57) -> 1.0748743 | ... BI58: =+BI56*(1-BI57) -> 0.019616008 | BR58: Latin America | BS58: =+LatAm!B61 -> 4.5584763 | BT58: =+LatAm!C61 -> 7.1172976 | BU58: =+LatAm!D61 -> 10.355426 | BV58: =+LatAm!E61 -> 14.112652 | BW58: =+LatAm!F61 -> 18.229912 | BX58: =+LatAm!G61 -> 22.467867 | BY58: =+LatAm!H61 -> 26.955504 | BZ58: =+LatAm!I61 -> 31.810045 | ... DZ58: =+LatAm!BI61 -> 619.56091
A59: CO2 cap (CO2) | S59: =+S58*3.666 -> 4.763476 | T59: =+T58*3.666 -> 4.7633722 | U59: =+U58*3.666 -> 4.7632683 | V59: =+V58*3.666 -> 0 | W59: =+W58*3.666 -> 0 | X59: =+X58*3.666 -> 3.8234281 | Y59: =+Y58*3.666 -> 4.15445 | Z59: =+Z58*3.666 -> 3.9404892 | ... BI59: =+BI58*3.666 -> 0.071912285 | BR59: OHI | BS59: =+OHI!B61 -> 3.8420498 | BT59: =+OHI!C61 -> 5.09415 | BU59: =+OHI!D61 -> 6.5770787 | BV59: =+OHI!E61 -> 8.0613059 | BW59: =+OHI!F61 -> 9.4773451 | BX59: =+OHI!G61 -> 10.76085 | BY59: =+OHI!H61 -> 11.940775 | BZ59: =+OHI!I61 -> 13.112103 | ... DZ59: =+OHI!BI61 -> 149.33456
A60: TOTAL CO2 emissions | BR60: Other non-OECD Asia | BS60: =+OthAsia!B61 -> 2.6191887 | BT60: =+OthAsia!C61 -> 4.1792624 | BU60: =+OthAsia!D61 -> 6.9275005 | BV60: =+OthAsia!E61 -> 10.642308 | BW60: =+OthAsia!F61 -> 15.379887 | BX60: =+OthAsia!G61 -> 20.830978 | BY60: =+OthAsia!H61 -> 27.006107 | BZ60: =+OthAsia!I61 -> 34.225516 | ... DZ60: =+OthAsia!BI61 -> 681.85974
A61: Tonnes C | S61: =+S58+(1-$Y$55)*S4 -> 1.6242076 | T61: =+T58+(1-$Y$55)*T4 -> 1.6241722 | U61: =+U58+(1-$Y$55)*U4 -> 1.6241368 | V61: =+V58+(1-W55)*V4 -> 1.6241014 | W61: =+W58+(1-X55)*W4 -> 0.4872198 | X61: =+X58+(1-Y55)*Y4 -> 1.3842794 | Y61: =+Y58+(1-Z55)*Z4 -> 1.4022927 | Z61: =+Z58+(1-AA55)*AA4 -> 1.3529484 | AA61: =+AA58+(1-AA55)*AA4 -> 1.192011 | AB61: =+AB58+(1-AB55)*AB4 -> 1.0650405 | AC61: =+AC58+(1-AC55)*AC4 -> 0.91906155 | AD61: =+AD58+(1-AD55)*AD4 -> 0.76569264 | AE61: =+AE58+(1-AE55)*AE4 -> 0.5992179 | AF61: =+AF58+(1-AF55)*AF4 -> 0.53914316 | AG61: =+AG58+(1-AG55)*AG4 -> 0.48474908 | AH61: =+AH58+(1-AH55)*AH4 -> 0.4379853 | ... BI61: =+BI58+(1-BI55)*BI4 -> 0.036035169 | BJ61: =+BJ58+(1-$Y$55)*BJ4 -> 0.51946418 | BK61: =+BK58+(1-$Y$55)*BK4 -> 0.52227235 | BR61: World | BS61: =SUM(BS49:BS60) -> 55.378946 | BT61: =SUM(BT49:BT60) -> 81.275403 | BU61: =SUM(BU49:BU60) -> 112.30948 | BV61: =SUM(BV49:BV60) -> 147.49223 | BW61: =SUM(BW49:BW60) -> 186.68558 | BX61: =SUM(BX49:BX60) -> 228.01799 | BY61: =SUM(BY49:BY60) -> 271.99925 | BZ61: =SUM(BZ49:BZ60) -> 320.37997 | ... DZ61: =SUM(DZ49:DZ60) -> 5568.3336
A62: Tonnes CO2 | S62: =+S61*3.666 -> 5.9543449 | T62: =+T61*3.666 -> 5.9542152 | U62: =+U61*3.666 -> 5.9540854 | V62: =+V61*3.666 -> 5.9539557 | W62: =+W61*3.666 -> 1.7861478 | X62: =+X61*3.666 -> 5.0747684 | Y62: =+Y61*3.666 -> 5.1408052 | Z62: =+Z61*3.666 -> 4.9599089 | ... BK62: =+BK61*3.666 -> 1.9146504
Y63: =+Y61/R4 -> 0.84367037
A64: EU calculations (follows EU commitment until gets to US reduction rate)
A65: Reduction from 1990 (commitment, then parallel to US emissions) | W65: 0.07 | X65: 0.12 | Y65: 0.2 | Z65: =+Y65 -> 0.2 | AA65: =+Z65 -> 0.2
A66: Total emissions | W66: =+$C$5*(1-W65) -> 1.0537535 | X66: =+$C$5*(1-X65) -> 0.99710011 | Y66: =+$C$5*(1-Y65) -> 0.90645465 | Z66: =+$C$5*(1-Z65) -> 0.90645465 | AA66: =+$C$5*(1-AA65) -> 0.90645465 | AB66: =+AA66*(AB61/AA61) -> 0.80990097 | AC66: =+AB66*(AC61/AB61) -> 0.69889253 | AD66: =+AC66*(AD61/AC61) -> 0.58226444 | AE66: =+AD66*(AE61/AD61) -> 0.45567015 | AF66: =+AE66*(AF61/AE61) -> 0.40998682 | AG66: =+AF66*(AG61/AF61) -> 0.36862331 | AH66: =+AG66*(AH61/AG61) -> 0.33306219 | AI66: =+AH66*(AI61/AH61) -> 0.30244162 | ... BK66: =+BJ66*(BK61/BJ61) -> 0.39715756
A67: Reduction from baseline | W67: =1-W66/W5 -> 0.064891572 | X67: =1-X66/X5 -> -0.0029433809 | Y67: =1-Y66/Y5 -> 0.1357844 | Z67: =1-Z66/Z5 -> 0.18085559 | AA67: =1-AA66/AA5 -> 0.20996655 | AB67: =1-AB66/AB5 -> 0.31920505 | AC67: =1-AC66/AC5 -> 0.42752969 | AD67: =1-AD66/AD5 -> 0.53524828 | ... BK67: =1-BK66/BK5 -> 0.78231274
A69: If participation
A70: US | S70: =+IF(S$3<$W160,0,1) -> 0 | T70: =+IF(T$3<$W160,0,1) -> 0 | U70: =+IF(U$3<$W160,0,1) -> 0 | W70: =+IF(W$3<$W160,0,1) -> 0 | X70: =+IF(X$3<$W160,0,1) -> 1 | Y70: =+IF(Y$3<$W160,0,1) -> 1 | Z70: =+IF(Z$3<$W160,0,1) -> 1 | AA70: =+IF(AA$3<$W160,0,1) -> 1 | AB70: =+IF(AB$3<$W160,0,1) -> 1 | AC70: =+IF(AC$3<$W160,0,1) -> 1 | AD70: =+IF(AD$3<$W160,0,1) -> 1 | ... BL70: =+IF(BL$3<$W160,0,1) -> 1
A71: EU | S71: =+IF(S$3<$W161,0,1) -> 1 | T71: =+IF(T$3<$W161,0,1) -> 1 | U71: =+IF(U$3<$W161,0,1) -> 1 | W71: =+IF(W$3<$W161,0,1) -> 1 | X71: =+IF(X$3<$W161,0,1) -> 1 | Y71: =+IF(Y$3<$W161,0,1) -> 1 | Z71: =+IF(Z$3<$W161,0,1) -> 1 | AA71: =+IF(AA$3<$W161,0,1) -> 1 | AB71: =+IF(AB$3<$W161,0,1) -> 1 | AC71: =+IF(AC$3<$W161,0,1) -> 1 | AD71: =+IF(AD$3<$W161,0,1) -> 1 | ... BL71: =+IF(BL$3<$W161,0,1) -> 1
A72: Japan | S72: =+IF(S$3<$W162,0,1) -> 1 | T72: =+IF(T$3<$W162,0,1) -> 1 | U72: =+IF(U$3<$W162,0,1) -> 1 | W72: =+IF(W$3<$W162,0,1) -> 1 | X72: =+IF(X$3<$W162,0,1) -> 1 | Y72: =+IF(Y$3<$W162,0,1) -> 1 | Z72: =+IF(Z$3<$W162,0,1) -> 1 | AA72: =+IF(AA$3<$W162,0,1) -> 1 | AB72: =+IF(AB$3<$W162,0,1) -> 1 | AC72: =+IF(AC$3<$W162,0,1) -> 1 | AD72: =+IF(AD$3<$W162,0,1) -> 1 | ... BL72: =+IF(BL$3<$W162,0,1) -> 1
A73: Russia | S73: =+IF(S$3<$W163,0,1) -> 1 | T73: =+IF(T$3<$W163,0,1) -> 1 | U73: =+IF(U$3<$W163,0,1) -> 1 | W73: =+IF(W$3<$W163,0,1) -> 1 | X73: =+IF(X$3<$W163,0,1) -> 1 | Y73: =+IF(Y$3<$W163,0,1) -> 1 | Z73: =+IF(Z$3<$W163,0,1) -> 1 | AA73: =+IF(AA$3<$W163,0,1) -> 1 | AB73: =+IF(AB$3<$W163,0,1) -> 1 | AC73: =+IF(AC$3<$W163,0,1) -> 1 | AD73: =+IF(AD$3<$W163,0,1) -> 1 | ... BL73: =+IF(BL$3<$W163,0,1) -> 1
A74: Eurasia | S74: =+IF(S$3<$W164,0,1) -> 0 | T74: =+IF(T$3<$W164,0,1) -> 0 | U74: =+IF(U$3<$W164,0,1) -> 0 | W74: =+IF(W$3<$W164,0,1) -> 0 | X74: =+IF(X$3<$W164,0,1) -> 0 | Y74: =+IF(Y$3<$W164,0,1) -> 1 | Z74: =+IF(Z$3<$W164,0,1) -> 1 | AA74: =+IF(AA$3<$W164,0,1) -> 1 | AB74: =+IF(AB$3<$W164,0,1) -> 1 | AC74: =+IF(AC$3<$W164,0,1) -> 1 | AD74: =+IF(AD$3<$W164,0,1) -> 1 | ... BL74: =+IF(BL$3<$W164,0,1) -> 1
A75: China | S75: =+IF(S$3<$W165,0,1) -> 0 | T75: =+IF(T$3<$W165,0,1) -> 0 | U75: =+IF(U$3<$W165,0,1) -> 0 | W75: =+IF(W$3<$W165,0,1) -> 0 | X75: =+IF(X$3<$W165,0,1) -> 0 | Y75: =+IF(Y$3<$W165,0,1) -> 0 | Z75: =+IF(Z$3<$W165,0,1) -> 0 | AA75: =+IF(AA$3<$W165,0,1) -> 1 | AB75: =+IF(AB$3<$W165,0,1) -> 1 | AC75: =+IF(AC$3<$W165,0,1) -> 1 | AD75: =+IF(AD$3<$W165,0,1) -> 1 | ... BL75: =+IF(BL$3<$W165,0,1) -> 1
A76: India | S76: =+IF(S$3<$W166,0,1) -> 0 | T76: =+IF(T$3<$W166,0,1) -> 0 | U76: =+IF(U$3<$W166,0,1) -> 0 | W76: =+IF(W$3<$W166,0,1) -> 0 | X76: =+IF(X$3<$W166,0,1) -> 0 | Y76: =+IF(Y$3<$W166,0,1) -> 0 | Z76: =+IF(Z$3<$W166,0,1) -> 0 | AA76: =+IF(AA$3<$W166,0,1) -> 0 | AB76: =+IF(AB$3<$W166,0,1) -> 0 | AC76: =+IF(AC$3<$W166,0,1) -> 1 | AD76: =+IF(AD$3<$W166,0,1) -> 1 | ... BL76: =+IF(BL$3<$W166,0,1) -> 1
A77: Middle East | S77: =+IF(S$3<$W167,0,1) -> 0 | T77: =+IF(T$3<$W167,0,1) -> 0 | U77: =+IF(U$3<$W167,0,1) -> 0 | W77: =+IF(W$3<$W167,0,1) -> 0 | X77: =+IF(X$3<$W167,0,1) -> 0 | Y77: =+IF(Y$3<$W167,0,1) -> 0 | Z77: =+IF(Z$3<$W167,0,1) -> 0 | AA77: =+IF(AA$3<$W167,0,1) -> 0 | AB77: =+IF(AB$3<$W167,0,1) -> 0 | AC77: =+IF(AC$3<$W167,0,1) -> 0 | AD77: =+IF(AD$3<$W167,0,1) -> 0 | ... BL77: =+IF(BL$3<$W167,0,1) -> 1
A78: Africa | S78: =+IF(S$3<$W168,0,1) -> 0 | T78: =+IF(T$3<$W168,0,1) -> 0 | U78: =+IF(U$3<$W168,0,1) -> 0 | W78: =+IF(W$3<$W168,0,1) -> 0 | X78: =+IF(X$3<$W168,0,1) -> 0 | Y78: =+IF(Y$3<$W168,0,1) -> 0 | Z78: =+IF(Z$3<$W168,0,1) -> 0 | AA78: =+IF(AA$3<$W168,0,1) -> 0 | AB78: =+IF(AB$3<$W168,0,1) -> 0 | AC78: =+IF(AC$3<$W168,0,1) -> 0 | AD78: =+IF(AD$3<$W168,0,1) -> 0 | ... BL78: =+IF(BL$3<$W168,0,1) -> 1
A79: Latin America | S79: =+IF(S$3<$W169,0,1) -> 0 | T79: =+IF(T$3<$W169,0,1) -> 0 | U79: =+IF(U$3<$W169,0,1) -> 0 | W79: =+IF(W$3<$W169,0,1) -> 0 | X79: =+IF(X$3<$W169,0,1) -> 0 | Y79: =+IF(Y$3<$W169,0,1) -> 0 | Z79: =+IF(Z$3<$W169,0,1) -> 0 | AA79: =+IF(AA$3<$W169,0,1) -> 1 | AB79: =+IF(AB$3<$W169,0,1) -> 1 | AC79: =+IF(AC$3<$W169,0,1) -> 1 | AD79: =+IF(AD$3<$W169,0,1) -> 1 | ... BL79: =+IF(BL$3<$W169,0,1) -> 1
A80: OHI | S80: =+IF(S$3<$W170,0,1) -> 0 | T80: =+IF(T$3<$W170,0,1) -> 0 | U80: =+IF(U$3<$W170,0,1) -> 0 | W80: =+IF(W$3<$W170,0,1) -> 0 | X80: =+IF(X$3<$W170,0,1) -> 1 | Y80: =+IF(Y$3<$W170,0,1) -> 1 | Z80: =+IF(Z$3<$W170,0,1) -> 1 | AA80: =+IF(AA$3<$W170,0,1) -> 1 | AB80: =+IF(AB$3<$W170,0,1) -> 1 | AC80: =+IF(AC$3<$W170,0,1) -> 1 | AD80: =+IF(AD$3<$W170,0,1) -> 1 | ... BL80: =+IF(BL$3<$W170,0,1) -> 1
A81: Other non-OECD Asia | S81: =+IF(S$3<$W171,0,1) -> 0 | T81: =+IF(T$3<$W171,0,1) -> 0 | U81: =+IF(U$3<$W171,0,1) -> 0 | W81: =+IF(W$3<$W171,0,1) -> 0 | X81: =+IF(X$3<$W171,0,1) -> 0 | Y81: =+IF(Y$3<$W171,0,1) -> 0 | Z81: =+IF(Z$3<$W171,0,1) -> 0 | AA81: =+IF(AA$3<$W171,0,1) -> 0 | AB81: =+IF(AB$3<$W171,0,1) -> 0 | AC81: =+IF(AC$3<$W171,0,1) -> 1 | AD81: =+IF(AD$3<$W171,0,1) -> 1 | ... BL81: =+IF(BL$3<$W171,0,1) -> 1
A82: World
A83: Increase in emissions rate post-2100 per group
A84: Reduction rate
A85: per five years | B85: 0.05
A86: maximum | B86: 0.95
A87: Emissions reduction rate | M87: from 1990
A88: US | C88: from baseline | S88: =1-S61/S4 -> 0 | T88: =1-T61/T4 -> 0 | U88: =1-U61/U4 -> 0 | W88: =+IF(W102<90,1-W102/W4,0) -> 0 | X88: =+IF(X102<90,1-X102/X4,0) -> 0.14755294 | Y88: =+IF(Y102<90,1-Y102/Y4,0) -> 0.1783522 | Z88: =+IF(Z102<90,1-Z102/Z4,0) -> 0.24572172 | AA88: =+IF(AA102<90,1-AA102/AA4,0) -> 0.357 | AB88: =+IF(AB102<90,1-AB102/AB4,0) -> 0.444125 | AC88: =+IF(AC102<90,1-AC102/AC4,0) -> 0.53125 | AD88: =+IF(AD102<90,1-AD102/AD4,0) -> 0.618375 | ... AO88: =+IF(AO102<90,1-AO102/AO4,0) -> 0.88810232 | AP88: =+AO88+($B$86-AO88)*$B$85 -> 0.89119721 | AQ88: =+AP88+($B$86-AP88)*$B$85 -> 0.89413735 | AR88: =+AQ88+($B$86-AQ88)*$B$85 -> 0.89693048 | AS88: =+AR88+($B$86-AR88)*$B$85 -> 0.89958396 | AT88: =+AS88+($B$86-AS88)*$B$85 -> 0.90210476 | AU88: =+AT88+($B$86-AT88)*$B$85 -> 0.90449952 | AV88: =+AU88+($B$86-AU88)*$B$85 -> 0.90677454 | AW88: =+AV88+($B$86-AV88)*$B$85 -> 0.90893582 | ... CL88: =+CK88+($B$86-CK88)*$B$85 -> 0.94498662
A89: EU | T89: =+S89 -> 0 | U89: =+T89 -> 0 | W89: =+IF(W103<90,1-W103/W5,0) -> 0.064891572 | X89: =+IF(X103<90,1-X103/X5,0) -> -0.0599288 | Y89: =+IF(Y103<90,1-Y103/Y5,0) -> 0.1357844 | Z89: =+IF(Z103<90,1-Z103/Z5,0) -> 0.18085559 | AA89: =+IF(AA103<90,1-AA103/AA5,0) -> 0.20996655 | AB89: =+IF(AB103<90,1-AB103/AB5,0) -> 0.31920505 | AC89: =+IF(AC103<90,1-AC103/AC5,0) -> 0.42752969 | AD89: =+IF(AD103<90,1-AD103/AD5,0) -> 0.53524828 | ... AO89: =+IF(AO103<90,1-AO103/AO5,0) -> 0.86261231 | AP89: =+AO89+($B$86-AO89)*$B$85 -> 0.8669817 | AQ89: =+AP89+($B$86-AP89)*$B$85 -> 0.87113261 | AR89: =+AQ89+($B$86-AQ89)*$B$85 -> 0.87507598 | AS89: =+AR89+($B$86-AR89)*$B$85 -> 0.87882218 | AT89: =+AS89+($B$86-AS89)*$B$85 -> 0.88238107 | AU89: =+AT89+($B$86-AT89)*$B$85 -> 0.88576202 | AV89: =+AU89+($B$86-AU89)*$B$85 -> 0.88897392 | AW89: =+AV89+($B$86-AV89)*$B$85 -> 0.89202522 | ... CL89: =+CK89+($B$86-CK89)*$B$85 -> 0.94292206
A90: Japan | C90: from baseline | S90: =+S88 -> 0 | T90: =+T88 -> 0 | U90: =+U88 -> 0 | W90: =+IF(W104<90,1-W104/W6,0) -> 0.25706963 | X90: =+IF(X104<90,1-X104/X6,0) -> 0.29303675 | Y90: =+IF(Y104<90,1-Y104/Y6,0) -> 0.28571092 | Z90: =+IF(Z104<90,1-Z104/Z6,0) -> 0.31264862 | AA90: =+IF(AA104<90,1-AA104/AA6,0) -> 0.38482974 | AB90: =+IF(AB104<90,1-AB104/AB6,0) -> 0.44166012 | AC90: =+IF(AC104<90,1-AC104/AC6,0) -> 0.50080659 | AD90: =+IF(AD104<90,1-AD104/AD6,0) -> 0.56910601 | ... AO90: =+IF(AO104<90,1-AO104/AO6,0) -> 0.83958793 | AP90: =+AO90+($B$86-AO90)*$B$85 -> 0.84510854 | AQ90: =+AP90+($B$86-AP90)*$B$85 -> 0.85035311 | AR90: =+AQ90+($B$86-AQ90)*$B$85 -> 0.85533545 | AS90: =+AR90+($B$86-AR90)*$B$85 -> 0.86006868 | AT90: =+AS90+($B$86-AS90)*$B$85 -> 0.86456525 | AU90: =+AT90+($B$86-AT90)*$B$85 -> 0.86883699 | AV90: =+AU90+($B$86-AU90)*$B$85 -> 0.87289514 | AW90: =+AV90+($B$86-AV90)*$B$85 -> 0.87675038 | ... CL90: =+CK90+($B$86-CK90)*$B$85 -> 0.94105721
A91: Russia | C91: from baseline | S91: =+(IF(R73>0,$B$85,0)*($B$86-R91))+R91 -> 0 | T91: =+(IF(S73>0,$B$85,0)*($B$86-S91))+S91 -> 0.0475 | U91: =+(IF(T73>0,$B$85,0)*($B$86-T91))+T91 -> 0.092625 | W91: =+IF(W105<90,1-W105/W7,0) -> -0.43585279 | X91: =+IF(X105<90,1-X105/X7,0) -> -0.53554092 | Y91: =+IF(Y105<90,1-Y105/Y7,0) -> -0.50015496 | Z91: =+IF(Z105<90,1-Z105/Z7,0) -> -0.414013 | AA91: =+IF(AA105<90,1-AA105/AA7,0) -> -0.23765321 | AB91: =+IF(AB105<90,1-AB105/AB7,0) -> -0.098579132 | AC91: =+IF(AC105<90,1-AC105/AC7,0) -> 0.054062894 | AD91: =+IF(AD105<90,1-AD105/AD7,0) -> 0.21363427 | ... AO91: =+IF(AO105<90,1-AO105/AO7,0) -> 0.73750875 | AP91: =+AO91+($B$86-AO91)*$B$85 -> 0.74813331 | AQ91: =+AP91+($B$86-AP91)*$B$85 -> 0.75822664 | AR91: =+AQ91+($B$86-AQ91)*$B$85 -> 0.76781531 | AS91: =+AR91+($B$86-AR91)*$B$85 -> 0.77692455 | AT91: =+AS91+($B$86-AS91)*$B$85 -> 0.78557832 | AU91: =+AT91+($B$86-AT91)*$B$85 -> 0.7937994 | AV91: =+AU91+($B$86-AU91)*$B$85 -> 0.80160943 | AW91: =+AV91+($B$86-AV91)*$B$85 -> 0.80902896 | ... CL91: =+CK91+($B$86-CK91)*$B$85 -> 0.93278933
A92: Eurasia | S92: =+MIN(IF(R74>0,$B$85+R92,0),$B$86) -> 0 | T92: =+MIN(IF(S74>0,$B$85+S92,0),$B$86) -> 0 | U92: =+MIN(IF(T74>0,$B$85+T92,0),$B$86) -> 0 | W92: =+IF(W106<90,1-W106/W8,0) -> -0.75211228 | X92: =+IF(X106<90,1-X106/X8,0) -> -1.1106022 | Y92: =+IF(Y106<90,1-Y106/Y8,0) -> -0.98612997 | Z92: =+IF(Z106<90,1-Z106/Z8,0) -> -0.80323152 | AA92: =+IF(AA106<90,1-AA106/AA8,0) -> -0.52680282 | AB92: =+IF(AB106<90,1-AB106/AB8,0) -> -0.31099554 | AC92: =+IF(AC106<90,1-AC106/AC8,0) -> -0.099530081 | AD92: =+IF(AD106<90,1-AD106/AD8,0) -> 0.10968352 | ... AO92: =+IF(AO106<90,1-AO106/AO8,0) -> 0.74732561 | AP92: =+AO92+($B$86-AO92)*$B$85 -> 0.75745933 | AQ92: =+AP92+($B$86-AP92)*$B$85 -> 0.76708636 | AR92: =+AQ92+($B$86-AQ92)*$B$85 -> 0.77623204 | AS92: =+AR92+($B$86-AR92)*$B$85 -> 0.78492044 | AT92: =+AS92+($B$86-AS92)*$B$85 -> 0.79317442 | AU92: =+AT92+($B$86-AT92)*$B$85 -> 0.8010157 | AV92: =+AU92+($B$86-AU92)*$B$85 -> 0.80846491 | AW92: =+AV92+($B$86-AV92)*$B$85 -> 0.81554167 | ... CL92: =+CK92+($B$86-CK92)*$B$85 -> 0.93358445
